Workbook

Sheet 信息总览
A1: 基本信息 | C1: 版本编号：v5 | H1: 备注：85届赛季初期名单v5，核对消费，包括交易，db变化，成长，选秀，解约，消费，随潜，有错联系大直塞报错
A2: 届数 | B2: 85 | D2: 序号 | E2: 级别 | F2: 球队名 | G2: 主教 | H2: 球队人数 | I2: 门将人数 | J2: 工资 | K2: 额外工资 | L2: 税后 | M2: 最终工资 | N2: 8M | O2: 7M | P2: 伪名 | Q2: 总身价 | R2: 平均身价 | S2: 平均CA | T2: 平均PA | U2: 成长总计 | V2: 备注
A3: 本版首届 | B3: 84 | C3: FLA | D3: 1 | E3: 超级 | F3: =C3 -> FLA | G3: 星星 | H3: =COUNTIF(联赛名单!L:L,信息总览!F3) -> 17 | I3: =COUNTIFS(联赛名单!L:L,信息总览!F3,联赛名单!J:J,"GK") -> 2 | J3: =SUMIF(联赛名单!L:L,信息总览!F3,联赛名单!U:U) -> 8.495 | L3: =IF(J3+K3-$B$5>0.3,"拍卖",IF(J3+K3>$B$5,(J3+K3-$B$5)*10+J3,J3+K3)) -> 8.495 | M3: =IF(L3<8,8,L3) -> 8.495 | N3: =COUNTIFS(联赛名单!L:L,信息总览!F3,联赛名单!W:W,"8M") -> 0 | O3: =COUNTIFS(联赛名单!L:L,信息总览!F3,联赛名单!W:W,"7M") -> 2 | P3: =COUNTIFS(联赛名单!L:L,信息总览!F3,联赛名单!W:W,"伪名") -> 5 | Q3: =SUMIF(联赛名单!L:L,信息总览!F3,联赛名单!S:S) -> 87.5 | R3: =Q3/H3 -> 5.1470588 | S3: =SUMIF(联赛名单!L:L,信息总览!F3,联赛名单!G:G)/H3 -> 149.41176 | T3: =SUMIF(联赛名单!L:L,信息总览!F3,联赛名单!I:I)/H3 -> 157.58824 | U3: =SUMIF(联赛名单!L:L,信息总览!F3,联赛名单!G:G)-SUMIF(联赛名单!L:L,信息总览!F3,联赛名单!F:F) -> 59
A4: 成长年龄上限 | B4: =IF(B2-B3>2,23,IF(B2-B3=1,24,25)) -> 24 | C4: Aston Villa | D4: 2 | E4: 超级 | F4: =C4 -> Aston Villa | G4: e指导 | H4: =COUNTIF(联赛名单!L:L,信息总览!F4) -> 20 | I4: =COUNTIFS(联赛名单!L:L,信息总览!F4,联赛名单!J:J,"GK") -> 2 | J4: =SUMIF(联赛名单!L:L,信息总览!F4,联赛名单!U:U) -> 9.22 | L4: =IF(J4+K4-$B$5>0.3,"拍卖",IF(J4+K4>$B$5,(J4+K4-$B$5)*10+J4,J4+K4)) -> 9.22 | M4: =IF(L4<8,8,L4) -> 9.22 | N4: =COUNTIFS(联赛名单!L:L,信息总览!F4,联赛名单!W:W,"8M") -> 1 | O4: =COUNTIFS(联赛名单!L:L,信息总览!F4,联赛名单!W:W,"7M") -> 0 | P4: =COUNTIFS(联赛名单!L:L,信息总览!F4,联赛名单!W:W,"伪名") -> 3 | Q4: =SUMIF(联赛名单!L:L,信息总览!F4,联赛名单!S:S) -> 100 | R4: =Q4/H4 -> 5 | S4: =SUMIF(联赛名单!L:L,信息总览!F4,联赛名单!G:G)/H4 -> 143.55 | T4: =SUMIF(联赛名单!L:L,信息总览!F4,联赛名单!I:I)/H4 -> 157.7 | U4: =SUMIF(联赛名单!L:L,信息总览!F4,联赛名单!G:G)-SUMIF(联赛名单!L:L,信息总览!F4,联赛名单!F:F) -> 78
A5: 超级级工资帽 | B5: 9.4 | C5: Barcelona | D5: 3 | E5: 超级 | F5: =C5 -> Barcelona | G5: cyrus | H5: =COUNTIF(联赛名单!L:L,信息总览!F5) -> 20 | I5: =COUNTIFS(联赛名单!L:L,信息总览!F5,联赛名单!J:J,"GK") -> 2 | J5: =SUMIF(联赛名单!L:L,信息总览!F5,联赛名单!U:U) -> 9.25 | L5: =IF(J5+K5-$B$5>0.3,"拍卖",IF(J5+K5>$B$5,(J5+K5-$B$5)*10+J5,J5+K5)) -> 9.25 | M5: =IF(L5<8,8,L5) -> 9.25 | N5: =COUNTIFS(联赛名单!L:L,信息总览!F5,联赛名单!W:W,"8M") -> 1 | O5: =COUNTIFS(联赛名单!L:L,信息总览!F5,联赛名单!W:W,"7M") -> 2 | P5: =COUNTIFS(联赛名单!L:L,信息总览!F5,联赛名单!W:W,"伪名") -> 3 | Q5: =SUMIF(联赛名单!L:L,信息总览!F5,联赛名单!S:S) -> 100 | R5: =Q5/H5 -> 5 | S5: =SUMIF(联赛名单!L:L,信息总览!F5,联赛名单!G:G)/H5 -> 144.75 | T5: =SUMIF(联赛名单!L:L,信息总览!F5,联赛名单!I:I)/H5 -> 157.95 | U5: =SUMIF(联赛名单!L:L,信息总览!F5,联赛名单!G:G)-SUMIF(联赛名单!L:L,信息总览!F5,联赛名单!F:F) -> 103
A6: 甲级级工资帽 | B6: 8.9 | C6: Bayer 04 | D6: 4 | E6: 超级 | F6: =C6 -> Bayer 04 | G6: AX | H6: =COUNTIF(联赛名单!L:L,信息总览!F6) -> 19 | I6: =COUNTIFS(联赛名单!L:L,信息总览!F6,联赛名单!J:J,"GK") -> 2 | J6: =SUMIF(联赛名单!L:L,信息总览!F6,联赛名单!U:U) -> 8.53 | L6: =IF(J6+K6-$B$5>0.3,"拍卖",IF(J6+K6>$B$5,(J6+K6-$B$5)*10+J6,J6+K6)) -> 8.53 | M6: =IF(L6<8,8,L6) -> 8.53 | N6: =COUNTIFS(联赛名单!L:L,信息总览!F6,联赛名单!W:W,"8M") -> 1 | O6: =COUNTIFS(联赛名单!L:L,信息总览!F6,联赛名单!W:W,"7M") -> 1 | P6: =COUNTIFS(联赛名单!L:L,信息总览!F6,联赛名单!W:W,"伪名") -> 1 | Q6: =SUMIF(联赛名单!L:L,信息总览!F6,联赛名单!S:S) -> 98 | R6: =Q6/H6 -> 5.1578947 | S6: =SUMIF(联赛名单!L:L,信息总览!F6,联赛名单!G:G)/H6 -> 147.15789 | T6: =SUMIF(联赛名单!L:L,信息总览!F6,联赛名单!I:I)/H6 -> 158.94737 | U6: =SUMIF(联赛名单!L:L,信息总览!F6,联赛名单!G:G)-SUMIF(联赛名单!L:L,信息总览!F6,联赛名单!F:F) -> 39
A7: 乙级级工资帽 | B7: 8.6 | C7: Nottm Forest | D7: 5 | E7: 超级 | F7: =C7 -> Nottm Forest | G7: 南国 | H7: =COUNTIF(联赛名单!L:L,信息总览!F7) -> 17 | I7: =COUNTIFS(联赛名单!L:L,信息总览!F7,联赛名单!J:J,"GK") -> 2 | J7: =SUMIF(联赛名单!L:L,信息总览!F7,联赛名单!U:U) -> 9.37 | L7: =IF(J7+K7-$B$5>0.3,"拍卖",IF(J7+K7>$B$5,(J7+K7-$B$5)*10+J7,J7+K7)) -> 9.37 | M7: =IF(L7<8,8,L7) -> 9.37 | N7: =COUNTIFS(联赛名单!L:L,信息总览!F7,联赛名单!W:W,"8M") -> 1 | O7: =COUNTIFS(联赛名单!L:L,信息总览!F7,联赛名单!W:W,"7M") -> 2 | P7: =COUNTIFS(联赛名单!L:L,信息总览!F7,联赛名单!W:W,"伪名") -> 3 | Q7: =SUMIF(联赛名单!L:L,信息总览!F7,联赛名单!S:S) -> 92 | R7: =Q7/H7 -> 5.4117647 | S7: =SUMIF(联赛名单!L:L,信息总览!F7,联赛名单!G:G)/H7 -> 148.52941 | T7: =SUMIF(联赛名单!L:L,信息总览!F7,联赛名单!I:I)/H7 -> 159.94118 | U7: =SUMIF(联赛名单!L:L,信息总览!F7,联赛名单!G:G)-SUMIF(联赛名单!L:L,信息总览!F7,联赛名单!F:F) -> 95
A8: 总工资 | B8: =SUM(M3:M20,M23:M40,M43:M60) -> 446.705 | C8: Borussia Dortmund | D8: 6 | E8: 超级 | F8: =C8 -> Borussia Dortmund | G8: 长臂猿 | H8: =COUNTIF(联赛名单!L:L,信息总览!F8) -> 18 | I8: =COUNTIFS(联赛名单!L:L,信息总览!F8,联赛名单!J:J,"GK") -> 2 | J8: =SUMIF(联赛名单!L:L,信息总览!F8,联赛名单!U:U) -> 9.375 | L8: =IF(J8+K8-$B$5>0.3,"拍卖",IF(J8+K8>$B$5,(J8+K8-$B$5)*10+J8,J8+K8)) -> 9.375 | M8: =IF(L8<8,8,L8) -> 9.375 | N8: =COUNTIFS(联赛名单!L:L,信息总览!F8,联赛名单!W:W,"8M") -> 1 | O8: =COUNTIFS(联赛名单!L:L,信息总览!F8,联赛名单!W:W,"7M") -> 2 | P8: =COUNTIFS(联赛名单!L:L,信息总览!F8,联赛名单!W:W,"伪名") -> 2 | Q8: =SUMIF(联赛名单!L:L,信息总览!F8,联赛名单!S:S) -> 98.5 | R8: =Q8/H8 -> 5.4722222 | S8: =SUMIF(联赛名单!L:L,信息总览!F8,联赛名单!G:G)/H8 -> 152.5 | T8: =SUMIF(联赛名单!L:L,信息总览!F8,联赛名单!I:I)/H8 -> 160.5 | U8: =SUMIF(联赛名单!L:L,信息总览!F8,联赛名单!G:G)-SUMIF(联赛名单!L:L,信息总览!F8,联赛名单!F:F) -> 56
A9: 总平均工资 | B9: =B8/54 -> 8.2723148 | C9: Everton | D9: 7 | E9: 超级 | F9: =C9 -> Everton | G9: 一笑 | H9: =COUNTIF(联赛名单!L:L,信息总览!F9) -> 20 | I9: =COUNTIFS(联赛名单!L:L,信息总览!F9,联赛名单!J:J,"GK") -> 2 | J9: =SUMIF(联赛名单!L:L,信息总览!F9,联赛名单!U:U) -> 6.485 | L9: =IF(J9+K9-$B$5>0.3,"拍卖",IF(J9+K9>$B$5,(J9+K9-$B$5)*10+J9,J9+K9)) -> 6.485 | M9: =IF(L9<8,8,L9) -> 8 | N9: =COUNTIFS(联赛名单!L:L,信息总览!F9,联赛名单!W:W,"8M") -> 1 | O9: =COUNTIFS(联赛名单!L:L,信息总览!F9,联赛名单!W:W,"7M") -> 0 | P9: =COUNTIFS(联赛名单!L:L,信息总览!F9,联赛名单!W:W,"伪名") -> 0 | Q9: =SUMIF(联赛名单!L:L,信息总览!F9,联赛名单!S:S) -> 82.5 | R9: =Q9/H9 -> 4.125 | S9: =SUMIF(联赛名单!L:L,信息总览!F9,联赛名单!G:G)/H9 -> 140.2 | T9: =SUMIF(联赛名单!L:L,信息总览!F9,联赛名单!I:I)/H9 -> 150.1 | U9: =SUMIF(联赛名单!L:L,信息总览!F9,联赛名单!G:G)-SUMIF(联赛名单!L:L,信息总览!F9,联赛名单!F:F) -> 55
A10: 总身价 | B10: =SUM(Q23:Q40,Q3:Q20,Q43:Q60) -> 4877.5 | C10: Inter | D10: 8 | E10: 超级 | F10: =C10 -> Inter | G10: 宝哥 | H10: =COUNTIF(联赛名单!L:L,信息总览!F10) -> 18 | I10: =COUNTIFS(联赛名单!L:L,信息总览!F10,联赛名单!J:J,"GK") -> 2 | J10: =SUMIF(联赛名单!L:L,信息总览!F10,联赛名单!U:U) -> 9.425 | L10: =IF(J10+K10-$B$5>0.3,"拍卖",IF(J10+K10>$B$5,(J10+K10-$B$5)*10+J10,J10+K10)) -> 9.675 | M10: =IF(L10<8,8,L10) -> 9.675 | N10: =COUNTIFS(联赛名单!L:L,信息总览!F10,联赛名单!W:W,"8M") -> 1 | O10: =COUNTIFS(联赛名单!L:L,信息总览!F10,联赛名单!W:W,"7M") -> 2 | P10: =COUNTIFS(联赛名单!L:L,信息总览!F10,联赛名单!W:W,"伪名") -> 0 | Q10: =SUMIF(联赛名单!L:L,信息总览!F10,联赛名单!S:S) -> 97.5 | R10: =Q10/H10 -> 5.4166667 | S10: =SUMIF(联赛名单!L:L,信息总览!F10,联赛名单!G:G)/H10 -> 150.72222 | T10: =SUMIF(联赛名单!L:L,信息总览!F10,联赛名单!I:I)/H10 -> 159.05556 | U10: =SUMIF(联赛名单!L:L,信息总览!F10,联赛名单!G:G)-SUMIF(联赛名单!L:L,信息总览!F10,联赛名单!F:F) -> 39
A11: 总平均身价 | B11: =SUM(R3:R20,R23:R40,R43:R60) -> 261.35877 | C11: Juventus | D11: 9 | E11: 超级 | F11: =C11 -> Juventus | G11: 幽灵 | H11: =COUNTIF(联赛名单!L:L,信息总览!F11) -> 18 | I11: =COUNTIFS(联赛名单!L:L,信息总览!F11,联赛名单!J:J,"GK") -> 2 | J11: =SUMIF(联赛名单!L:L,信息总览!F11,联赛名单!U:U) -> 9.38 | L11: =IF(J11+K11-$B$5>0.3,"拍卖",IF(J11+K11>$B$5,(J11+K11-$B$5)*10+J11,J11+K11)) -> 9.38 | M11: =IF(L11<8,8,L11) -> 9.38 | N11: =COUNTIFS(联赛名单!L:L,信息总览!F11,联赛名单!W:W,"8M") -> 0 | O11: =COUNTIFS(联赛名单!L:L,信息总览!F11,联赛名单!W:W,"7M") -> 2 | P11: =COUNTIFS(联赛名单!L:L,信息总览!F11,联赛名单!W:W,"伪名") -> 3 | Q11: =SUMIF(联赛名单!L:L,信息总览!F11,联赛名单!S:S) -> 98.5 | R11: =Q11/H11 -> 5.4722222 | S11: =SUMIF(联赛名单!L:L,信息总览!F11,联赛名单!G:G)/H11 -> 151.66667 | T11: =SUMIF(联赛名单!L:L,信息总览!F11,联赛名单!I:I)/H11 -> 158.55556 | U11: =SUMIF(联赛名单!L:L,信息总览!F11,联赛名单!G:G)-SUMIF(联赛名单!L:L,信息总览!F11,联赛名单!F:F) -> 68
A12: 身价极差 | B12: =MAX(Q3:Q20,Q23:Q40,Q43:Q60)-MIN(Q3:Q20,Q23:Q40,Q43:Q60) -> 30 | C12: Liverpool | D12: 10 | E12: 超级 | F12: =C12 -> Liverpool | G12: 简单 | H12: =COUNTIF(联赛名单!L:L,信息总览!F12) -> 18 | I12: =COUNTIFS(联赛名单!L:L,信息总览!F12,联赛名单!J:J,"GK") -> 2 | J12: =SUMIF(联赛名单!L:L,信息总览!F12,联赛名单!U:U) -> 9.41 | L12: =IF(J12+K12-$B$5>0.3,"拍卖",IF(J12+K12>$B$5,(J12+K12-$B$5)*10+J12,J12+K12)) -> 9.51 | M12: =IF(L12<8,8,L12) -> 9.51 | N12: =COUNTIFS(联赛名单!L:L,信息总览!F12,联赛名单!W:W,"8M") -> 0 | O12: =COUNTIFS(联赛名单!L:L,信息总览!F12,联赛名单!W:W,"7M") -> 0 | P12: =COUNTIFS(联赛名单!L:L,信息总览!F12,联赛名单!W:W,"伪名") -> 6 | Q12: =SUMIF(联赛名单!L:L,信息总览!F12,联赛名单!S:S) -> 99 | R12: =Q12/H12 -> 5.5 | S12: =SUMIF(联赛名单!L:L,信息总览!F12,联赛名单!G:G)/H12 -> 150.88889 | T12: =SUMIF(联赛名单!L:L,信息总览!F12,联赛名单!I:I)/H12 -> 161.11111 | U12: =SUMIF(联赛名单!L:L,信息总览!F12,联赛名单!G:G)-SUMIF(联赛名单!L:L,信息总览!F12,联赛名单!F:F) -> 97
A13: 总平均CA | B13: =SUM(S3:S20,S23:S40,S43:S60) -> 7637.9624 | C13: Man UFC | D13: 11 | E13: 超级 | F13: =C13 -> Man UFC | G13: 包子 | H13: =COUNTIF(联赛名单!L:L,信息总览!F13) -> 19 | I13: =COUNTIFS(联赛名单!L:L,信息总览!F13,联赛名单!J:J,"GK") -> 2 | J13: =SUMIF(联赛名单!L:L,信息总览!F13,联赛名单!U:U) -> 8.84 | L13: =IF(J13+K13-$B$5>0.3,"拍卖",IF(J13+K13>$B$5,(J13+K13-$B$5)*10+J13,J13+K13)) -> 8.84 | M13: =IF(L13<8,8,L13) -> 8.84 | N13: =COUNTIFS(联赛名单!L:L,信息总览!F13,联赛名单!W:W,"8M") -> 1 | O13: =COUNTIFS(联赛名单!L:L,信息总览!F13,联赛名单!W:W,"7M") -> 0 | P13: =COUNTIFS(联赛名单!L:L,信息总览!F13,联赛名单!W:W,"伪名") -> 2 | Q13: =SUMIF(联赛名单!L:L,信息总览!F13,联赛名单!S:S) -> 97 | R13: =Q13/H13 -> 5.1052632 | S13: =SUMIF(联赛名单!L:L,信息总览!F13,联赛名单!G:G)/H13 -> 148 | T13: =SUMIF(联赛名单!L:L,信息总览!F13,联赛名单!I:I)/H13 -> 159.42105 | U13: =SUMIF(联赛名单!L:L,信息总览!F13,联赛名单!G:G)-SUMIF(联赛名单!L:L,信息总览!F13,联赛名单!F:F) -> 84
A14: CA极差 | B14: =MAX(S3:S20,S23:S40,S43:S60)-MIN(S3:S20,S23:S40,S43:S60) -> 31.4 | C14: Southampton | D14: 12 | E14: 超级 | F14: =C14 -> Southampton | G14: 李指导 | H14: =COUNTIF(联赛名单!L:L,信息总览!F14) -> 20 | I14: =COUNTIFS(联赛名单!L:L,信息总览!F14,联赛名单!J:J,"GK") -> 2 | J14: =SUMIF(联赛名单!L:L,信息总览!F14,联赛名单!U:U) -> 8.265 | L14: =IF(J14+K14-$B$5>0.3,"拍卖",IF(J14+K14>$B$5,(J14+K14-$B$5)*10+J14,J14+K14)) -> 8.265 | M14: =IF(L14<8,8,L14) -> 8.265 | N14: =COUNTIFS(联赛名单!L:L,信息总览!F14,联赛名单!W:W,"8M") -> 1 | O14: =COUNTIFS(联赛名单!L:L,信息总览!F14,联赛名单!W:W,"7M") -> 0 | P14: =COUNTIFS(联赛名单!L:L,信息总览!F14,联赛名单!W:W,"伪名") -> 2 | Q14: =SUMIF(联赛名单!L:L,信息总览!F14,联赛名单!S:S) -> 94.5 | R14: =Q14/H14 -> 4.725 | S14: =SUMIF(联赛名单!L:L,信息总览!F14,联赛名单!G:G)/H14 -> 142.4 | T14: =SUMIF(联赛名单!L:L,信息总览!F14,联赛名单!I:I)/H14 -> 152.45 | U14: =SUMIF(联赛名单!L:L,信息总览!F14,联赛名单!G:G)-SUMIF(联赛名单!L:L,信息总览!F14,联赛名单!F:F) -> 104
A15: 总平均PA | B15: =SUM(T3:T20,T23:T40,T43:T60) -> 8472.0481 | C15: Tottenham | D15: 13 | E15: 超级 | F15: =C15 -> Tottenham | G15: 小R | H15: =COUNTIF(联赛名单!L:L,信息总览!F15) -> 20 | I15: =COUNTIFS(联赛名单!L:L,信息总览!F15,联赛名单!J:J,"GK") -> 2 | J15: =SUMIF(联赛名单!L:L,信息总览!F15,联赛名单!U:U) -> 8.945 | L15: =IF(J15+K15-$B$5>0.3,"拍卖",IF(J15+K15>$B$5,(J15+K15-$B$5)*10+J15,J15+K15)) -> 8.945 | M15: =IF(L15<8,8,L15) -> 8.945 | N15: =COUNTIFS(联赛名单!L:L,信息总览!F15,联赛名单!W:W,"8M") -> 1 | O15: =COUNTIFS(联赛名单!L:L,信息总览!F15,联赛名单!W:W,"7M") -> 0 | P15: =COUNTIFS(联赛名单!L:L,信息总览!F15,联赛名单!W:W,"伪名") -> 3 | Q15: =SUMIF(联赛名单!L:L,信息总览!F15,联赛名单!S:S) -> 100.5 | R15: =Q15/H15 -> 5.025 | S15: =SUMIF(联赛名单!L:L,信息总览!F15,联赛名单!G:G)/H15 -> 144.7 | T15: =SUMIF(联赛名单!L:L,信息总览!F15,联赛名单!I:I)/H15 -> 157.6 | U15: =SUMIF(联赛名单!L:L,信息总览!F15,联赛名单!G:G)-SUMIF(联赛名单!L:L,信息总览!F15,联赛名单!F:F) -> 116
A16: PA极差 | B16: =MAX(T3:T20,T23:T40,T43:T60)-MIN(T3:T20,T23:T40,T43:T60) -> 12.981424 | C16: FC Bayern | D16: 14 | E16: 超级 | F16: =C16 -> FC Bayern | G16: 杰拉德 | H16: =COUNTIF(联赛名单!L:L,信息总览!F16) -> 20 | I16: =COUNTIFS(联赛名单!L:L,信息总览!F16,联赛名单!J:J,"GK") -> 2 | J16: =SUMIF(联赛名单!L:L,信息总览!F16,联赛名单!U:U) -> 8.575 | L16: =IF(J16+K16-$B$5>0.3,"拍卖",IF(J16+K16>$B$5,(J16+K16-$B$5)*10+J16,J16+K16)) -> 8.575 | M16: =IF(L16<8,8,L16) -> 8.575 | N16: =COUNTIFS(联赛名单!L:L,信息总览!F16,联赛名单!W:W,"8M") -> 1 | O16: =COUNTIFS(联赛名单!L:L,信息总览!F16,联赛名单!W:W,"7M") -> 0 | P16: =COUNTIFS(联赛名单!L:L,信息总览!F16,联赛名单!W:W,"伪名") -> 3 | Q16: =SUMIF(联赛名单!L:L,信息总览!F16,联赛名单!S:S) -> 94.5 | R16: =Q16/H16 -> 4.725 | S16: =SUMIF(联赛名单!L:L,信息总览!F16,联赛名单!G:G)/H16 -> 138.05 | T16: =SUMIF(联赛名单!L:L,信息总览!F16,联赛名单!I:I)/H16 -> 158.45 | U16: =SUMIF(联赛名单!L:L,信息总览!F16,联赛名单!G:G)-SUMIF(联赛名单!L:L,信息总览!F16,联赛名单!F:F) -> 104
A17: 总平均成长 | B17: =SUM(U43,U43:U60,U23:U40,U3:U20)/54 -> 83.277778 | C17: R. Madrid | D17: 15 | E17: 超级 | F17: =C17 -> R. Madrid | G17: 小刑 | H17: =COUNTIF(联赛名单!L:L,信息总览!F17) -> 17 | I17: =COUNTIFS(联赛名单!L:L,信息总览!F17,联赛名单!J:J,"GK") -> 2 | J17: =SUMIF(联赛名单!L:L,信息总览!F17,联赛名单!U:U) -> 9.34 | L17: =IF(J17+K17-$B$5>0.3,"拍卖",IF(J17+K17>$B$5,(J17+K17-$B$5)*10+J17,J17+K17)) -> 9.34 | M17: =IF(L17<8,8,L17) -> 9.34 | N17: =COUNTIFS(联赛名单!L:L,信息总览!F17,联赛名单!W:W,"8M") -> 1 | O17: =COUNTIFS(联赛名单!L:L,信息总览!F17,联赛名单!W:W,"7M") -> 1 | P17: =COUNTIFS(联赛名单!L:L,信息总览!F17,联赛名单!W:W,"伪名") -> 3 | Q17: =SUMIF(联赛名单!L:L,信息总览!F17,联赛名单!S:S) -> 94 | R17: =Q17/H17 -> 5.5294118 | S17: =SUMIF(联赛名单!L:L,信息总览!F17,联赛名单!G:G)/H17 -> 151.70588 | T17: =SUMIF(联赛名单!L:L,信息总览!F17,联赛名单!I:I)/H17 -> 160.64706 | U17: =SUMIF(联赛名单!L:L,信息总览!F17,联赛名单!G:G)-SUMIF(联赛名单!L:L,信息总览!F17,联赛名单!F:F) -> 106
A18: 全新工资系数 | C18: Schalke 04 | D18: 16 | E18: 超级 | F18: =C18 -> Schalke 04 | G18: 梅尔 | H18: =COUNTIF(联赛名单!L:L,信息总览!F18) -> 19 | I18: =COUNTIFS(联赛名单!L:L,信息总览!F18,联赛名单!J:J,"GK") -> 2 | J18: =SUMIF(联赛名单!L:L,信息总览!F18,联赛名单!U:U) -> 7.895 | L18: =IF(J18+K18-$B$5>0.3,"拍卖",IF(J18+K18>$B$5,(J18+K18-$B$5)*10+J18,J18+K18)) -> 7.895 | M18: =IF(L18<8,8,L18) -> 8 | N18: =COUNTIFS(联赛名单!L:L,信息总览!F18,联赛名单!W:W,"8M") -> 0 | O18: =COUNTIFS(联赛名单!L:L,信息总览!F18,联赛名单!W:W,"7M") -> 1 | P18: =COUNTIFS(联赛名单!L:L,信息总览!F18,联赛名单!W:W,"伪名") -> 2 | Q18: =SUMIF(联赛名单!L:L,信息总览!F18,联赛名单!S:S) -> 92.5 | R18: =Q18/H18 -> 4.8684211 | S18: =SUMIF(联赛名单!L:L,信息总览!F18,联赛名单!G:G)/H18 -> 143.10526 | T18: =SUMIF(联赛名单!L:L,信息总览!F18,联赛名单!I:I)/H18 -> 154.26316 | U18: =SUMIF(联赛名单!L:L,信息总览!F18,联赛名单!G:G)-SUMIF(联赛名单!L:L,信息总览!F18,联赛名单!F:F) -> 70
A19: 8M名额 | B19: 1.5 | C19: Napoli | D19: 17 | E19: 超级 | F19: =C19 -> Napoli | G19: 大头 | H19: =COUNTIF(联赛名单!L:L,信息总览!F19) -> 20 | I19: =COUNTIFS(联赛名单!L:L,信息总览!F19,联赛名单!J:J,"GK") -> 2 | J19: =SUMIF(联赛名单!L:L,信息总览!F19,联赛名单!U:U) -> 8.29 | L19: =IF(J19+K19-$B$5>0.3,"拍卖",IF(J19+K19>$B$5,(J19+K19-$B$5)*10+J19,J19+K19)) -> 8.29 | M19: =IF(L19<8,8,L19) -> 8.29 | N19: =COUNTIFS(联赛名单!L:L,信息总览!F19,联赛名单!W:W,"8M") -> 0 | O19: =COUNTIFS(联赛名单!L:L,信息总览!F19,联赛名单!W:W,"7M") -> 1 | P19: =COUNTIFS(联赛名单!L:L,信息总览!F19,联赛名单!W:W,"伪名") -> 1 | Q19: =SUMIF(联赛名单!L:L,信息总览!F19,联赛名单!S:S) -> 99 | R19: =Q19/H19 -> 4.95 | S19: =SUMIF(联赛名单!L:L,信息总览!F19,联赛名单!G:G)/H19 -> 147.7 | T19: =SUMIF(联赛名单!L:L,信息总览!F19,联赛名单!I:I)/H19 -> 157.2 | U19: =SUMIF(联赛名单!L:L,信息总览!F19,联赛名单!G:G)-SUMIF(联赛名单!L:L,信息总览!F19,联赛名单!F:F) -> 55
A20: 7M名额 | B20: 1.3 | C20: Chelsea | D20: 18 | E20: 超级 | F20: =C20 -> Chelsea | G20: 无铭剑 | H20: =COUNTIF(联赛名单!L:L,信息总览!F20) -> 20 | I20: =COUNTIFS(联赛名单!L:L,信息总览!F20,联赛名单!J:J,"GK") -> 2 | J20: =SUMIF(联赛名单!L:L,信息总览!F20,联赛名单!U:U) -> 9.375 | L20: =IF(J20+K20-$B$5-0.1>0.3,"拍卖",IF(J20+K20>$B$5+0.1,(J20+K20-$B$5)*10+J20,J20+K20)) -> 9.375 | M20: =IF(L20<8,8,L20) -> 9.375 | N20: =COUNTIFS(联赛名单!L:L,信息总览!F20,联赛名单!W:W,"8M") -> 0 | O20: =COUNTIFS(联赛名单!L:L,信息总览!F20,联赛名单!W:W,"7M") -> 2 | P20: =COUNTIFS(联赛名单!L:L,信息总览!F20,联赛名单!W:W,"伪名") -> 3 | Q20: =SUMIF(联赛名单!L:L,信息总览!F20,联赛名单!S:S) -> 97.5 | R20: =Q20/H20 -> 4.875 | S20: =SUMIF(联赛名单!L:L,信息总览!F20,联赛名单!G:G)/H20 -> 143.25 | T20: =SUMIF(联赛名单!L:L,信息总览!F20,联赛名单!I:I)/H20 -> 159.3 | U20: =SUMIF(联赛名单!L:L,信息总览!F20,联赛名单!G:G)-SUMIF(联赛名单!L:L,信息总览!F20,联赛名单!F:F) -> 77 | V20: 额外0.1M工资帽
A21: 可成长名额 | B21: 1.1
A22: 非名PA6M | B22: 0.9
A23: 非名身价1M | B23: 1 | C23: A. Madrid | D23: 1 | E23: 甲级 | F23: =C23 -> A. Madrid | G23: dogking623 | H23: =COUNTIF(联赛名单!L:L,信息总览!F23) -> 19 | I23: =COUNTIFS(联赛名单!L:L,信息总览!F23,联赛名单!J:J,"GK") -> 2 | J23: =SUMIF(联赛名单!L:L,信息总览!F23,联赛名单!U:U) -> 7.85 | L23: =IF(J23+K23-$B$6>0.3,"拍卖",IF(J23+K23>$B$6,(J23+K23-$B$6)*10+J23,J23+K23)) -> 7.85 | M23: =IF(L23<7.5,7.5,L23) -> 7.85 | N23: =COUNTIFS(联赛名单!L:L,信息总览!F23,联赛名单!W:W,"8M") -> 1 | O23: =COUNTIFS(联赛名单!L:L,信息总览!F23,联赛名单!W:W,"7M") -> 0 | P23: =COUNTIFS(联赛名单!L:L,信息总览!F23,联赛名单!W:W,"伪名") -> 3 | Q23: =SUMIF(联赛名单!L:L,信息总览!F23,联赛名单!S:S) -> 87 | R23: =Q23/H23 -> 4.5789474 | S23: =SUMIF(联赛名单!L:L,信息总览!F23,联赛名单!G:G)/H23 -> 139.57895 | T23: =SUMIF(联赛名单!L:L,信息总览!F23,联赛名单!I:I)/H23 -> 154.31579 | U23: =SUMIF(联赛名单!L:L,信息总览!F23,联赛名单!G:G)-SUMIF(联赛名单!L:L,信息总览!F23,联赛名单!F:F) -> 93
A24: 非名其他 | B24: 0.7 | C24: AC Milan | D24: 2 | E24: 甲级 | F24: =C24 -> AC Milan | G24: 陈先生 | H24: =COUNTIF(联赛名单!L:L,信息总览!F24) -> 16 | I24: =COUNTIFS(联赛名单!L:L,信息总览!F24,联赛名单!J:J,"GK") -> 2 | J24: =SUMIF(联赛名单!L:L,信息总览!F24,联赛名单!U:U) -> 5.975 | L24: =IF(J24+K24-$B$6-0.1>0.3,"拍卖",IF(J24+K24>$B$6+0.1,(J24+K24-$B$6)*10+J24,J24+K24)) -> 5.975 | M24: =IF(L24<7.5,7.5,L24) -> 7.5 | N24: =COUNTIFS(联赛名单!L:L,信息总览!F24,联赛名单!W:W,"8M") -> 0 | O24: =COUNTIFS(联赛名单!L:L,信息总览!F24,联赛名单!W:W,"7M") -> 0 | P24: =COUNTIFS(联赛名单!L:L,信息总览!F24,联赛名单!W:W,"伪名") -> 2 | Q24: =SUMIF(联赛名单!L:L,信息总览!F24,联赛名单!S:S) -> 70.5 | R24: =Q24/H24 -> 4.40625 | S24: =SUMIF(联赛名单!L:L,信息总览!F24,联赛名单!G:G)/H24 -> 133.875 | T24: =SUMIF(联赛名单!L:L,信息总览!F24,联赛名单!I:I)/H24 -> 153.625 | U24: =SUMIF(联赛名单!L:L,信息总览!F24,联赛名单!G:G)-SUMIF(联赛名单!L:L,信息总览!F24,联赛名单!F:F) -> 24 | V24: 额外0.1M工资帽
A25: 注：名额GK系数为1 | C25: Hamburger Sport-Verein | D25: 3 | E25: 甲级 | F25: =C25 -> Hamburger Sport-Verein | G25: 小a | H25: =COUNTIF(联赛名单!L:L,信息总览!F25) -> 20 | I25: =COUNTIFS(联赛名单!L:L,信息总览!F25,联赛名单!J:J,"GK") -> 2 | J25: =SUMIF(联赛名单!L:L,信息总览!F25,联赛名单!U:U) -> 8.37 | L25: =IF(J25+K25-$B$6>0.3,"拍卖",IF(J25+K25>$B$6,(J25+K25-$B$6)*10+J25,J25+K25)) -> 8.37 | M25: =IF(L25<7.5,7.5,L25) -> 8.37 | N25: =COUNTIFS(联赛名单!L:L,信息总览!F25,联赛名单!W:W,"8M") -> 0 | O25: =COUNTIFS(联赛名单!L:L,信息总览!F25,联赛名单!W:W,"7M") -> 0 | P25: =COUNTIFS(联赛名单!L:L,信息总览!F25,联赛名单!W:W,"伪名") -> 5 | Q25: =SUMIF(联赛名单!L:L,信息总览!F25,联赛名单!S:S) -> 97 | R25: =Q25/H25 -> 4.85 | S25: =SUMIF(联赛名单!L:L,信息总览!F25,联赛名单!G:G)/H25 -> 144.85 | T25: =SUMIF(联赛名单!L:L,信息总览!F25,联赛名单!I:I)/H25 -> 156.15 | U25: =SUMIF(联赛名单!L:L,信息总览!F25,联赛名单!G:G)-SUMIF(联赛名单!L:L,信息总览!F25,联赛名单!F:F) -> 82
C26: A. Bilbao | D26: 4 | E26: 甲级 | F26: =C26 -> A. Bilbao | G26: 大V | H26: =COUNTIF(联赛名单!L:L,信息总览!F26) -> 17 | I26: =COUNTIFS(联赛名单!L:L,信息总览!F26,联赛名单!J:J,"GK") -> 2 | J26: =SUMIF(联赛名单!L:L,信息总览!F26,联赛名单!U:U) -> 8.775 | L26: =IF(J26+K26-$B$6>0.3,"拍卖",IF(J26+K26>$B$6,(J26+K26-$B$6)*10+J26,J26+K26)) -> 8.775 | M26: =IF(L26<7.5,7.5,L26) -> 8.775 | N26: =COUNTIFS(联赛名单!L:L,信息总览!F26,联赛名单!W:W,"8M") -> 1 | O26: =COUNTIFS(联赛名单!L:L,信息总览!F26,联赛名单!W:W,"7M") -> 1 | P26: =COUNTIFS(联赛名单!L:L,信息总览!F26,联赛名单!W:W,"伪名") -> 4 | Q26: =SUMIF(联赛名单!L:L,信息总览!F26,联赛名单!S:S) -> 88.5 | R26: =Q26/H26 -> 5.2058824 | S26: =SUMIF(联赛名单!L:L,信息总览!F26,联赛名单!G:G)/H26 -> 143.29412 | T26: =SUMIF(联赛名单!L:L,信息总览!F26,联赛名单!I:I)/H26 -> 161.82353 | U26: =SUMIF(联赛名单!L:L,信息总览!F26,联赛名单!G:G)-SUMIF(联赛名单!L:L,信息总览!F26,联赛名单!F:F) -> 149
C27: Celtic | D27: 5 | E27: 甲级 | F27: =C27 -> Celtic | G27: 天王 | H27: =COUNTIF(联赛名单!L:L,信息总览!F27) -> 19 | I27: =COUNTIFS(联赛名单!L:L,信息总览!F27,联赛名单!J:J,"GK") -> 2 | J27: =SUMIF(联赛名单!L:L,信息总览!F27,联赛名单!U:U) -> 8.625 | L27: =IF(J27+K27-$B$6>0.3,"拍卖",IF(J27+K27>$B$6,(J27+K27-$B$6)*10+J27,J27+K27)) -> 8.625 | M27: =IF(L27<7.5,7.5,L27) -> 8.625 | N27: =COUNTIFS(联赛名单!L:L,信息总览!F27,联赛名单!W:W,"8M") -> 0 | O27: =COUNTIFS(联赛名单!L:L,信息总览!F27,联赛名单!W:W,"7M") -> 1 | P27: =COUNTIFS(联赛名单!L:L,信息总览!F27,联赛名单!W:W,"伪名") -> 4 | Q27: =SUMIF(联赛名单!L:L,信息总览!F27,联赛名单!S:S) -> 95.5 | R27: =Q27/H27 -> 5.0263158 | S27: =SUMIF(联赛名单!L:L,信息总览!F27,联赛名单!G:G)/H27 -> 144.84211 | T27: =SUMIF(联赛名单!L:L,信息总览!F27,联赛名单!I:I)/H27 -> 157 | U27: =SUMIF(联赛名单!L:L,信息总览!F27,联赛名单!G:G)-SUMIF(联赛名单!L:L,信息总览!F27,联赛名单!F:F) -> 112
C28: RB Leipzig | D28: 6 | E28: 甲级 | F28: =C28 -> RB Leipzig | G28: 索夜 | H28: =COUNTIF(联赛名单!L:L,信息总览!F28) -> 20 | I28: =COUNTIFS(联赛名单!L:L,信息总览!F28,联赛名单!J:J,"GK") -> 2 | J28: =SUMIF(联赛名单!L:L,信息总览!F28,联赛名单!U:U) -> 7.615 | L28: =IF(J28+K28-$B$6>0.3,"拍卖",IF(J28+K28>$B$6,(J28+K28-$B$6)*10+J28,J28+K28)) -> 7.615 | M28: =IF(L28<7.5,7.5,L28) -> 7.615 | N28: =COUNTIFS(联赛名单!L:L,信息总览!F28,联赛名单!W:W,"8M") -> 1 | O28: =COUNTIFS(联赛名单!L:L,信息总览!F28,联赛名单!W:W,"7M") -> 0 | P28: =COUNTIFS(联赛名单!L:L,信息总览!F28,联赛名单!W:W,"伪名") -> 2 | Q28: =SUMIF(联赛名单!L:L,信息总览!F28,联赛名单!S:S) -> 94.5 | R28: =Q28/H28 -> 4.725 | S28: =SUMIF(联赛名单!L:L,信息总览!F28,联赛名单!G:G)/H28 -> 140.6 | T28: =SUMIF(联赛名单!L:L,信息总览!F28,联赛名单!I:I)/H28 -> 153.45 | U28: =SUMIF(联赛名单!L:L,信息总览!F28,联赛名单!G:G)-SUMIF(联赛名单!L:L,信息总览!F28,联赛名单!F:F) -> 126
C29: Sunderland | D29: 7 | E29: 甲级 | F29: =C29 -> Sunderland | G29: DTA | H29: =COUNTIF(联赛名单!L:L,信息总览!F29) -> 19 | I29: =COUNTIFS(联赛名单!L:L,信息总览!F29,联赛名单!J:J,"GK") -> 2 | J29: =SUMIF(联赛名单!L:L,信息总览!F29,联赛名单!U:U) -> 8.89 | L29: =IF(J29+K29-$B$6-0.1>0.3,"拍卖",IF(J29+K29>$B$6+0.1,(J29+K29-$B$6)*10+J29,J29+K29)) -> 8.89 | M29: =IF(L29<7.5,7.5,L29) -> 8.89 | N29: =COUNTIFS(联赛名单!L:L,信息总览!F29,联赛名单!W:W,"8M") -> 0 | O29: =COUNTIFS(联赛名单!L:L,信息总览!F29,联赛名单!W:W,"7M") -> 1 | P29: =COUNTIFS(联赛名单!L:L,信息总览!F29,联赛名单!W:W,"伪名") -> 4 | Q29: =SUMIF(联赛名单!L:L,信息总览!F29,联赛名单!S:S) -> 94 | R29: =Q29/H29 -> 4.9473684 | S29: =SUMIF(联赛名单!L:L,信息总览!F29,联赛名单!G:G)/H29 -> 144.15789 | T29: =SUMIF(联赛名单!L:L,信息总览!F29,联赛名单!I:I)/H29 -> 155.78947 | U29: =SUMIF(联赛名单!L:L,信息总览!F29,联赛名单!G:G)-SUMIF(联赛名单!L:L,信息总览!F29,联赛名单!F:F) -> 110 | V29: 额外0.1M工资帽
C30: West Ham | D30: 8 | E30: 甲级 | F30: =C30 -> West Ham | G30: heyes | H30: =COUNTIF(联赛名单!L:L,信息总览!F30) -> 19 | I30: =COUNTIFS(联赛名单!L:L,信息总览!F30,联赛名单!J:J,"GK") -> 2 | J30: =SUMIF(联赛名单!L:L,信息总览!F30,联赛名单!U:U) -> 7.51 | L30: =IF(J30+K30-$B$6>0.3,"拍卖",IF(J30+K30>$B$6,(J30+K30-$B$6)*10+J30,J30+K30)) -> 7.51 | M30: =IF(L30<7.5,7.5,L30) -> 7.51 | N30: =COUNTIFS(联赛名单!L:L,信息总览!F30,联赛名单!W:W,"8M") -> 0 | O30: =COUNTIFS(联赛名单!L:L,信息总览!F30,联赛名单!W:W,"7M") -> 0 | P30: =COUNTIFS(联赛名单!L:L,信息总览!F30,联赛名单!W:W,"伪名") -> 4 | Q30: =SUMIF(联赛名单!L:L,信息总览!F30,联赛名单!S:S) -> 88 | R30: =Q30/H30 -> 4.6315789 | S30: =SUMIF(联赛名单!L:L,信息总览!F30,联赛名单!G:G)/H30 -> 139.47368 | T30: =SUMIF(联赛名单!L:L,信息总览!F30,联赛名单!I:I)/H30 -> 156.84211 | U30: =SUMIF(联赛名单!L:L,信息总览!F30,联赛名单!G:G)-SUMIF(联赛名单!L:L,信息总览!F30,联赛名单!F:F) -> 99
C31: Crystal Palace | D31: 9 | E31: 甲级 | F31: =C31 -> Crystal Palace | G31: 完美 | H31: =COUNTIF(联赛名单!L:L,信息总览!F31) -> 17 | I31: =COUNTIFS(联赛名单!L:L,信息总览!F31,联赛名单!J:J,"GK") -> 2 | J31: =SUMIF(联赛名单!L:L,信息总览!F31,联赛名单!U:U) -> 8.54 | L31: =IF(J31+K31-$B$6>0.3,"拍卖",IF(J31+K31>$B$6,(J31+K31-$B$6)*10+J31,J31+K31)) -> 8.54 | M31: =IF(L31<7.5,7.5,L31) -> 8.54 | N31: =COUNTIFS(联赛名单!L:L,信息总览!F31,联赛名单!W:W,"8M") -> 1 | O31: =COUNTIFS(联赛名单!L:L,信息总览!F31,联赛名单!W:W,"7M") -> 0 | P31: =COUNTIFS(联赛名单!L:L,信息总览!F31,联赛名单!W:W,"伪名") -> 4 | Q31: =SUMIF(联赛名单!L:L,信息总览!F31,联赛名单!S:S) -> 86 | R31: =Q31/H31 -> 5.0588235 | S31: =SUMIF(联赛名单!L:L,信息总览!F31,联赛名单!G:G)/H31 -> 140.70588 | T31: =SUMIF(联赛名单!L:L,信息总览!F31,联赛名单!I:I)/H31 -> 158.35294 | U31: =SUMIF(联赛名单!L:L,信息总览!F31,联赛名单!G:G)-SUMIF(联赛名单!L:L,信息总览!F31,联赛名单!F:F) -> 129
C32: Sporting CP | D32: 10 | E32: 甲级 | F32: =C32 -> Sporting CP | G32: 魔力鸡 | H32: =COUNTIF(联赛名单!L:L,信息总览!F32) -> 19 | I32: =COUNTIFS(联赛名单!L:L,信息总览!F32,联赛名单!J:J,"GK") -> 2 | J32: =SUMIF(联赛名单!L:L,信息总览!F32,联赛名单!U:U) -> 8.73 | L32: =IF(J32+K32-$B$6>0.3,"拍卖",IF(J32+K32>$B$6,(J32+K32-$B$6)*10+J32,J32+K32)) -> 8.73 | M32: =IF(L32<7.5,7.5,L32) -> 8.73 | N32: =COUNTIFS(联赛名单!L:L,信息总览!F32,联赛名单!W:W,"8M") -> 1 | O32: =COUNTIFS(联赛名单!L:L,信息总览!F32,联赛名单!W:W,"7M") -> 0 | P32: =COUNTIFS(联赛名单!L:L,信息总览!F32,联赛名单!W:W,"伪名") -> 4 | Q32: =SUMIF(联赛名单!L:L,信息总览!F32,联赛名单!S:S) -> 93 | R32: =Q32/H32 -> 4.8947368 | S32: =SUMIF(联赛名单!L:L,信息总览!F32,联赛名单!G:G)/H32 -> 140 | T32: =SUMIF(联赛名单!L:L,信息总览!F32,联赛名单!I:I)/H32 -> 156.36842 | U32: =SUMIF(联赛名单!L:L,信息总览!F32,联赛名单!G:G)-SUMIF(联赛名单!L:L,信息总览!F32,联赛名单!F:F) -> 131
C33: Lazio | D33: 11 | E33: 甲级 | F33: =C33 -> Lazio | G33: superS | H33: =COUNTIF(联赛名单!L:L,信息总览!F33) -> 20 | I33: =COUNTIFS(联赛名单!L:L,信息总览!F33,联赛名单!J:J,"GK") -> 2 | J33: =SUMIF(联赛名单!L:L,信息总览!F33,联赛名单!U:U) -> 8.305 | L33: =IF(J33+K33-$B$6>0.3,"拍卖",IF(J33+K33>$B$6,(J33+K33-$B$6)*10+J33,J33+K33)) -> 8.305 | M33: =IF(L33<7.5,7.5,L33) -> 8.305 | N33: =COUNTIFS(联赛名单!L:L,信息总览!F33,联赛名单!W:W,"8M") -> 0 | O33: =COUNTIFS(联赛名单!L:L,信息总览!F33,联赛名单!W:W,"7M") -> 1 | P33: =COUNTIFS(联赛名单!L:L,信息总览!F33,联赛名单!W:W,"伪名") -> 3 | Q33: =SUMIF(联赛名单!L:L,信息总览!F33,联赛名单!S:S) -> 93.5 | R33: =Q33/H33 -> 4.675 | S33: =SUMIF(联赛名单!L:L,信息总览!F33,联赛名单!G:G)/H33 -> 137.1 | T33: =SUMIF(联赛名单!L:L,信息总览!F33,联赛名单!I:I)/H33 -> 154.4 | U33: =SUMIF(联赛名单!L:L,信息总览!F33,联赛名单!G:G)-SUMIF(联赛名单!L:L,信息总览!F33,联赛名单!F:F) -> 74
C34: FK Bodø/Glimt | D34: 12 | E34: 甲级 | F34: =C34 -> FK Bodø/Glimt | G34: PD | H34: =COUNTIF(联赛名单!L:L,信息总览!F34) -> 19 | I34: =COUNTIFS(联赛名单!L:L,信息总览!F34,联赛名单!J:J,"GK") -> 2 | J34: =SUMIF(联赛名单!L:L,信息总览!F34,联赛名单!U:U) -> 8.245 | L34: =IF(J34+K34-$B$6>0.3,"拍卖",IF(J34+K34>$B$6,(J34+K34-$B$6)*10+J34,J34+K34)) -> 8.245 | M34: =IF(L34<7.5,7.5,L34) -> 8.245 | N34: =COUNTIFS(联赛名单!L:L,信息总览!F34,联赛名单!W:W,"8M") -> 0 | O34: =COUNTIFS(联赛名单!L:L,信息总览!F34,联赛名单!W:W,"7M") -> 0 | P34: =COUNTIFS(联赛名单!L:L,信息总览!F34,联赛名单!W:W,"伪名") -> 6 | Q34: =SUMIF(联赛名单!L:L,信息总览!F34,联赛名单!S:S) -> 91.5 | R34: =Q34/H34 -> 4.8157895 | S34: =SUMIF(联赛名单!L:L,信息总览!F34,联赛名单!G:G)/H34 -> 137.89474 | T34: =SUMIF(联赛名单!L:L,信息总览!F34,联赛名单!I:I)/H34 -> 157.68421 | U34: =SUMIF(联赛名单!L:L,信息总览!F34,联赛名单!G:G)-SUMIF(联赛名单!L:L,信息总览!F34,联赛名单!F:F) -> 126
C35: Paris SG | D35: 13 | E35: 甲级 | F35: =C35 -> Paris SG | G35: 拿破仑 | H35: =COUNTIF(联赛名单!L:L,信息总览!F35) -> 20 | I35: =COUNTIFS(联赛名单!L:L,信息总览!F35,联赛名单!J:J,"GK") -> 2 | J35: =SUMIF(联赛名单!L:L,信息总览!F35,联赛名单!U:U) -> 8.27 | L35: =IF(J35+K35-$B$6>0.3,"拍卖",IF(J35+K35>$B$6,(J35+K35-$B$6)*10+J35,J35+K35)) -> 8.27 | M35: =IF(L35<7.5,7.5,L35) -> 8.27 | N35: =COUNTIFS(联赛名单!L:L,信息总览!F35,联赛名单!W:W,"8M") -> 1 | O35: =COUNTIFS(联赛名单!L:L,信息总览!F35,联赛名单!W:W,"7M") -> 0 | P35: =COUNTIFS(联赛名单!L:L,信息总览!F35,联赛名单!W:W,"伪名") -> 1 | Q35: =SUMIF(联赛名单!L:L,信息总览!F35,联赛名单!S:S) -> 92 | R35: =Q35/H35 -> 4.6 | S35: =SUMIF(联赛名单!L:L,信息总览!F35,联赛名单!G:G)/H35 -> 138.5 | T35: =SUMIF(联赛名单!L:L,信息总览!F35,联赛名单!I:I)/H35 -> 154.35 | U35: =SUMIF(联赛名单!L:L,信息总览!F35,联赛名单!G:G)-SUMIF(联赛名单!L:L,信息总览!F35,联赛名单!F:F) -> 122
C36: OM | D36: 14 | E36: 甲级 | F36: =C36 -> OM | G36: fmgamer | H36: =COUNTIF(联赛名单!L:L,信息总览!F36) -> 16 | I36: =COUNTIFS(联赛名单!L:L,信息总览!F36,联赛名单!J:J,"GK") -> 2 | J36: =SUMIF(联赛名单!L:L,信息总览!F36,联赛名单!U:U) -> 8.56 | L36: =IF(J36+K36-$B$6>0.3,"拍卖",IF(J36+K36>$B$6,(J36+K36-$B$6)*10+J36,J36+K36)) -> 8.56 | M36: =IF(L36<7.5,7.5,L36) -> 8.56 | N36: =COUNTIFS(联赛名单!L:L,信息总览!F36,联赛名单!W:W,"8M") -> 0 | O36: =COUNTIFS(联赛名单!L:L,信息总览!F36,联赛名单!W:W,"7M") -> 3 | P36: =COUNTIFS(联赛名单!L:L,信息总览!F36,联赛名单!W:W,"伪名") -> 1 | Q36: =SUMIF(联赛名单!L:L,信息总览!F36,联赛名单!S:S) -> 87 | R36: =Q36/H36 -> 5.4375 | S36: =SUMIF(联赛名单!L:L,信息总览!F36,联赛名单!G:G)/H36 -> 152.1875 | T36: =SUMIF(联赛名单!L:L,信息总览!F36,联赛名单!I:I)/H36 -> 157.125 | U36: =SUMIF(联赛名单!L:L,信息总览!F36,联赛名单!G:G)-SUMIF(联赛名单!L:L,信息总览!F36,联赛名单!F:F) -> 46
C37: AS Roma | D37: 15 | E37: 甲级 | F37: =C37 -> AS Roma | G37: 14 | H37: =COUNTIF(联赛名单!L:L,信息总览!F37) -> 18 | I37: =COUNTIFS(联赛名单!L:L,信息总览!F37,联赛名单!J:J,"GK") -> 2 | J37: =SUMIF(联赛名单!L:L,信息总览!F37,联赛名单!U:U) -> 8.86 | L37: =IF(J37+K37-$B$6>0.3,"拍卖",IF(J37+K37>$B$6,(J37+K37-$B$6)*10+J37,J37+K37)) -> 8.86 | M37: =IF(L37<7.5,7.5,L37) -> 8.86 | N37: =COUNTIFS(联赛名单!L:L,信息总览!F37,联赛名单!W:W,"8M") -> 1 | O37: =COUNTIFS(联赛名单!L:L,信息总览!F37,联赛名单!W:W,"7M") -> 0 | P37: =COUNTIFS(联赛名单!L:L,信息总览!F37,联赛名单!W:W,"伪名") -> 3 | Q37: =SUMIF(联赛名单!L:L,信息总览!F37,联赛名单!S:S) -> 95 | R37: =Q37/H37 -> 5.2777778 | S37: =SUMIF(联赛名单!L:L,信息总览!F37,联赛名单!G:G)/H37 -> 146.27778 | T37: =SUMIF(联赛名单!L:L,信息总览!F37,联赛名单!I:I)/H37 -> 158.38889 | U37: =SUMIF(联赛名单!L:L,信息总览!F37,联赛名单!G:G)-SUMIF(联赛名单!L:L,信息总览!F37,联赛名单!F:F) -> 105
C38: Newcastle | D38: 16 | E38: 甲级 | F38: =C38 -> Newcastle | G38: 金牛 | H38: =COUNTIF(联赛名单!L:L,信息总览!F38) -> 20 | I38: =COUNTIFS(联赛名单!L:L,信息总览!F38,联赛名单!J:J,"GK") -> 2 | J38: =SUMIF(联赛名单!L:L,信息总览!F38,联赛名单!U:U) -> 8.27 | L38: =IF(J38+K38-$B$6>0.3,"拍卖",IF(J38+K38>$B$6,(J38+K38-$B$6)*10+J38,J38+K38)) -> 8.27 | M38: =IF(L38<7.5,7.5,L38) -> 8.27 | N38: =COUNTIFS(联赛名单!L:L,信息总览!F38,联赛名单!W:W,"8M") -> 0 | O38: =COUNTIFS(联赛名单!L:L,信息总览!F38,联赛名单!W:W,"7M") -> 1 | P38: =COUNTIFS(联赛名单!L:L,信息总览!F38,联赛名单!W:W,"伪名") -> 3 | Q38: =SUMIF(联赛名单!L:L,信息总览!F38,联赛名单!S:S) -> 93 | R38: =Q38/H38 -> 4.65 | S38: =SUMIF(联赛名单!L:L,信息总览!F38,联赛名单!G:G)/H38 -> 137.05 | T38: =SUMIF(联赛名单!L:L,信息总览!F38,联赛名单!I:I)/H38 -> 155.2 | U38: =SUMIF(联赛名单!L:L,信息总览!F38,联赛名单!G:G)-SUMIF(联赛名单!L:L,信息总览!F38,联赛名单!F:F) -> 40
C39: Wolverhampton Wanderers | D39: 17 | E39: 甲级 | F39: =C39 -> Wolverhampton Wanderers | G39: lav | H39: =COUNTIF(联赛名单!L:L,信息总览!F39) -> 20 | I39: =COUNTIFS(联赛名单!L:L,信息总览!F39,联赛名单!J:J,"GK") -> 2 | J39: =SUMIF(联赛名单!L:L,信息总览!F39,联赛名单!U:U) -> 8.375 | L39: =IF(J39+K39-$B$6>0.3,"拍卖",IF(J39+K39>$B$6,(J39+K39-$B$6)*10+J39,J39+K39)) -> 8.375 | M39: =IF(L39<7.5,7.5,L39) -> 8.375 | N39: =COUNTIFS(联赛名单!L:L,信息总览!F39,联赛名单!W:W,"8M") -> 0 | O39: =COUNTIFS(联赛名单!L:L,信息总览!F39,联赛名单!W:W,"7M") -> 2 | P39: =COUNTIFS(联赛名单!L:L,信息总览!F39,联赛名单!W:W,"伪名") -> 0 | Q39: =SUMIF(联赛名单!L:L,信息总览!F39,联赛名单!S:S) -> 95.5 | R39: =Q39/H39 -> 4.775 | S39: =SUMIF(联赛名单!L:L,信息总览!F39,联赛名单!G:G)/H39 -> 143.95 | T39: =SUMIF(联赛名单!L:L,信息总览!F39,联赛名单!I:I)/H39 -> 158.45 | U39: =SUMIF(联赛名单!L:L,信息总览!F39,联赛名单!G:G)-SUMIF(联赛名单!L:L,信息总览!F39,联赛名单!F:F) -> 34
C40: Talleres | D40: 18 | E40: 甲级 | F40: =C40 -> Talleres | G40: xx | H40: =COUNTIF(联赛名单!L:L,信息总览!F40) -> 20 | I40: =COUNTIFS(联赛名单!L:L,信息总览!F40,联赛名单!J:J,"GK") -> 2 | J40: =SUMIF(联赛名单!L:L,信息总览!F40,联赛名单!U:U) -> 6.56 | L40: =IF(J40+K40-$B$6>0.3,"拍卖",IF(J40+K40>$B$6,(J40+K40-$B$6)*10+J40,J40+K40)) -> 6.56 | M40: =IF(L40<7.5,7.5,L40) -> 7.5 | N40: =COUNTIFS(联赛名单!L:L,信息总览!F40,联赛名单!W:W,"8M") -> 0 | O40: =COUNTIFS(联赛名单!L:L,信息总览!F40,联赛名单!W:W,"7M") -> 0 | P40: =COUNTIFS(联赛名单!L:L,信息总览!F40,联赛名单!W:W,"伪名") -> 0 | Q40: =SUMIF(联赛名单!L:L,信息总览!F40,联赛名单!S:S) -> 78 | R40: =Q40/H40 -> 3.9 | S40: =SUMIF(联赛名单!L:L,信息总览!F40,联赛名单!G:G)/H40 -> 127.8 | T40: =SUMIF(联赛名单!L:L,信息总览!F40,联赛名单!I:I)/H40 -> 152.95 | U40: =SUMIF(联赛名单!L:L,信息总览!F40,联赛名单!G:G)-SUMIF(联赛名单!L:L,信息总览!F40,联赛名单!F:F) -> 119
C43: VfB Stuttgart | D43: 1 | E43: 乙级 | F43: =C43 -> VfB Stuttgart | G43: jiong | H43: =COUNTIF(联赛名单!L:L,信息总览!F43) -> 19 | I43: =COUNTIFS(联赛名单!L:L,信息总览!F43,联赛名单!J:J,"GK") -> 2 | J43: =SUMIF(联赛名单!L:L,信息总览!F43,联赛名单!U:U) -> 6.06 | L43: =IF(J43+K43-$B$7>0.3,"拍卖",IF(J43+K43>$B$7,(J43+K43-$B$7)*10+J43,J43+K43)) -> 6.06 | M43: =IF(L43<6.5,6.5,L43) -> 6.5 | N43: =COUNTIFS(联赛名单!L:L,信息总览!F43,联赛名单!W:W,"8M") -> 0 | O43: =COUNTIFS(联赛名单!L:L,信息总览!F43,联赛名单!W:W,"7M") -> 0 | P43: =COUNTIFS(联赛名单!L:L,信息总览!F43,联赛名单!W:W,"伪名") -> 1 | Q43: =SUMIF(联赛名单!L:L,信息总览!F43,联赛名单!S:S) -> 77 | R43: =Q43/H43 -> 4.0526316 | S43: =SUMIF(联赛名单!L:L,信息总览!F43,联赛名单!G:G)/H43 -> 132.05263 | T43: =SUMIF(联赛名单!L:L,信息总览!F43,联赛名单!I:I)/H43 -> 148.84211 | U43: =SUMIF(联赛名单!L:L,信息总览!F43,联赛名单!G:G)-SUMIF(联赛名单!L:L,信息总览!F43,联赛名单!F:F) -> 12
C44: Man City | D44: 2 | E44: 乙级 | F44: =C44 -> Man City | G44: 大神 | H44: =COUNTIF(联赛名单!L:L,信息总览!F44) -> 18 | I44: =COUNTIFS(联赛名单!L:L,信息总览!F44,联赛名单!J:J,"GK") -> 2 | J44: =SUMIF(联赛名单!L:L,信息总览!F44,联赛名单!U:U) -> 7.82 | L44: =IF(J44+K44-$B$7>0.3,"拍卖",IF(J44+K44>$B$7,(J44+K44-$B$7)*10+J44,J44+K44)) -> 7.82 | M44: =IF(L44<6.5,6.5,L44) -> 7.82 | N44: =COUNTIFS(联赛名单!L:L,信息总览!F44,联赛名单!W:W,"8M") -> 0 | O44: =COUNTIFS(联赛名单!L:L,信息总览!F44,联赛名单!W:W,"7M") -> 1 | P44: =COUNTIFS(联赛名单!L:L,信息总览!F44,联赛名单!W:W,"伪名") -> 4 | Q44: =SUMIF(联赛名单!L:L,信息总览!F44,联赛名单!S:S) -> 85 | R44: =Q44/H44 -> 4.7222222 | S44: =SUMIF(联赛名单!L:L,信息总览!F44,联赛名单!G:G)/H44 -> 135.83333 | T44: =SUMIF(联赛名单!L:L,信息总览!F44,联赛名单!I:I)/H44 -> 158.61111 | U44: =SUMIF(联赛名单!L:L,信息总览!F44,联赛名单!G:G)-SUMIF(联赛名单!L:L,信息总览!F44,联赛名单!F:F) -> 180
C45: Arsenal | D45: 3 | E45: 乙级 | F45: =C45 -> Arsenal | G45: 囊个 | H45: =COUNTIF(联赛名单!L:L,信息总览!F45) -> 20 | I45: =COUNTIFS(联赛名单!L:L,信息总览!F45,联赛名单!J:J,"GK") -> 2 | J45: =SUMIF(联赛名单!L:L,信息总览!F45,联赛名单!U:U) -> 7.145 | L45: =IF(J45+K45-$B$7>0.3,"拍卖",IF(J45+K45>$B$7,(J45+K45-$B$7)*10+J45,J45+K45)) -> 7.145 | M45: =IF(L45<6.5,6.5,L45) -> 7.145 | N45: =COUNTIFS(联赛名单!L:L,信息总览!F45,联赛名单!W:W,"8M") -> 0 | O45: =COUNTIFS(联赛名单!L:L,信息总览!F45,联赛名单!W:W,"7M") -> 1 | P45: =COUNTIFS(联赛名单!L:L,信息总览!F45,联赛名单!W:W,"伪名") -> 1 | Q45: =SUMIF(联赛名单!L:L,信息总览!F45,联赛名单!S:S) -> 82.5 | R45: =Q45/H45 -> 4.125 | S45: =SUMIF(联赛名单!L:L,信息总览!F45,联赛名单!G:G)/H45 -> 121.1 | T45: =SUMIF(联赛名单!L:L,信息总览!F45,联赛名单!I:I)/H45 -> 157.85 | U45: =SUMIF(联赛名单!L:L,信息总览!F45,联赛名单!G:G)-SUMIF(联赛名单!L:L,信息总览!F45,联赛名单!F:F) -> 61
C46: Brighton | D46: 4 | E46: 乙级 | F46: =C46 -> Brighton | G46: 小曲奇 | H46: =COUNTIF(联赛名单!L:L,信息总览!F46) -> 18 | I46: =COUNTIFS(联赛名单!L:L,信息总览!F46,联赛名单!J:J,"GK") -> 2 | J46: =SUMIF(联赛名单!L:L,信息总览!F46,联赛名单!U:U) -> 7.88 | L46: =IF(J46+K46-$B$7>0.3,"拍卖",IF(J46+K46>$B$7,(J46+K46-$B$7)*10+J46,J46+K46)) -> 7.88 | M46: =IF(L46<6.5,6.5,L46) -> 7.88 | N46: =COUNTIFS(联赛名单!L:L,信息总览!F46,联赛名单!W:W,"8M") -> 0 | O46: =COUNTIFS(联赛名单!L:L,信息总览!F46,联赛名单!W:W,"7M") -> 2 | P46: =COUNTIFS(联赛名单!L:L,信息总览!F46,联赛名单!W:W,"伪名") -> 1 | Q46: =SUMIF(联赛名单!L:L,信息总览!F46,联赛名单!S:S) -> 89 | R46: =Q46/H46 -> 4.9444444 | S46: =SUMIF(联赛名单!L:L,信息总览!F46,联赛名单!G:G)/H46 -> 143.05556 | T46: =SUMIF(联赛名单!L:L,信息总览!F46,联赛名单!I:I)/H46 -> 158.16667 | U46: =SUMIF(联赛名单!L:L,信息总览!F46,联赛名单!G:G)-SUMIF(联赛名单!L:L,信息总览!F46,联赛名单!F:F) -> 14
C47: Benfica | D47: 5 | E47: 乙级 | F47: =C47 -> Benfica | G47: 黑豹 | H47: =COUNTIF(联赛名单!L:L,信息总览!F47) -> 19 | I47: =COUNTIFS(联赛名单!L:L,信息总览!F47,联赛名单!J:J,"GK") -> 2 | J47: =SUMIF(联赛名单!L:L,信息总览!F47,联赛名单!U:U) -> 7.68 | L47: =IF(J47+K47-$B$7-0.1>0.3,"拍卖",IF(J47+K47>$B$7+0.1,(J47+K47-$B$7)*10+J47,J47+K47)) -> 7.68 | M47: =IF(L47<6.5,6.5,L47) -> 7.68 | N47: =COUNTIFS(联赛名单!L:L,信息总览!F47,联赛名单!W:W,"8M") -> 1 | O47: =COUNTIFS(联赛名单!L:L,信息总览!F47,联赛名单!W:W,"7M") -> 0 | P47: =COUNTIFS(联赛名单!L:L,信息总览!F47,联赛名单!W:W,"伪名") -> 1 | Q47: =SUMIF(联赛名单!L:L,信息总览!F47,联赛名单!S:S) -> 88 | R47: =Q47/H47 -> 4.6315789 | S47: =SUMIF(联赛名单!L:L,信息总览!F47,联赛名单!G:G)/H47 -> 140.57895 | T47: =SUMIF(联赛名单!L:L,信息总览!F47,联赛名单!I:I)/H47 -> 153.36842 | U47: =SUMIF(联赛名单!L:L,信息总览!F47,联赛名单!G:G)-SUMIF(联赛名单!L:L,信息总览!F47,联赛名单!F:F) -> 128 | V47: 额外0.1M工资帽
C48: Boca | D48: 6 | E48: 乙级 | F48: =C48 -> Boca | G48: 回忆 | H48: =COUNTIF(联赛名单!L:L,信息总览!F48) -> 16 | I48: =COUNTIFS(联赛名单!L:L,信息总览!F48,联赛名单!J:J,"GK") -> 2 | J48: =SUMIF(联赛名单!L:L,信息总览!F48,联赛名单!U:U) -> 7.205 | L48: =IF(J48+K48-$B$7>0.3,"拍卖",IF(J48+K48>$B$7,(J48+K48-$B$7)*10+J48,J48+K48)) -> 7.205 | M48: =IF(L48<6.5,6.5,L48) -> 7.205 | N48: =COUNTIFS(联赛名单!L:L,信息总览!F48,联赛名单!W:W,"8M") -> 1 | O48: =COUNTIFS(联赛名单!L:L,信息总览!F48,联赛名单!W:W,"7M") -> 0 | P48: =COUNTIFS(联赛名单!L:L,信息总览!F48,联赛名单!W:W,"伪名") -> 3 | Q48: =SUMIF(联赛名单!L:L,信息总览!F48,联赛名单!S:S) -> 76.5 | R48: =Q48/H48 -> 4.78125 | S48: =SUMIF(联赛名单!L:L,信息总览!F48,联赛名单!G:G)/H48 -> 137.5625 | T48: =SUMIF(联赛名单!L:L,信息总览!F48,联赛名单!I:I)/H48 -> 157.875 | U48: =SUMIF(联赛名单!L:L,信息总览!F48,联赛名单!G:G)-SUMIF(联赛名单!L:L,信息总览!F48,联赛名单!F:F) -> 123
C49: Bournemouth | D49: 7 | E49: 乙级 | F49: =C49 -> Bournemouth | G49: ISO | H49: =COUNTIF(联赛名单!L:L,信息总览!F49) -> 17 | I49: =COUNTIFS(联赛名单!L:L,信息总览!F49,联赛名单!J:J,"GK") -> 2 | J49: =SUMIF(联赛名单!L:L,信息总览!F49,联赛名单!U:U) -> 8.375 | L49: =IF(J49+K49-$B$7-0.1>0.3,"拍卖",IF(J49+K49>$B$7+0.1,(J49+K49-$B$7)*10+J49,J49+K49)) -> 8.375 | M49: =IF(L49<6.5,6.5,L49) -> 8.375 | N49: =COUNTIFS(联赛名单!L:L,信息总览!F49,联赛名单!W:W,"8M") -> 1 | O49: =COUNTIFS(联赛名单!L:L,信息总览!F49,联赛名单!W:W,"7M") -> 0 | P49: =COUNTIFS(联赛名单!L:L,信息总览!F49,联赛名单!W:W,"伪名") -> 3 | Q49: =SUMIF(联赛名单!L:L,信息总览!F49,联赛名单!S:S) -> 88.5 | R49: =Q49/H49 -> 5.2058824 | S49: =SUMIF(联赛名单!L:L,信息总览!F49,联赛名单!G:G)/H49 -> 143.17647 | T49: =SUMIF(联赛名单!L:L,信息总览!F49,联赛名单!I:I)/H49 -> 161.82353 | U49: =SUMIF(联赛名单!L:L,信息总览!F49,联赛名单!G:G)-SUMIF(联赛名单!L:L,信息总览!F49,联赛名单!F:F) -> 81 | V49: 额外0.1M工资帽
C50: Como | D50: 8 | E50: 乙级 | F50: =C50 -> Como | G50: haze | H50: =COUNTIF(联赛名单!L:L,信息总览!F50) -> 18 | I50: =COUNTIFS(联赛名单!L:L,信息总览!F50,联赛名单!J:J,"GK") -> 2 | J50: =SUMIF(联赛名单!L:L,信息总览!F50,联赛名单!U:U) -> 7.46 | L50: =IF(J50+K50-$B$7-0.1>0.3,"拍卖",IF(J50+K50>$B$7+0.1,(J50+K50-$B$7)*10+J50,J50+K50)) -> 7.46 | M50: =IF(L50<6.5,6.5,L50) -> 7.46 | N50: =COUNTIFS(联赛名单!L:L,信息总览!F50,联赛名单!W:W,"8M") -> 0 | O50: =COUNTIFS(联赛名单!L:L,信息总览!F50,联赛名单!W:W,"7M") -> 0 | P50: =COUNTIFS(联赛名单!L:L,信息总览!F50,联赛名单!W:W,"伪名") -> 5 | Q50: =SUMIF(联赛名单!L:L,信息总览!F50,联赛名单!S:S) -> 81 | R50: =Q50/H50 -> 4.5 | S50: =SUMIF(联赛名单!L:L,信息总览!F50,联赛名单!G:G)/H50 -> 132 | T50: =SUMIF(联赛名单!L:L,信息总览!F50,联赛名单!I:I)/H50 -> 158.27778 | U50: =SUMIF(联赛名单!L:L,信息总览!F50,联赛名单!G:G)-SUMIF(联赛名单!L:L,信息总览!F50,联赛名单!F:F) -> 102 | V50: 额外0.1M工资帽
C51: FC Porto | D51: 9 | E51: 乙级 | F51: =C51 -> FC Porto | G51: nice | H51: =COUNTIF(联赛名单!L:L,信息总览!F51) -> 19 | I51: =COUNTIFS(联赛名单!L:L,信息总览!F51,联赛名单!J:J,"GK") -> 2 | J51: =SUMIF(联赛名单!L:L,信息总览!F51,联赛名单!U:U) -> 6.98 | L51: =IF(J51+K51-$B$7-0.1>0.3,"拍卖",IF(J51+K51>$B$7+0.1,(J51+K51-$B$7)*10+J51,J51+K51)) -> 6.98 | M51: =IF(L51<6.5,6.5,L51) -> 6.98 | N51: =COUNTIFS(联赛名单!L:L,信息总览!F51,联赛名单!W:W,"8M") -> 0 | O51: =COUNTIFS(联赛名单!L:L,信息总览!F51,联赛名单!W:W,"7M") -> 1 | P51: =COUNTIFS(联赛名单!L:L,信息总览!F51,联赛名单!W:W,"伪名") -> 1 | Q51: =SUMIF(联赛名单!L:L,信息总览!F51,联赛名单!S:S) -> 82 | R51: =Q51/H51 -> 4.3157895 | S51: =SUMIF(联赛名单!L:L,信息总览!F51,联赛名单!G:G)/H51 -> 136.42105 | T51: =SUMIF(联赛名单!L:L,信息总览!F51,联赛名单!I:I)/H51 -> 156.94737 | U51: =SUMIF(联赛名单!L:L,信息总览!F51,联赛名单!G:G)-SUMIF(联赛名单!L:L,信息总览!F51,联赛名单!F:F) -> 55 | V51: 额外0.1M工资帽
C52: Strasbourg | D52: 10 | E52: 乙级 | F52: =C52 -> Strasbourg | G52: 青云 | H52: =COUNTIF(联赛名单!L:L,信息总览!F52) -> 19 | I52: =COUNTIFS(联赛名单!L:L,信息总览!F52,联赛名单!J:J,"GK") -> 2 | J52: =SUMIF(联赛名单!L:L,信息总览!F52,联赛名单!U:U) -> 8.425 | L52: =IF(J52+K52-$B$7>0.3,"拍卖",IF(J52+K52>$B$7,(J52+K52-$B$7)*10+J52,J52+K52)) -> 8.425 | M52: =IF(L52<6.5,6.5,L52) -> 8.425 | N52: =COUNTIFS(联赛名单!L:L,信息总览!F52,联赛名单!W:W,"8M") -> 0 | O52: =COUNTIFS(联赛名单!L:L,信息总览!F52,联赛名单!W:W,"7M") -> 2 | P52: =COUNTIFS(联赛名单!L:L,信息总览!F52,联赛名单!W:W,"伪名") -> 2 | Q52: =SUMIF(联赛名单!L:L,信息总览!F52,联赛名单!S:S) -> 91.5 | R52: =Q52/H52 -> 4.8157895 | S52: =SUMIF(联赛名单!L:L,信息总览!F52,联赛名单!G:G)/H52 -> 142.52632 | T52: =SUMIF(联赛名单!L:L,信息总览!F52,联赛名单!I:I)/H52 -> 155.63158 | U52: =SUMIF(联赛名单!L:L,信息总览!F52,联赛名单!G:G)-SUMIF(联赛名单!L:L,信息总览!F52,联赛名单!F:F) -> 91
C53: Inter Miami | D53: 11 | E53: 乙级 | F53: =C53 -> Inter Miami | G53: Mk | H53: =COUNTIF(联赛名单!L:L,信息总览!F53) -> 18 | I53: =COUNTIFS(联赛名单!L:L,信息总览!F53,联赛名单!J:J,"GK") -> 2 | J53: =SUMIF(联赛名单!L:L,信息总览!F53,联赛名单!U:U) -> 8.02 | L53: =IF(J53+K53-$B$7-0.1>0.3,"拍卖",IF(J53+K53>$B$7+0.1,(J53+K53-$B$7)*10+J53,J53+K53)) -> 8.02 | M53: =IF(L53<6.5,6.5,L53) -> 8.02 | N53: =COUNTIFS(联赛名单!L:L,信息总览!F53,联赛名单!W:W,"8M") -> 0 | O53: =COUNTIFS(联赛名单!L:L,信息总览!F53,联赛名单!W:W,"7M") -> 0 | P53: =COUNTIFS(联赛名单!L:L,信息总览!F53,联赛名单!W:W,"伪名") -> 4 | Q53: =SUMIF(联赛名单!L:L,信息总览!F53,联赛名单!S:S) -> 88 | R53: =Q53/H53 -> 4.8888889 | S53: =SUMIF(联赛名单!L:L,信息总览!F53,联赛名单!G:G)/H53 -> 140.72222 | T53: =SUMIF(联赛名单!L:L,信息总览!F53,联赛名单!I:I)/H53 -> 157.05556 | U53: =SUMIF(联赛名单!L:L,信息总览!F53,联赛名单!G:G)-SUMIF(联赛名单!L:L,信息总览!F53,联赛名单!F:F) -> 46 | V53: 额外0.1M工资帽
C54: Coventry City | D54: 12 | E54: 乙级 | F54: =C54 -> Coventry City | G54: 夜南南 | H54: =COUNTIF(联赛名单!L:L,信息总览!F54) -> 20 | I54: =COUNTIFS(联赛名单!L:L,信息总览!F54,联赛名单!J:J,"GK") -> 2 | J54: =SUMIF(联赛名单!L:L,信息总览!F54,联赛名单!U:U) -> 7.47 | L54: =IF(J54+K54-$B$7>0.3,"拍卖",IF(J54+K54>$B$7,(J54+K54-$B$7)*10+J54,J54+K54)) -> 7.47 | M54: =IF(L54<6.5,6.5,L54) -> 7.47 | N54: =COUNTIFS(联赛名单!L:L,信息总览!F54,联赛名单!W:W,"8M") -> 0 | O54: =COUNTIFS(联赛名单!L:L,信息总览!F54,联赛名单!W:W,"7M") -> 0 | P54: =COUNTIFS(联赛名单!L:L,信息总览!F54,联赛名单!W:W,"伪名") -> 3 | Q54: =SUMIF(联赛名单!L:L,信息总览!F54,联赛名单!S:S) -> 89 | R54: =Q54/H54 -> 4.45 | S54: =SUMIF(联赛名单!L:L,信息总览!F54,联赛名单!G:G)/H54 -> 135.8 | T54: =SUMIF(联赛名单!L:L,信息总览!F54,联赛名单!I:I)/H54 -> 155.55 | U54: =SUMIF(联赛名单!L:L,信息总览!F54,联赛名单!G:G)-SUMIF(联赛名单!L:L,信息总览!F54,联赛名单!F:F) -> 23
C55: Leicester | D55: 13 | E55: 乙级 | F55: =C55 -> Leicester | G55: 大直塞 | H55: =COUNTIF(联赛名单!L:L,信息总览!F55) -> 18 | I55: =COUNTIFS(联赛名单!L:L,信息总览!F55,联赛名单!J:J,"GK") -> 2 | J55: =SUMIF(联赛名单!L:L,信息总览!F55,联赛名单!U:U) -> 7.215 | L55: =IF(J55+K55-$B$7>0.3,"拍卖",IF(J55+K55>$B$7,(J55+K55-$B$7)*10+J55,J55+K55)) -> 7.215 | M55: =IF(L55<6.5,6.5,L55) -> 7.215 | N55: =COUNTIFS(联赛名单!L:L,信息总览!F55,联赛名单!W:W,"8M") -> 0 | O55: =COUNTIFS(联赛名单!L:L,信息总览!F55,联赛名单!W:W,"7M") -> 0 | P55: =COUNTIFS(联赛名单!L:L,信息总览!F55,联赛名单!W:W,"伪名") -> 3 | Q55: =SUMIF(联赛名单!L:L,信息总览!F55,联赛名单!S:S) -> 82.5 | R55: =Q55/H55 -> 4.5833333 | S55: =SUMIF(联赛名单!L:L,信息总览!F55,联赛名单!G:G)/H55 -> 138.83333 | T55: =SUMIF(联赛名单!L:L,信息总览!F55,联赛名单!I:I)/H55 -> 153.77778 | U55: =SUMIF(联赛名单!L:L,信息总览!F55,联赛名单!G:G)-SUMIF(联赛名单!L:L,信息总览!F55,联赛名单!F:F) -> 93
C56: AFC Ajax | D56: 14 | E56: 乙级 | F56: =C56 -> AFC Ajax | G56: 7指导 | H56: =COUNTIF(联赛名单!L:L,信息总览!F56) -> 19 | I56: =COUNTIFS(联赛名单!L:L,信息总览!F56,联赛名单!J:J,"GK") -> 2 | J56: =SUMIF(联赛名单!L:L,信息总览!F56,联赛名单!U:U) -> 7.99 | L56: =IF(J56+K56-$B$7>0.3,"拍卖",IF(J56+K56>$B$7,(J56+K56-$B$7)*10+J56,J56+K56)) -> 7.99 | M56: =IF(L56<6.5,6.5,L56) -> 7.99 | N56: =COUNTIFS(联赛名单!L:L,信息总览!F56,联赛名单!W:W,"8M") -> 1 | O56: =COUNTIFS(联赛名单!L:L,信息总览!F56,联赛名单!W:W,"7M") -> 0 | P56: =COUNTIFS(联赛名单!L:L,信息总览!F56,联赛名单!W:W,"伪名") -> 3 | Q56: =SUMIF(联赛名单!L:L,信息总览!F56,联赛名单!S:S) -> 87 | R56: =Q56/H56 -> 4.5789474 | S56: =SUMIF(联赛名单!L:L,信息总览!F56,联赛名单!G:G)/H56 -> 134.21053 | T56: =SUMIF(联赛名单!L:L,信息总览!F56,联赛名单!I:I)/H56 -> 154.57895 | U56: =SUMIF(联赛名单!L:L,信息总览!F56,联赛名单!G:G)-SUMIF(联赛名单!L:L,信息总览!F56,联赛名单!F:F) -> 53
C57: Sturm Graz | D57: 15 | E57: 乙级 | F57: =C57 -> Sturm Graz | G57: kuzz | H57: =COUNTIF(联赛名单!L:L,信息总览!F57) -> 18 | I57: =COUNTIFS(联赛名单!L:L,信息总览!F57,联赛名单!J:J,"GK") -> 2 | J57: =SUMIF(联赛名单!L:L,信息总览!F57,联赛名单!U:U) -> 7.295 | L57: =IF(J57+K57-$B$7>0.3,"拍卖",IF(J57+K57>$B$7,(J57+K57-$B$7)*10+J57,J57+K57)) -> 7.295 | M57: =IF(L57<6.5,6.5,L57) -> 7.295 | N57: =COUNTIFS(联赛名单!L:L,信息总览!F57,联赛名单!W:W,"8M") -> 0 | O57: =COUNTIFS(联赛名单!L:L,信息总览!F57,联赛名单!W:W,"7M") -> 1 | P57: =COUNTIFS(联赛名单!L:L,信息总览!F57,联赛名单!W:W,"伪名") -> 2 | Q57: =SUMIF(联赛名单!L:L,信息总览!F57,联赛名单!S:S) -> 84.5 | R57: =Q57/H57 -> 4.6944444 | S57: =SUMIF(联赛名单!L:L,信息总览!F57,联赛名单!G:G)/H57 -> 139.16667 | T57: =SUMIF(联赛名单!L:L,信息总览!F57,联赛名单!I:I)/H57 -> 156.05556 | U57: =SUMIF(联赛名单!L:L,信息总览!F57,联赛名单!G:G)-SUMIF(联赛名单!L:L,信息总览!F57,联赛名单!F:F) -> 83
C58: Eintracht Frankfurt | D58: 16 | E58: 乙级 | F58: =C58 -> Eintracht Frankfurt | G58: 小沃 | H58: =COUNTIF(联赛名单!L:L,信息总览!F58) -> 21 | I58: =COUNTIFS(联赛名单!L:L,信息总览!F58,联赛名单!J:J,"GK") -> 2 | J58: =SUMIF(联赛名单!L:L,信息总览!F58,联赛名单!U:U) -> 8.405 | L58: =IF(J58+K58-$B$7>0.3,"拍卖",IF(J58+K58>$B$7,(J58+K58-$B$7)*10+J58,J58+K58)) -> 8.405 | M58: =IF(L58<6.5,6.5,L58) -> 8.405 | N58: =COUNTIFS(联赛名单!L:L,信息总览!F58,联赛名单!W:W,"8M") -> 0 | O58: =COUNTIFS(联赛名单!L:L,信息总览!F58,联赛名单!W:W,"7M") -> 0 | P58: =COUNTIFS(联赛名单!L:L,信息总览!F58,联赛名单!W:W,"伪名") -> 3 | Q58: =SUMIF(联赛名单!L:L,信息总览!F58,联赛名单!S:S) -> 96.5 | R58: =Q58/H58 -> 4.5952381 | S58: =SUMIF(联赛名单!L:L,信息总览!F58,联赛名单!G:G)/H58 -> 136.7619 | T58: =SUMIF(联赛名单!L:L,信息总览!F58,联赛名单!I:I)/H58 -> 157.57143 | U58: =SUMIF(联赛名单!L:L,信息总览!F58,联赛名单!G:G)-SUMIF(联赛名单!L:L,信息总览!F58,联赛名单!F:F) -> 63
C59: Sheff Utd | D59: 17 | E59: 乙级 | F59: =C59 -> Sheff Utd | G59: 司徒 | H59: =COUNTIF(联赛名单!L:L,信息总览!F59) -> 18 | I59: =COUNTIFS(联赛名单!L:L,信息总览!F59,联赛名单!J:J,"GK") -> 2 | J59: =SUMIF(联赛名单!L:L,信息总览!F59,联赛名单!U:U) -> 7.905 | L59: =IF(J59+K59-$B$7>0.3,"拍卖",IF(J59+K59>$B$7,(J59+K59-$B$7)*10+J59,J59+K59)) -> 7.905 | M59: =IF(L59<6.5,6.5,L59) -> 7.905 | N59: =COUNTIFS(联赛名单!L:L,信息总览!F59,联赛名单!W:W,"8M") -> 1 | O59: =COUNTIFS(联赛名单!L:L,信息总览!F59,联赛名单!W:W,"7M") -> 0 | P59: =COUNTIFS(联赛名单!L:L,信息总览!F59,联赛名单!W:W,"伪名") -> 3 | Q59: =SUMIF(联赛名单!L:L,信息总览!F59,联赛名单!S:S) -> 86.5 | R59: =Q59/H59 -> 4.8055556 | S59: =SUMIF(联赛名单!L:L,信息总览!F59,联赛名单!G:G)/H59 -> 141.5 | T59: =SUMIF(联赛名单!L:L,信息总览!F59,联赛名单!I:I)/H59 -> 159.66667 | U59: =SUMIF(联赛名单!L:L,信息总览!F59,联赛名单!G:G)-SUMIF(联赛名单!L:L,信息总览!F59,联赛名单!F:F) -> 70
C60: Zhejiang | D60: 18 | E60: 乙级 | F60: =C60 -> Zhejiang | G60: 青蛙王子 | H60: =COUNTIF(联赛名单!L:L,信息总览!F60) -> 17 | I60: =COUNTIFS(联赛名单!L:L,信息总览!F60,联赛名单!J:J,"GK") -> 2 | J60: =SUMIF(联赛名单!L:L,信息总览!F60,联赛名单!U:U) -> 7.71 | L60: =IF(J60+K60-$B$7>0.3,"拍卖",IF(J60+K60>$B$7,(J60+K60-$B$7)*10+J60,J60+K60)) -> 7.71 | M60: =IF(L60<6.5,6.5,L60) -> 7.71 | N60: =COUNTIFS(联赛名单!L:L,信息总览!F60,联赛名单!W:W,"8M") -> 0 | O60: =COUNTIFS(联赛名单!L:L,信息总览!F60,联赛名单!W:W,"7M") -> 2 | P60: =COUNTIFS(联赛名单!L:L,信息总览!F60,联赛名单!W:W,"伪名") -> 3 | Q60: =SUMIF(联赛名单!L:L,信息总览!F60,联赛名单!S:S) -> 80 | R60: =Q60/H60 -> 4.7058824 | S60: =SUMIF(联赛名单!L:L,信息总览!F60,联赛名单!G:G)/H60 -> 136.23529 | T60: =SUMIF(联赛名单!L:L,信息总览!F60,联赛名单!I:I)/H60 -> 157.35294 | U60: =SUMIF(联赛名单!L:L,信息总览!F60,联赛名单!G:G)-SUMIF(联赛名单!L:L,信息总览!F60,联赛名单!F:F) -> 81

Sheet 联赛名单
A1: 名额 | B1: 编​号 | C1: 姓​名 | D1: 原年龄 | E1: 年​龄 | F1: 初始CA | G1: 当前CA | H1: 更新CA | I1: PA | J1: 位​置 | K1: 国籍 | L1: 俱乐部 | M1: 级​别 | N1: 身​高 | O1: 体​重 | P1: 初始身价 | Q1: 当前身价 | R1: 潜力身价 | S1: 身价 | T1: 系数 | U1: 工资 | V1: 初始 | W1: 名额
A2: =W2 -> 7M | B2: 24048100 | C2: Dani Olmo | E2: 27 | F2: 165 | G2: 165 | H2: =IFERROR(VLOOKUP(B2,球员对应球队!A:D,4,FALSE)-G2,"") -> 0 | I2: 170 | J2: M/AMRLC | K2: 西班牙 | L2: A. Bilbao | M2: =VLOOKUP(L2,信息总览!C:E,3,FALSE) -> 甲级 | P2: =IF(F2<115,1,INT((F2-95)/10)) -> 7 | Q2: =IF(G2<115,1,INT((G2-95)/10)) -> 7 | R2: =IF(I2<115,1,INT((I2-95)/10)) -> 7 | S2: =IF(E2>信息总览!$B$4,Q2,IF(I2<140,Q2,(Q2+R2)/2)) -> 7 | T2: =IF(AND(J2="GK",W2<>""),0.1,IF(S2=1,0.1,IF((S2+V2)/2=1,0.1,IF(W2="8M",0.15,IF(W2="7M",0.13,IF(W2="伪名",0.11,IF(E2>信息总览!$B$4,IF(INT((G2-95)/10)>5,0.09,0.07),IF(INT((I2-95)/10)>5,0.09,0.07)))))))) -> 0.13 | U2: =S2*T2 -> 0.91 | V2: =IF(E2>25,IF(F2<115,1,INT((F2-95)/10)),(IF(F2<115,1,INT((F2-95)/10))+IF(I2<115,1,INT((I2-95)/10)))/2) -> 7 | W2: =IF(V2>=8,"8M",IF(V2>=7,"7M",IF(E2<=信息总览!$B$4,IF(I2>164,"伪名",""),IF(AND(E2>信息总览!$B$4,E2<26,G2>164),"伪名","")))) -> 7M | X2: =IF(I2<140,0,IF(E2>23,0,I2-G2)) -> 0
A3: =W3 | B3: 43391659 | C3: Elia Caprile | E3: 23 | F3: 139 | G3: 144 | H3: =IFERROR(VLOOKUP(B3,球员对应球队!A:D,4,FALSE)-G3,"") -> 0 | I3: 154 | J3: GK | K3: 意大利 | L3: A. Bilbao | M3: =VLOOKUP(L3,信息总览!C:E,3,FALSE) -> 甲级 | P3: =IF(F3<115,1,INT((F3-95)/10)) -> 4 | Q3: =IF(G3<115,1,INT((G3-95)/10)) -> 4 | R3: =IF(I3<115,1,INT((I3-95)/10)) -> 5 | S3: =IF(E3>信息总览!$B$4,Q3,IF(I3<140,Q3,(Q3+R3)/2)) -> 4.5 | T3: =IF(AND(J3="GK",W3<>""),0.1,IF(S3=1,0.1,IF((S3+V3)/2=1,0.1,IF(W3="8M",0.15,IF(W3="7M",0.13,IF(W3="伪名",0.11,IF(E3>信息总览!$B$4,IF(INT((G3-95)/10)>5,0.09,0.07),IF(INT((I3-95)/10)>5,0.09,0.07)))))))) -> 0.07 | U3: =S3*T3 -> 0.315 | V3: =IF(E3>25,IF(F3<115,1,INT((F3-95)/10)),(IF(F3<115,1,INT((F3-95)/10))+IF(I3<115,1,INT((I3-95)/10)))/2) -> 4.5 | W3: =IF(V3>=8,"8M",IF(V3>=7,"7M",IF(E3<=信息总览!$B$4,IF(I3>164,"伪名",""),IF(AND(E3>信息总览!$B$4,E3<26,G3>164),"伪名","")))) | X3: =IF(I3<140,0,IF(E3>23,0,I3-G3)) -> 10
A4: =W4 | B4: 48032198 | C4: Evan N'Dicka | E4: 25 | F4: 154 | G4: 158 | H4: =IFERROR(VLOOKUP(B4,球员对应球队!A:D,4,FALSE)-G4,"") -> 0 | I4: 158 | J4: D/LC | K4: 科特迪瓦 | L4: A. Bilbao | M4: =VLOOKUP(L4,信息总览!C:E,3,FALSE) -> 甲级 | P4: =IF(F4<115,1,INT((F4-95)/10)) -> 5 | Q4: =IF(G4<115,1,INT((G4-95)/10)) -> 6 | R4: =IF(I4<115,1,INT((I4-95)/10)) -> 6 | S4: =IF(E4>信息总览!$B$4,Q4,IF(I4<140,Q4,(Q4+R4)/2)) -> 6 | T4: =IF(AND(J4="GK",W4<>""),0.1,IF(S4=1,0.1,IF((S4+V4)/2=1,0.1,IF(W4="8M",0.15,IF(W4="7M",0.13,IF(W4="伪名",0.11,IF(E4>信息总览!$B$4,IF(INT((G4-95)/10)>5,0.09,0.07),IF(INT((I4-95)/10)>5,0.09,0.07)))))))) -> 0.09 | U4: =S4*T4 -> 0.54 | V4: =IF(E4>25,IF(F4<115,1,INT((F4-95)/10)),(IF(F4<115,1,INT((F4-95)/10))+IF(I4<115,1,INT((I4-95)/10)))/2) -> 5.5 | W4: =IF(V4>=8,"8M",IF(V4>=7,"7M",IF(E4<=信息总览!$B$4,IF(I4>164,"伪名",""),IF(AND(E4>信息总览!$B$4,E4<26,G4>164),"伪名","")))) | X4: =IF(I4<140,0,IF(E4>23,0,I4-G4)) -> 0
A5: =W5 -> 伪名 | B5: 2000051578 | C5: Facundo Buonanotte | E5: 20 | F5: 133 | G5: 141 | H5: =IFERROR(VLOOKUP(B5,球员对应球队!A:D,4,FALSE)-G5,"") -> 0 | I5: 178 | J5: M/AMRLC | K5: Argentina,Italy | L5: A. Bilbao | M5: =VLOOKUP(L5,信息总览!C:E,3,FALSE) -> 甲级 | P5: =IF(F5<115,1,INT((F5-95)/10)) -> 3 | Q5: =IF(G5<115,1,INT((G5-95)/10)) -> 4 | R5: =IF(I5<115,1,INT((I5-95)/10)) -> 8 | S5: =IF(E5>信息总览!$B$4,Q5,IF(I5<140,Q5,(Q5+R5)/2)) -> 6 | T5: =IF(AND(J5="GK",W5<>""),0.1,IF(S5=1,0.1,IF((S5+V5)/2=1,0.1,IF(W5="8M",0.15,IF(W5="7M",0.13,IF(W5="伪名",0.11,IF(E5>信息总览!$B$4,IF(INT((G5-95)/10)>5,0.09,0.07),IF(INT((I5-95)/10)>5,0.09,0.07)))))))) -> 0.11 | U5: =S5*T5 -> 0.66 | V5: =IF(E5>25,IF(F5<115,1,INT((F5-95)/10)),(IF(F5<115,1,INT((F5-95)/10))+IF(I5<115,1,INT((I5-95)/10)))/2) -> 5.5 | W5: =IF(V5>=8,"8M",IF(V5>=7,"7M",IF(E5<=信息总览!$B$4,IF(I5>164,"伪名",""),IF(AND(E5>信息总览!$B$4,E5<26,G5>164),"伪名","")))) -> 伪名 | X5: =IF(I5<140,0,IF(E5>23,0,I5-G5)) -> 37
A6: =W6 -> 8M | B6: 28049320 | C6: Harry Kane | E6: 31 | F6: 188 | G6: 188 | H6: =IFERROR(VLOOKUP(B6,球员对应球队!A:D,4,FALSE)-G6,"") -> 0 | I6: 190 | J6: ST | K6: 英格兰 | L6: A. Bilbao | M6: =VLOOKUP(L6,信息总览!C:E,3,FALSE) -> 甲级 | P6: =IF(F6<115,1,INT((F6-95)/10)) -> 9 | Q6: =IF(G6<115,1,INT((G6-95)/10)) -> 9 | R6: =IF(I6<115,1,INT((I6-95)/10)) -> 9 | S6: =IF(E6>信息总览!$B$4,Q6,IF(I6<140,Q6,(Q6+R6)/2)) -> 9 | T6: =IF(AND(J6="GK",W6<>""),0.1,IF(S6=1,0.1,IF((S6+V6)/2=1,0.1,IF(W6="8M",0.15,IF(W6="7M",0.13,IF(W6="伪名",0.11,IF(E6>信息总览!$B$4,IF(INT((G6-95)/10)>5,0.09,0.07),IF(INT((I6-95)/10)>5,0.09,0.07)))))))) -> 0.15 | U6: =S6*T6 -> 1.35 | V6: =IF(E6>25,IF(F6<115,1,INT((F6-95)/10)),(IF(F6<115,1,INT((F6-95)/10))+IF(I6<115,1,INT((I6-95)/10)))/2) -> 9 | W6: =IF(V6>=8,"8M",IF(V6>=7,"7M",IF(E6<=信息总览!$B$4,IF(I6>164,"伪名",""),IF(AND(E6>信息总览!$B$4,E6<26,G6>164),"伪名","")))) -> 8M | X6: =IF(I6<140,0,IF(E6>23,0,I6-G6)) -> 0
A7: =W7 | B7: 67153377 | C7: Jose Suarez | E7: 29 | F7: 102 | G7: 102 | H7: =IFERROR(VLOOKUP(B7,球员对应球队!A:D,4,FALSE)-G7,"") -> 0 | I7: 120 | J7: GK | K7: 西班牙 | L7: A. Bilbao | M7: =VLOOKUP(L7,信息总览!C:E,3,FALSE) -> 甲级 | P7: =IF(F7<115,1,INT((F7-95)/10)) -> 1 | Q7: =IF(G7<115,1,INT((G7-95)/10)) -> 1 | R7: =IF(I7<115,1,INT((I7-95)/10)) -> 2 | S7: =IF(E7>信息总览!$B$4,Q7,IF(I7<140,Q7,(Q7+R7)/2)) -> 1 | T7: =IF(AND(J7="GK",W7<>""),0.1,IF(S7=1,0.1,IF((S7+V7)/2=1,0.1,IF(W7="8M",0.15,IF(W7="7M",0.13,IF(W7="伪名",0.11,IF(E7>信息总览!$B$4,IF(INT((G7-95)/10)>5,0.09,0.07),IF(INT((I7-95)/10)>5,0.09,0.07)))))))) -> 0.1 | U7: =S7*T7 -> 0.1 | V7: =IF(E7>25,IF(F7<115,1,INT((F7-95)/10)),(IF(F7<115,1,INT((F7-95)/10))+IF(I7<115,1,INT((I7-95)/10)))/2) -> 1 | W7: =IF(V7>=8,"8M",IF(V7>=7,"7M",IF(E7<=信息总览!$B$4,IF(I7>164,"伪名",""),IF(AND(E7>信息总览!$B$4,E7<26,G7>164),"伪名","")))) | X7: =IF(I7<140,0,IF(E7>23,0,I7-G7)) -> 0
A8: =W8 | B8: 2000241413 | C8: Kirill Glebov | E8: 19 | F8: 120 | G8: 149 | H8: =IFERROR(VLOOKUP(B8,球员对应球队!A:D,4,FALSE)-G8,"") -> 0 | I8: 160 | J8: AM/RLC | K8: Russia | L8: A. Bilbao | M8: =VLOOKUP(L8,信息总览!C:E,3,FALSE) -> 甲级 | P8: =IF(F8<115,1,INT((F8-95)/10)) -> 2 | Q8: =IF(G8<115,1,INT((G8-95)/10)) -> 5 | R8: =IF(I8<115,1,INT((I8-95)/10)) -> 6 | S8: =IF(E8>信息总览!$B$4,Q8,IF(I8<140,Q8,(Q8+R8)/2)) -> 5.5 | T8: =IF(AND(J8="GK",W8<>""),0.1,IF(S8=1,0.1,IF((S8+V8)/2=1,0.1,IF(W8="8M",0.15,IF(W8="7M",0.13,IF(W8="伪名",0.11,IF(E8>信息总览!$B$4,IF(INT((G8-95)/10)>5,0.09,0.07),IF(INT((I8-95)/10)>5,0.09,0.07)))))))) -> 0.09 | U8: =S8*T8 -> 0.495 | V8: =IF(E8>25,IF(F8<115,1,INT((F8-95)/10)),(IF(F8<115,1,INT((F8-95)/10))+IF(I8<115,1,INT((I8-95)/10)))/2) -> 4 | W8: =IF(V8>=8,"8M",IF(V8>=7,"7M",IF(E8<=信息总览!$B$4,IF(I8>164,"伪名",""),IF(AND(E8>信息总览!$B$4,E8<26,G8>164),"伪名","")))) | X8: =IF(I8<140,0,IF(E8>23,0,I8-G8)) -> 11
A9: =W9 | B9: 36096824 | C9: Kostas Tsimikas | E9: 29 | F9: 149 | G9: 149 | H9: =IFERROR(VLOOKUP(B9,球员对应球队!A:D,4,FALSE)-G9,"") -> 0 | I9: 159 | J9: D/WB/L | K9: 希腊 | L9: A. Bilbao | M9: =VLOOKUP(L9,信息总览!C:E,3,FALSE) -> 甲级 | P9: =IF(F9<115,1,INT((F9-95)/10)) -> 5 | Q9: =IF(G9<115,1,INT((G9-95)/10)) -> 5 | R9: =IF(I9<115,1,INT((I9-95)/10)) -> 6 | S9: =IF(E9>信息总览!$B$4,Q9,IF(I9<140,Q9,(Q9+R9)/2)) -> 5 | T9: =IF(AND(J9="GK",W9<>""),0.1,IF(S9=1,0.1,IF((S9+V9)/2=1,0.1,IF(W9="8M",0.15,IF(W9="7M",0.13,IF(W9="伪名",0.11,IF(E9>信息总览!$B$4,IF(INT((G9-95)/10)>5,0.09,0.07),IF(INT((I9-95)/10)>5,0.09,0.07)))))))) -> 0.07 | U9: =S9*T9 -> 0.35 | V9: =IF(E9>25,IF(F9<115,1,INT((F9-95)/10)),(IF(F9<115,1,INT((F9-95)/10))+IF(I9<115,1,INT((I9-95)/10)))/2) -> 5 | W9: =IF(V9>=8,"8M",IF(V9>=7,"7M",IF(E9<=信息总览!$B$4,IF(I9>164,"伪名",""),IF(AND(E9>信息总览!$B$4,E9<26,G9>164),"伪名","")))) | X9: =IF(I9<140,0,IF(E9>23,0,I9-G9)) -> 0
A10: =W10 -> 伪名 | B10: 2000298715 | C10: Mikey Moore | E10: 17 | F10: 124 | G10: 131 | H10: =IFERROR(VLOOKUP(B10,球员对应球队!A:D,4,FALSE)-G10,"") -> 0 | I10: 169 | J10: AM/RLC | K10: England,Wales | L10: A. Bilbao | M10: =VLOOKUP(L10,信息总览!C:E,3,FALSE) -> 甲级 | P10: =IF(F10<115,1,INT((F10-95)/10)) -> 2 | Q10: =IF(G10<115,1,INT((G10-95)/10)) -> 3 | R10: =IF(I10<115,1,INT((I10-95)/10)) -> 7 | S10: =IF(E10>信息总览!$B$4,Q10,IF(I10<140,Q10,(Q10+R10)/2)) -> 5 | T10: =IF(AND(J10="GK",W10<>""),0.1,IF(S10=1,0.1,IF((S10+V10)/2=1,0.1,IF(W10="8M",0.15,IF(W10="7M",0.13,IF(W10="伪名",0.11,IF(E10>信息总览!$B$4,IF(INT((G10-95)/10)>5,0.09,0.07),IF(INT((I10-95)/10)>5,0.09,0.07)))))))) -> 0.11 | U10: =S10*T10 -> 0.55 | V10: =IF(E10>25,IF(F10<115,1,INT((F10-95)/10)),(IF(F10<115,1,INT((F10-95)/10))+IF(I10<115,1,INT((I10-95)/10)))/2) -> 4.5 | W10: =IF(V10>=8,"8M",IF(V10>=7,"7M",IF(E10<=信息总览!$B$4,IF(I10>164,"伪名",""),IF(AND(E10>信息总览!$B$4,E10<26,G10>164),"伪名","")))) -> 伪名 | X10: =IF(I10<140,0,IF(E10>23,0,I10-G10)) -> 38
A11: =W11 -> 伪名 | B11: 2000254793 | C11: Nypan | E11: 18 | F11: 120 | G11: 140 | H11: =IFERROR(VLOOKUP(B11,球员对应球队!A:D,4,FALSE)-G11,"") -> 0 | I11: 179 | J11: M/AMRLC | K11: 丹麦 | L11: A. Bilbao | M11: =VLOOKUP(L11,信息总览!C:E,3,FALSE) -> 甲级 | P11: =IF(F11<115,1,INT((F11-95)/10)) -> 2 | Q11: =IF(G11<115,1,INT((G11-95)/10)) -> 4 | R11: =IF(I11<115,1,INT((I11-95)/10)) -> 8 | S11: =IF(E11>信息总览!$B$4,Q11,IF(I11<140,Q11,(Q11+R11)/2)) -> 6 | T11: =IF(AND(J11="GK",W11<>""),0.1,IF(S11=1,0.1,IF((S11+V11)/2=1,0.1,IF(W11="8M",0.15,IF(W11="7M",0.13,IF(W11="伪名",0.11,IF(E11>信息总览!$B$4,IF(INT((G11-95)/10)>5,0.09,0.07),IF(INT((I11-95)/10)>5,0.09,0.07)))))))) -> 0.11 | U11: =S11*T11 -> 0.66 | V11: =IF(E11>25,IF(F11<115,1,INT((F11-95)/10)),(IF(F11<115,1,INT((F11-95)/10))+IF(I11<115,1,INT((I11-95)/10)))/2) -> 5 | W11: =IF(V11>=8,"8M",IF(V11>=7,"7M",IF(E11<=信息总览!$B$4,IF(I11>164,"伪名",""),IF(AND(E11>信息总览!$B$4,E11<26,G11>164),"伪名","")))) -> 伪名 | X11: =IF(I11<140,0,IF(E11>23,0,I11-G11)) -> 39
A12: =W12 | B12: 2000466343 | C12: Olivier Mambwa | E12: 16 | F12: 89 | G12: 107 | H12: =IFERROR(VLOOKUP(B12,球员对应球队!A:D,4,FALSE)-G12,"") -> 0 | I12: 160 | J12: D/L | K12: Switzerland,Democratic Republic of Congo | L12: A. Bilbao | M12: =VLOOKUP(L12,信息总览!C:E,3,FALSE) -> 甲级 | P12: =IF(F12<115,1,INT((F12-95)/10)) -> 1 | Q12: =IF(G12<115,1,INT((G12-95)/10)) -> 1 | R12: =IF(I12<115,1,INT((I12-95)/10)) -> 6 | S12: =IF(E12>信息总览!$B$4,Q12,IF(I12<140,Q12,(Q12+R12)/2)) -> 3.5 | T12: =IF(AND(J12="GK",W12<>""),0.1,IF(S12=1,0.1,IF((S12+V12)/2=1,0.1,IF(W12="8M",0.15,IF(W12="7M",0.13,IF(W12="伪名",0.11,IF(E12>信息总览!$B$4,IF(INT((G12-95)/10)>5,0.09,0.07),IF(INT((I12-95)/10)>5,0.09,0.07)))))))) -> 0.09 | U12: =S12*T12 -> 0.315 | V12: =IF(E12>25,IF(F12<115,1,INT((F12-95)/10)),(IF(F12<115,1,INT((F12-95)/10))+IF(I12<115,1,INT((I12-95)/10)))/2) -> 3.5 | W12: =IF(V12>=8,"8M",IF(V12>=7,"7M",IF(E12<=信息总览!$B$4,IF(I12>164,"伪名",""),IF(AND(E12>信息总览!$B$4,E12<26,G12>164),"伪名","")))) | X12: =IF(I12<140,0,IF(E12>23,0,I12-G12)) -> 53
A13: =W13 | B13: 14094572 | C13: Rodrigo Bentancur | E13: 28 | F13: 150 | G13: 150 | H13: =IFERROR(VLOOKUP(B13,球员对应球队!A:D,4,FALSE)-G13,"") -> 0 | I13: 164 | J13: DM/MC | K13: 乌拉圭 | L13: A. Bilbao | M13: =VLOOKUP(L13,信息总览!C:E,3,FALSE) -> 甲级 | P13: =IF(F13<115,1,INT((F13-95)/10)) -> 5 | Q13: =IF(G13<115,1,INT((G13-95)/10)) -> 5 | R13: =IF(I13<115,1,INT((I13-95)/10)) -> 6 | S13: =IF(E13>信息总览!$B$4,Q13,IF(I13<140,Q13,(Q13+R13)/2)) -> 5 | T13: =IF(AND(J13="GK",W13<>""),0.1,IF(S13=1,0.1,IF((S13+V13)/2=1,0.1,IF(W13="8M",0.15,IF(W13="7M",0.13,IF(W13="伪名",0.11,IF(E13>信息总览!$B$4,IF(INT((G13-95)/10)>5,0.09,0.07),IF(INT((I13-95)/10)>5,0.09,0.07)))))))) -> 0.07 | U13: =S13*T13 -> 0.35 | V13: =IF(E13>25,IF(F13<115,1,INT((F13-95)/10)),(IF(F13<115,1,INT((F13-95)/10))+IF(I13<115,1,INT((I13-95)/10)))/2) -> 5 | W13: =IF(V13>=8,"8M",IF(V13>=7,"7M",IF(E13<=信息总览!$B$4,IF(I13>164,"伪名",""),IF(AND(E13>信息总览!$B$4,E13<26,G13>164),"伪名","")))) | X13: =IF(I13<140,0,IF(E13>23,0,I13-G13)) -> 0
... A35: =W35 | B35: 14048328 | C35: Juan Musso | E35: 31 | F35: 140 | G35: 140 | H35: =IFERROR(VLOOKUP(B35,球员对应球队!A:D,4,FALSE)-G35,"") -> 0 | I35: 149 | J35: GK | K35: 阿根廷 | L35: A. Madrid | M35: =VLOOKUP(L35,信息总览!C:E,3,FALSE) -> 甲级 | P35: =IF(F35<115,1,INT((F35-95)/10)) -> 4 | Q35: =IF(G35<115,1,INT((G35-95)/10)) -> 4 | R35: =IF(I35<115,1,INT((I35-95)/10)) -> 5 | S35: =IF(E35>信息总览!$B$4,Q35,IF(I35<140,Q35,(Q35+R35)/2)) -> 4 | T35: =IF(AND(J35="GK",W35<>""),0.1,IF(S35=1,0.1,IF((S35+V35)/2=1,0.1,IF(W35="8M",0.15,IF(W35="7M",0.13,IF(W35="伪名",0.11,IF(E35>信息总览!$B$4,IF(INT((G35-95)/10)>5,0.09,0.07),IF(INT((I35-95)/10)>5,0.09,0.07)))))))) -> 0.07 | U35: =S35*T35 -> 0.28 | V35: =IF(E35>25,IF(F35<115,1,INT((F35-95)/10)),(IF(F35<115,1,INT((F35-95)/10))+IF(I35<115,1,INT((I35-95)/10)))/2) -> 4 | W35: =IF(V35>=8,"8M",IF(V35>=7,"7M",IF(E35<=信息总览!$B$4,IF(I35>164,"伪名",""),IF(AND(E35>信息总览!$B$4,E35<26,G35>164),"伪名","")))) | X35: =IF(I35<140,0,IF(E35>23,0,I35-G35)) -> 0
A36: =W36 | B36: 2000221411 | C36: Allan | E36: 21 | F36: 115 | G36: 115 | I36: 139 | J36: M/AM RLC | K36: Brazil | L36: A. Madrid | M36: =VLOOKUP(L36,信息总览!C:E,3,FALSE) -> 甲级 | P36: =IF(F36<115,1,INT((F36-95)/10)) -> 2 | Q36: =IF(G36<115,1,INT((G36-95)/10)) -> 2 | R36: =IF(I36<115,1,INT((I36-95)/10)) -> 4 | S36: =IF(E36>信息总览!$B$4,Q36,IF(I36<140,Q36,(Q36+R36)/2)) -> 2 | T36: =IF(AND(J36="GK",W36<>""),0.1,IF(S36=1,0.1,IF((S36+V36)/2=1,0.1,IF(W36="8M",0.15,IF(W36="7M",0.13,IF(W36="伪名",0.11,IF(E36>信息总览!$B$4,IF(INT((G36-95)/10)>5,0.09,0.07),IF(INT((I36-95)/10)>5,0.09,0.07)))))))) -> 0.07 | U36: =S36*T36 -> 0.14 | V36: =IF(E36>25,IF(F36<115,1,INT((F36-95)/10)),(IF(F36<115,1,INT((F36-95)/10))+IF(I36<115,1,INT((I36-95)/10)))/2) -> 3 | W36: =IF(V36>=8,"8M",IF(V36>=7,"7M",IF(E36<=信息总览!$B$4,IF(I36>164,"伪名",""),IF(AND(E36>信息总览!$B$4,E36<26,G36>164),"伪名","")))) | X36: =IF(I36<140,0,IF(E36>23,0,I36-G36)) -> 0
A37: =W37 | B37: 29141472 | C37: Benjamin White | E37: 27 | F37: 155 | G37: 155 | I37: 162 | J37: D RC | K37: England | L37: A. Madrid | M37: =VLOOKUP(L37,信息总览!C:E,3,FALSE) -> 甲级 | P37: =IF(F37<115,1,INT((F37-95)/10)) -> 6 | Q37: =IF(G37<115,1,INT((G37-95)/10)) -> 6 | R37: =IF(I37<115,1,INT((I37-95)/10)) -> 6 | S37: =IF(E37>信息总览!$B$4,Q37,IF(I37<140,Q37,(Q37+R37)/2)) -> 6 | T37: =IF(AND(J37="GK",W37<>""),0.1,IF(S37=1,0.1,IF((S37+V37)/2=1,0.1,IF(W37="8M",0.15,IF(W37="7M",0.13,IF(W37="伪名",0.11,IF(E37>信息总览!$B$4,IF(INT((G37-95)/10)>5,0.09,0.07),IF(INT((I37-95)/10)>5,0.09,0.07)))))))) -> 0.09 | U37: =S37*T37 -> 0.54 | V37: =IF(E37>25,IF(F37<115,1,INT((F37-95)/10)),(IF(F37<115,1,INT((F37-95)/10))+IF(I37<115,1,INT((I37-95)/10)))/2) -> 6 | W37: =IF(V37>=8,"8M",IF(V37>=7,"7M",IF(E37<=信息总览!$B$4,IF(I37>164,"伪名",""),IF(AND(E37>信息总览!$B$4,E37<26,G37>164),"伪名","")))) | X37: =IF(I37<140,0,IF(E37>23,0,I37-G37)) -> 0
A38: =W38 -> 伪名 | B38: 2000094252 | C38: Beraldo | E38: 21 | F38: 142 | G38: 142 | H38: =IFERROR(VLOOKUP(B38,球员对应球队!A:D,4,FALSE)-G38,"") -> 0 | I38: 165 | J38: DC/DM | K38: 巴西 | L38: AC Milan | M38: =VLOOKUP(L38,信息总览!C:E,3,FALSE) -> 甲级 | P38: =IF(F38<115,1,INT((F38-95)/10)) -> 4 | Q38: =IF(G38<115,1,INT((G38-95)/10)) -> 4 | R38: =IF(I38<115,1,INT((I38-95)/10)) -> 7 | S38: =IF(E38>信息总览!$B$4,Q38,IF(I38<140,Q38,(Q38+R38)/2)) -> 5.5 | T38: =IF(AND(J38="GK",W38<>""),0.1,IF(S38=1,0.1,IF((S38+V38)/2=1,0.1,IF(W38="8M",0.15,IF(W38="7M",0.13,IF(W38="伪名",0.11,IF(E38>信息总览!$B$4,IF(INT((G38-95)/10)>5,0.09,0.07),IF(INT((I38-95)/10)>5,0.09,0.07)))))))) -> 0.11 | U38: =S38*T38 -> 0.605 | V38: =IF(E38>25,IF(F38<115,1,INT((F38-95)/10)),(IF(F38<115,1,INT((F38-95)/10))+IF(I38<115,1,INT((I38-95)/10)))/2) -> 5.5 | W38: =IF(V38>=8,"8M",IF(V38>=7,"7M",IF(E38<=信息总览!$B$4,IF(I38>164,"伪名",""),IF(AND(E38>信息总览!$B$4,E38<26,G38>164),"伪名","")))) -> 伪名 | X38: =IF(I38<140,0,IF(E38>23,0,I38-G38)) -> 23
A39: =W39 | B39: 2000094152 | C39: Claudio Echeverri | E39: 19 | F39: 123 | G39: 123 | H39: =IFERROR(VLOOKUP(B39,球员对应球队!A:D,4,FALSE)-G39,"") -> 0 | I39: 158 | J39: AM/RLC | K39: 阿根廷 | L39: AC Milan | M39: =VLOOKUP(L39,信息总览!C:E,3,FALSE) -> 甲级 | P39: =IF(F39<115,1,INT((F39-95)/10)) -> 2 | Q39: =IF(G39<115,1,INT((G39-95)/10)) -> 2 | R39: =IF(I39<115,1,INT((I39-95)/10)) -> 6 | S39: =IF(E39>信息总览!$B$4,Q39,IF(I39<140,Q39,(Q39+R39)/2)) -> 4 | T39: =IF(AND(J39="GK",W39<>""),0.1,IF(S39=1,0.1,IF((S39+V39)/2=1,0.1,IF(W39="8M",0.15,IF(W39="7M",0.13,IF(W39="伪名",0.11,IF(E39>信息总览!$B$4,IF(INT((G39-95)/10)>5,0.09,0.07),IF(INT((I39-95)/10)>5,0.09,0.07)))))))) -> 0.09 | U39: =S39*T39 -> 0.36 | V39: =IF(E39>25,IF(F39<115,1,INT((F39-95)/10)),(IF(F39<115,1,INT((F39-95)/10))+IF(I39<115,1,INT((I39-95)/10)))/2) -> 4 | W39: =IF(V39>=8,"8M",IF(V39>=7,"7M",IF(E39<=信息总览!$B$4,IF(I39>164,"伪名",""),IF(AND(E39>信息总览!$B$4,E39<26,G39>164),"伪名","")))) | X39: =IF(I39<140,0,IF(E39>23,0,I39-G39)) -> 35
A40: =W40 | B40: 43491384 | C40: Federico Gatti | E40: 27 | F40: 150 | G40: 150 | H40: =IFERROR(VLOOKUP(B40,球员对应球队!A:D,4,FALSE)-G40,"") -> 0 | I40: 153 | J40: D/C | K40: 意大利 | L40: AC Milan | M40: =VLOOKUP(L40,信息总览!C:E,3,FALSE) -> 甲级 | P40: =IF(F40<115,1,INT((F40-95)/10)) -> 5 | Q40: =IF(G40<115,1,INT((G40-95)/10)) -> 5 | R40: =IF(I40<115,1,INT((I40-95)/10)) -> 5 | S40: =IF(E40>信息总览!$B$4,Q40,IF(I40<140,Q40,(Q40+R40)/2)) -> 5 | T40: =IF(AND(J40="GK",W40<>""),0.1,IF(S40=1,0.1,IF((S40+V40)/2=1,0.1,IF(W40="8M",0.15,IF(W40="7M",0.13,IF(W40="伪名",0.11,IF(E40>信息总览!$B$4,IF(INT((G40-95)/10)>5,0.09,0.07),IF(INT((I40-95)/10)>5,0.09,0.07)))))))) -> 0.07 | U40: =S40*T40 -> 0.35 | V40: =IF(E40>25,IF(F40<115,1,INT((F40-95)/10)),(IF(F40<115,1,INT((F40-95)/10))+IF(I40<115,1,INT((I40-95)/10)))/2) -> 5 | W40: =IF(V40>=8,"8M",IF(V40>=7,"7M",IF(E40<=信息总览!$B$4,IF(I40>164,"伪名",""),IF(AND(E40>信息总览!$B$4,E40<26,G40>164),"伪名","")))) | X40: =IF(I40<140,0,IF(E40>23,0,I40-G40)) -> 0
A41: =W41 | B41: 2000293312 | C41: Jesús Fortea | E41: 18 | F41: 99 | G41: 99 | H41: =IFERROR(VLOOKUP(B41,球员对应球队!A:D,4,FALSE)-G41,"") -> 0 | I41: 155 | J41: D/WB/R | K41: 西班牙 | L41: AC Milan | M41: =VLOOKUP(L41,信息总览!C:E,3,FALSE) -> 甲级 | P41: =IF(F41<115,1,INT((F41-95)/10)) -> 1 | Q41: =IF(G41<115,1,INT((G41-95)/10)) -> 1 | R41: =IF(I41<115,1,INT((I41-95)/10)) -> 6 | S41: =IF(E41>信息总览!$B$4,Q41,IF(I41<140,Q41,(Q41+R41)/2)) -> 3.5 | T41: =IF(AND(J41="GK",W41<>""),0.1,IF(S41=1,0.1,IF((S41+V41)/2=1,0.1,IF(W41="8M",0.15,IF(W41="7M",0.13,IF(W41="伪名",0.11,IF(E41>信息总览!$B$4,IF(INT((G41-95)/10)>5,0.09,0.07),IF(INT((I41-95)/10)>5,0.09,0.07)))))))) -> 0.09 | U41: =S41*T41 -> 0.315 | V41: =IF(E41>25,IF(F41<115,1,INT((F41-95)/10)),(IF(F41<115,1,INT((F41-95)/10))+IF(I41<115,1,INT((I41-95)/10)))/2) -> 3.5 | W41: =IF(V41>=8,"8M",IF(V41>=7,"7M",IF(E41<=信息总览!$B$4,IF(I41>164,"伪名",""),IF(AND(E41>信息总览!$B$4,E41<26,G41>164),"伪名","")))) | X41: =IF(I41<140,0,IF(E41>23,0,I41-G41)) -> 56
A42: =W42 | B42: 2000299435 | C42: Joan | E42: 17 | F42: 86 | G42: 86 | H42: =IFERROR(VLOOKUP(B42,球员对应球队!A:D,4,FALSE)-G42,"") -> 0 | I42: 160 | J42: D/C | K42: 西班牙 | L42: AC Milan | M42: =VLOOKUP(L42,信息总览!C:E,3,FALSE) -> 甲级 | P42: =IF(F42<115,1,INT((F42-95)/10)) -> 1 | Q42: =IF(G42<115,1,INT((G42-95)/10)) -> 1 | R42: =IF(I42<115,1,INT((I42-95)/10)) -> 6 | S42: =IF(E42>信息总览!$B$4,Q42,IF(I42<140,Q42,(Q42+R42)/2)) -> 3.5 | T42: =IF(AND(J42="GK",W42<>""),0.1,IF(S42=1,0.1,IF((S42+V42)/2=1,0.1,IF(W42="8M",0.15,IF(W42="7M",0.13,IF(W42="伪名",0.11,IF(E42>信息总览!$B$4,IF(INT((G42-95)/10)>5,0.09,0.07),IF(INT((I42-95)/10)>5,0.09,0.07)))))))) -> 0.09 | U42: =S42*T42 -> 0.315 | V42: =IF(E42>25,IF(F42<115,1,INT((F42-95)/10)),(IF(F42<115,1,INT((F42-95)/10))+IF(I42<115,1,INT((I42-95)/10)))/2) -> 3.5 | W42: =IF(V42>=8,"8M",IF(V42>=7,"7M",IF(E42<=信息总览!$B$4,IF(I42>164,"伪名",""),IF(AND(E42>信息总览!$B$4,E42<26,G42>164),"伪名","")))) | X42: =IF(I42<140,0,IF(E42>23,0,I42-G42)) -> 74
A43: =W43 -> 伪名 | B43: 2000205927 | C43: Jobe Bellingham | E43: 19 | F43: 134 | G43: 141 | H43: =IFERROR(VLOOKUP(B43,球员对应球队!A:D,4,FALSE)-G43,"") -> 0 | I43: 167 | J43: M/AMC | K43: 英格兰 | L43: AC Milan | M43: =VLOOKUP(L43,信息总览!C:E,3,FALSE) -> 甲级 | P43: =IF(F43<115,1,INT((F43-95)/10)) -> 3 | Q43: =IF(G43<115,1,INT((G43-95)/10)) -> 4 | R43: =IF(I43<115,1,INT((I43-95)/10)) -> 7 | S43: =IF(E43>信息总览!$B$4,Q43,IF(I43<140,Q43,(Q43+R43)/2)) -> 5.5 | T43: =IF(AND(J43="GK",W43<>""),0.1,IF(S43=1,0.1,IF((S43+V43)/2=1,0.1,IF(W43="8M",0.15,IF(W43="7M",0.13,IF(W43="伪名",0.11,IF(E43>信息总览!$B$4,IF(INT((G43-95)/10)>5,0.09,0.07),IF(INT((I43-95)/10)>5,0.09,0.07)))))))) -> 0.11 | U43: =S43*T43 -> 0.605 | V43: =IF(E43>25,IF(F43<115,1,INT((F43-95)/10)),(IF(F43<115,1,INT((F43-95)/10))+IF(I43<115,1,INT((I43-95)/10)))/2) -> 5 | W43: =IF(V43>=8,"8M",IF(V43>=7,"7M",IF(E43<=信息总览!$B$4,IF(I43>164,"伪名",""),IF(AND(E43>信息总览!$B$4,E43<26,G43>164),"伪名","")))) -> 伪名 | X43: =IF(I43<140,0,IF(E43>23,0,I43-G43)) -> 26
A44: =W44 | B44: 58123738 | C44: Matvey Safonov | E44: 26 | F44: 140 | G44: 140 | H44: =IFERROR(VLOOKUP(B44,球员对应球队!A:D,4,FALSE)-G44,"") -> 0 | I44: 145 | J44: GK | K44: 英格兰 | L44: AC Milan | M44: =VLOOKUP(L44,信息总览!C:E,3,FALSE) -> 甲级 | P44: =IF(F44<115,1,INT((F44-95)/10)) -> 4 | Q44: =IF(G44<115,1,INT((G44-95)/10)) -> 4 | R44: =IF(I44<115,1,INT((I44-95)/10)) -> 5 | S44: =IF(E44>信息总览!$B$4,Q44,IF(I44<140,Q44,(Q44+R44)/2)) -> 4 | T44: =IF(AND(J44="GK",W44<>""),0.1,IF(S44=1,0.1,IF((S44+V44)/2=1,0.1,IF(W44="8M",0.15,IF(W44="7M",0.13,IF(W44="伪名",0.11,IF(E44>信息总览!$B$4,IF(INT((G44-95)/10)>5,0.09,0.07),IF(INT((I44-95)/10)>5,0.09,0.07)))))))) -> 0.07 | U44: =S44*T44 -> 0.28 | V44: =IF(E44>25,IF(F44<115,1,INT((F44-95)/10)),(IF(F44<115,1,INT((F44-95)/10))+IF(I44<115,1,INT((I44-95)/10)))/2) -> 4 | W44: =IF(V44>=8,"8M",IF(V44>=7,"7M",IF(E44<=信息总览!$B$4,IF(I44>164,"伪名",""),IF(AND(E44>信息总览!$B$4,E44<26,G44>164),"伪名","")))) | X44: =IF(I44<140,0,IF(E44>23,0,I44-G44)) -> 0
A45: =W45 | B45: 93127195 | C45: Odilon Kossounou | E45: 24 | F45: 144 | G45: 144 | H45: =IFERROR(VLOOKUP(B45,球员对应球队!A:D,4,FALSE)-G45,"") -> 0 | I45: 154 | J45: D/RC | K45: 科特迪瓦 | L45: AC Milan | M45: =VLOOKUP(L45,信息总览!C:E,3,FALSE) -> 甲级 | P45: =IF(F45<115,1,INT((F45-95)/10)) -> 4 | Q45: =IF(G45<115,1,INT((G45-95)/10)) -> 4 | R45: =IF(I45<115,1,INT((I45-95)/10)) -> 5 | S45: =IF(E45>信息总览!$B$4,Q45,IF(I45<140,Q45,(Q45+R45)/2)) -> 4.5 | T45: =IF(AND(J45="GK",W45<>""),0.1,IF(S45=1,0.1,IF((S45+V45)/2=1,0.1,IF(W45="8M",0.15,IF(W45="7M",0.13,IF(W45="伪名",0.11,IF(E45>信息总览!$B$4,IF(INT((G45-95)/10)>5,0.09,0.07),IF(INT((I45-95)/10)>5,0.09,0.07)))))))) -> 0.07 | U45: =S45*T45 -> 0.315 | V45: =IF(E45>25,IF(F45<115,1,INT((F45-95)/10)),(IF(F45<115,1,INT((F45-95)/10))+IF(I45<115,1,INT((I45-95)/10)))/2) -> 4.5 | W45: =IF(V45>=8,"8M",IF(V45>=7,"7M",IF(E45<=信息总览!$B$4,IF(I45>164,"伪名",""),IF(AND(E45>信息总览!$B$4,E45<26,G45>164),"伪名","")))) | X45: =IF(I45<140,0,IF(E45>23,0,I45-G45)) -> 0
A46: =W46 | B46: 2000095783 | C46: Vitor Roque | E46: 20 | F46: 138 | G46: 143 | H46: =IFERROR(VLOOKUP(B46,球员对应球队!A:D,4,FALSE)-G46,"") -> 0 | I46: 151 | J46: ST | K46: 巴西 | L46: AC Milan | M46: =VLOOKUP(L46,信息总览!C:E,3,FALSE) -> 甲级 | P46: =IF(F46<115,1,INT((F46-95)/10)) -> 4 | Q46: =IF(G46<115,1,INT((G46-95)/10)) -> 4 | R46: =IF(I46<115,1,INT((I46-95)/10)) -> 5 | S46: =IF(E46>信息总览!$B$4,Q46,IF(I46<140,Q46,(Q46+R46)/2)) -> 4.5 | T46: =IF(AND(J46="GK",W46<>""),0.1,IF(S46=1,0.1,IF((S46+V46)/2=1,0.1,IF(W46="8M",0.15,IF(W46="7M",0.13,IF(W46="伪名",0.11,IF(E46>信息总览!$B$4,IF(INT((G46-95)/10)>5,0.09,0.07),IF(INT((I46-95)/10)>5,0.09,0.07)))))))) -> 0.07 | U46: =S46*T46 -> 0.315 | V46: =IF(E46>25,IF(F46<115,1,INT((F46-95)/10)),(IF(F46<115,1,INT((F46-95)/10))+IF(I46<115,1,INT((I46-95)/10)))/2) -> 4.5 | W46: =IF(V46>=8,"8M",IF(V46>=7,"7M",IF(E46<=信息总览!$B$4,IF(I46>164,"伪名",""),IF(AND(E46>信息总览!$B$4,E46<26,G46>164),"伪名","")))) | X46: =IF(I46<140,0,IF(E46>23,0,I46-G46)) -> 8
A47: =W47 | B47: 1007737 | C47: Wang Dalei | E47: 36 | F47: 106 | G47: 106 | H47: =IFERROR(VLOOKUP(B47,球员对应球队!A:D,4,FALSE)-G47,"") -> 0 | I47: 118 | J47: GK | K47: 中国 | L47: AC Milan | M47: =VLOOKUP(L47,信息总览!C:E,3,FALSE) -> 甲级 | P47: =IF(F47<115,1,INT((F47-95)/10)) -> 1 | Q47: =IF(G47<115,1,INT((G47-95)/10)) -> 1 | R47: =IF(I47<115,1,INT((I47-95)/10)) -> 2 | S47: =IF(E47>信息总览!$B$4,Q47,IF(I47<140,Q47,(Q47+R47)/2)) -> 1 | T47: =IF(AND(J47="GK",W47<>""),0.1,IF(S47=1,0.1,IF((S47+V47)/2=1,0.1,IF(W47="8M",0.15,IF(W47="7M",0.13,IF(W47="伪名",0.11,IF(E47>信息总览!$B$4,IF(INT((G47-95)/10)>5,0.09,0.07),IF(INT((I47-95)/10)>5,0.09,0.07)))))))) -> 0.1 | U47: =S47*T47 -> 0.1 | V47: =IF(E47>25,IF(F47<115,1,INT((F47-95)/10)),(IF(F47<115,1,INT((F47-95)/10))+IF(I47<115,1,INT((I47-95)/10)))/2) -> 1 | W47: =IF(V47>=8,"8M",IF(V47>=7,"7M",IF(E47<=信息总览!$B$4,IF(I47>164,"伪名",""),IF(AND(E47>信息总览!$B$4,E47<26,G47>164),"伪名","")))) | X47: =IF(I47<140,0,IF(E47>23,0,I47-G47)) -> 0
A48: =W48 | B48: 67260204 | C48: Oihan Sancet | E48: 25 | F48: 156 | G48: 156 | H48: =IFERROR(VLOOKUP(B48,球员对应球队!A:D,4,FALSE)-G48,"") -> 0 | I48: 162 | J48: M/AMC | K48: 西班牙 | L48: AC Milan | M48: =VLOOKUP(L48,信息总览!C:E,3,FALSE) -> 甲级 | P48: =IF(F48<115,1,INT((F48-95)/10)) -> 6 | Q48: =IF(G48<115,1,INT((G48-95)/10)) -> 6 | R48: =IF(I48<115,1,INT((I48-95)/10)) -> 6 | S48: =IF(E48>信息总览!$B$4,Q48,IF(I48<140,Q48,(Q48+R48)/2)) -> 6 | T48: =IF(AND(J48="GK",W48<>""),0.1,IF(S48=1,0.1,IF((S48+V48)/2=1,0.1,IF(W48="8M",0.15,IF(W48="7M",0.13,IF(W48="伪名",0.11,IF(E48>信息总览!$B$4,IF(INT((G48-95)/10)>5,0.09,0.07),IF(INT((I48-95)/10)>5,0.09,0.07)))))))) -> 0.09 | U48: =S48*T48 -> 0.54 | V48: =IF(E48>25,IF(F48<115,1,INT((F48-95)/10)),(IF(F48<115,1,INT((F48-95)/10))+IF(I48<115,1,INT((I48-95)/10)))/2) -> 6 | W48: =IF(V48>=8,"8M",IF(V48>=7,"7M",IF(E48<=信息总览!$B$4,IF(I48>164,"伪名",""),IF(AND(E48>信息总览!$B$4,E48<26,G48>164),"伪名","")))) | X48: =IF(I48<140,0,IF(E48>23,0,I48-G48)) -> 0
A49: =W49 | B49: 76063258 | C49: Jhon Durán | E49: 21 | F49: 130 | G49: 130 | H49: =IFERROR(VLOOKUP(B49,球员对应球队!A:D,4,FALSE)-G49,"") -> 0 | I49: 150 | J49: ST | K49: 哥伦比亚 | L49: AC Milan | M49: =VLOOKUP(L49,信息总览!C:E,3,FALSE) -> 甲级 | P49: =IF(F49<115,1,INT((F49-95)/10)) -> 3 | Q49: =IF(G49<115,1,INT((G49-95)/10)) -> 3 | R49: =IF(I49<115,1,INT((I49-95)/10)) -> 5 | S49: =IF(E49>信息总览!$B$4,Q49,IF(I49<140,Q49,(Q49+R49)/2)) -> 4 | T49: =IF(AND(J49="GK",W49<>""),0.1,IF(S49=1,0.1,IF((S49+V49)/2=1,0.1,IF(W49="8M",0.15,IF(W49="7M",0.13,IF(W49="伪名",0.11,IF(E49>信息总览!$B$4,IF(INT((G49-95)/10)>5,0.09,0.07),IF(INT((I49-95)/10)>5,0.09,0.07)))))))) -> 0.07 | U49: =S49*T49 -> 0.28 | V49: =IF(E49>25,IF(F49<115,1,INT((F49-95)/10)),(IF(F49<115,1,INT((F49-95)/10))+IF(I49<115,1,INT((I49-95)/10)))/2) -> 4 | W49: =IF(V49>=8,"8M",IF(V49>=7,"7M",IF(E49<=信息总览!$B$4,IF(I49>164,"伪名",""),IF(AND(E49>信息总览!$B$4,E49<26,G49>164),"伪名","")))) | X49: =IF(I49<140,0,IF(E49>23,0,I49-G49)) -> 20
... A128: =W128 | B128: 2000466272 | C128: Brian Madjo | E128: 16 | F128: 95 | G128: 95 | H128: =IFERROR(VLOOKUP(B128,球员对应球队!A:D,4,FALSE)-G128,"") -> 0 | I128: 160 | J128: ST | K128: England,Luxembourg,Cameroon | L128: Aston Villa | M128: =VLOOKUP(L128,信息总览!C:E,3,FALSE) -> 超级 | P128: =IF(F128<115,1,INT((F128-95)/10)) -> 1 | Q128: =IF(G128<115,1,INT((G128-95)/10)) -> 1 | R128: =IF(I128<115,1,INT((I128-95)/10)) -> 6 | S128: =IF(E128>信息总览!$B$4,Q128,IF(I128<140,Q128,(Q128+R128)/2)) -> 3.5 | T128: =IF(AND(J128="GK",W128<>""),0.1,IF(S128=1,0.1,IF((S128+V128)/2=1,0.1,IF(W128="8M",0.15,IF(W128="7M",0.13,IF(W128="伪名",0.11,IF(E128>信息总览!$B$4,IF(INT((G128-95)/10)>5,0.09,0.07),IF(INT((I128-95)/10)>5,0.09,0.07)))))))) -> 0.09 | U128: =S128*T128 -> 0.315 | V128: =IF(E128>25,IF(F128<115,1,INT((F128-95)/10)),(IF(F128<115,1,INT((F128-95)/10))+IF(I128<115,1,INT((I128-95)/10)))/2) -> 3.5 | W128: =IF(V128>=8,"8M",IF(V128>=7,"7M",IF(E128<=信息总览!$B$4,IF(I128>164,"伪名",""),IF(AND(E128>信息总览!$B$4,E128<26,G128>164),"伪名","")))) | X128: =IF(I128<140,0,IF(E128>23,0,I128-G128)) -> 65
A129: =W129 | B129: 2000277689 | C129: Alysson Edward | E129: 19 | F129: 115 | G129: 115 | I129: 150 | J129: AMRL | K129: 巴西 | L129: Aston Villa | M129: =VLOOKUP(L129,信息总览!C:E,3,FALSE) -> 超级 | P129: =IF(F129<115,1,INT((F129-95)/10)) -> 2 | Q129: =IF(G129<115,1,INT((G129-95)/10)) -> 2 | R129: =IF(I129<115,1,INT((I129-95)/10)) -> 5 | S129: =IF(E129>信息总览!$B$4,Q129,IF(I129<140,Q129,(Q129+R129)/2)) -> 3.5 | T129: =IF(AND(J129="GK",W129<>""),0.1,IF(S129=1,0.1,IF((S129+V129)/2=1,0.1,IF(W129="8M",0.15,IF(W129="7M",0.13,IF(W129="伪名",0.11,IF(E129>信息总览!$B$4,IF(INT((G129-95)/10)>5,0.09,0.07),IF(INT((I129-95)/10)>5,0.09,0.07)))))))) -> 0.07 | U129: =S129*T129 -> 0.245 | V129: =IF(E129>25,IF(F129<115,1,INT((F129-95)/10)),(IF(F129<115,1,INT((F129-95)/10))+IF(I129<115,1,INT((I129-95)/10)))/2) -> 3.5 | W129: =IF(V129>=8,"8M",IF(V129>=7,"7M",IF(E129<=信息总览!$B$4,IF(I129>164,"伪名",""),IF(AND(E129>信息总览!$B$4,E129<26,G129>164),"伪名","")))) | X129: =IF(I129<140,0,IF(E129>23,0,I129-G129)) -> 35
A130: =W130 -> 伪名 | B130: 67296654 | C130: Alejandro Balde | E130: 21 | F130: 153 | G130: 160 | H130: =IFERROR(VLOOKUP(B130,球员对应球队!A:D,4,FALSE)-G130,"") -> 0 | I130: 170 | J130: D/WB/M/AM/L | K130: 西班牙 | L130: Barcelona | M130: =VLOOKUP(L130,信息总览!C:E,3,FALSE) -> 超级 | P130: =IF(F130<115,1,INT((F130-95)/10)) -> 5 | Q130: =IF(G130<115,1,INT((G130-95)/10)) -> 6 | R130: =IF(I130<115,1,INT((I130-95)/10)) -> 7 | S130: =IF(E130>信息总览!$B$4,Q130,IF(I130<140,Q130,(Q130+R130)/2)) -> 6.5 | T130: =IF(AND(J130="GK",W130<>""),0.1,IF(S130=1,0.1,IF((S130+V130)/2=1,0.1,IF(W130="8M",0.15,IF(W130="7M",0.13,IF(W130="伪名",0.11,IF(E130>信息总览!$B$4,IF(INT((G130-95)/10)>5,0.09,0.07),IF(INT((I130-95)/10)>5,0.09,0.07)))))))) -> 0.11 | U130: =S130*T130 -> 0.715 | V130: =IF(E130>25,IF(F130<115,1,INT((F130-95)/10)),(IF(F130<115,1,INT((F130-95)/10))+IF(I130<115,1,INT((I130-95)/10)))/2) -> 6 | W130: =IF(V130>=8,"8M",IF(V130>=7,"7M",IF(E130<=信息总览!$B$4,IF(I130>164,"伪名",""),IF(AND(E130>信息总览!$B$4,E130<26,G130>164),"伪名","")))) -> 伪名 | X130: =IF(I130<140,0,IF(E130>23,0,I130-G130)) -> 10
A131: =W131 | B131: 67221484 | C131: Iñaki Peña | E131: 26 | F131: 138 | G131: 138 | H131: =IFERROR(VLOOKUP(B131,球员对应球队!A:D,4,FALSE)-G131,"") -> 0 | I131: 150 | J131: GK | K131: 西班牙 | L131: Barcelona | M131: =VLOOKUP(L131,信息总览!C:E,3,FALSE) -> 超级 | P131: =IF(F131<115,1,INT((F131-95)/10)) -> 4 | Q131: =IF(G131<115,1,INT((G131-95)/10)) -> 4 | R131: =IF(I131<115,1,INT((I131-95)/10)) -> 5 | S131: =IF(E131>信息总览!$B$4,Q131,IF(I131<140,Q131,(Q131+R131)/2)) -> 4 | T131: =IF(AND(J131="GK",W131<>""),0.1,IF(S131=1,0.1,IF((S131+V131)/2=1,0.1,IF(W131="8M",0.15,IF(W131="7M",0.13,IF(W131="伪名",0.11,IF(E131>信息总览!$B$4,IF(INT((G131-95)/10)>5,0.09,0.07),IF(INT((I131-95)/10)>5,0.09,0.07)))))))) -> 0.07 | U131: =S131*T131 -> 0.28 | V131: =IF(E131>25,IF(F131<115,1,INT((F131-95)/10)),(IF(F131<115,1,INT((F131-95)/10))+IF(I131<115,1,INT((I131-95)/10)))/2) -> 4 | W131: =IF(V131>=8,"8M",IF(V131>=7,"7M",IF(E131<=信息总览!$B$4,IF(I131>164,"伪名",""),IF(AND(E131>信息总览!$B$4,E131<26,G131>164),"伪名","")))) | X131: =IF(I131<140,0,IF(E131>23,0,I131-G131)) -> 0
A132: =W132 -> 7M | B132: 67277675 | C132: Joan García | E132: 24 | F132: 155 | G132: 163 | H132: =IFERROR(VLOOKUP(B132,球员对应球队!A:D,4,FALSE)-G132,"") -> 0 | I132: 175 | J132: GK | K132: 西班牙 | L132: Barcelona | M132: =VLOOKUP(L132,信息总览!C:E,3,FALSE) -> 超级 | P132: =IF(F132<115,1,INT((F132-95)/10)) -> 6 | Q132: =IF(G132<115,1,INT((G132-95)/10)) -> 6 | R132: =IF(I132<115,1,INT((I132-95)/10)) -> 8 | S132: =IF(E132>信息总览!$B$4,Q132,IF(I132<140,Q132,(Q132+R132)/2)) -> 7 | T132: =IF(AND(J132="GK",W132<>""),0.1,IF(S132=1,0.1,IF((S132+V132)/2=1,0.1,IF(W132="8M",0.15,IF(W132="7M",0.13,IF(W132="伪名",0.11,IF(E132>信息总览!$B$4,IF(INT((G132-95)/10)>5,0.09,0.07),IF(INT((I132-95)/10)>5,0.09,0.07)))))))) -> 0.1 | U132: =S132*T132 -> 0.7 | V132: =IF(E132>25,IF(F132<115,1,INT((F132-95)/10)),(IF(F132<115,1,INT((F132-95)/10))+IF(I132<115,1,INT((I132-95)/10)))/2) -> 7 | W132: =IF(V132>=8,"8M",IF(V132>=7,"7M",IF(E132<=信息总览!$B$4,IF(I132>164,"伪名",""),IF(AND(E132>信息总览!$B$4,E132<26,G132>164),"伪名","")))) -> 7M | X132: =IF(I132<140,0,IF(E132>23,0,I132-G132)) -> 0
A133: =W133 -> 7M | B133: 48036304 | C133: Jules Koundé | D133: 26 | E133: 25 | F133: 162 | G133: 173 | H133: =IFERROR(VLOOKUP(B133,球员对应球队!A:D,4,FALSE)-G133,"") -> 0 | I133: 175 | J133: D/RC | K133: 法国 | L133: Barcelona | M133: =VLOOKUP(L133,信息总览!C:E,3,FALSE) -> 超级 | P133: =IF(F133<115,1,INT((F133-95)/10)) -> 6 | Q133: =IF(G133<115,1,INT((G133-95)/10)) -> 7 | R133: =IF(I133<115,1,INT((I133-95)/10)) -> 8 | S133: =IF(E133>信息总览!$B$4,Q133,IF(I133<140,Q133,(Q133+R133)/2)) -> 7 | T133: =IF(AND(J133="GK",W133<>""),0.1,IF(S133=1,0.1,IF((S133+V133)/2=1,0.1,IF(W133="8M",0.15,IF(W133="7M",0.13,IF(W133="伪名",0.11,IF(E133>信息总览!$B$4,IF(INT((G133-95)/10)>5,0.09,0.07),IF(INT((I133-95)/10)>5,0.09,0.07)))))))) -> 0.13 | U133: =S133*T133 -> 0.91 | V133: =IF(E133>25,IF(F133<115,1,INT((F133-95)/10)),(IF(F133<115,1,INT((F133-95)/10))+IF(I133<115,1,INT((I133-95)/10)))/2) -> 7 | W133: =IF(V133>=8,"8M",IF(V133>=7,"7M",IF(E133<=信息总览!$B$4,IF(I133>164,"伪名",""),IF(AND(E133>信息总览!$B$4,E133<26,G133>164),"伪名","")))) -> 7M | X133: =IF(I133<140,0,IF(E133>23,0,I133-G133)) -> 0
A134: =W134 | B134: 2000190386 | C134: Karl Etta Eyong | E134: 21 | F134: 138 | G134: 144 | H134: =IFERROR(VLOOKUP(B134,球员对应球队!A:D,4,FALSE)-G134,"") -> 0 | I134: 162 | J134: ST | K134: 喀麦隆 | L134: Barcelona | M134: =VLOOKUP(L134,信息总览!C:E,3,FALSE) -> 超级 | P134: =IF(F134<115,1,INT((F134-95)/10)) -> 4 | Q134: =IF(G134<115,1,INT((G134-95)/10)) -> 4 | R134: =IF(I134<115,1,INT((I134-95)/10)) -> 6 | S134: =IF(E134>信息总览!$B$4,Q134,IF(I134<140,Q134,(Q134+R134)/2)) -> 5 | T134: =IF(AND(J134="GK",W134<>""),0.1,IF(S134=1,0.1,IF((S134+V134)/2=1,0.1,IF(W134="8M",0.15,IF(W134="7M",0.13,IF(W134="伪名",0.11,IF(E134>信息总览!$B$4,IF(INT((G134-95)/10)>5,0.09,0.07),IF(INT((I134-95)/10)>5,0.09,0.07)))))))) -> 0.09 | U134: =S134*T134 -> 0.45 | V134: =IF(E134>25,IF(F134<115,1,INT((F134-95)/10)),(IF(F134<115,1,INT((F134-95)/10))+IF(I134<115,1,INT((I134-95)/10)))/2) -> 5 | W134: =IF(V134>=8,"8M",IF(V134>=7,"7M",IF(E134<=信息总览!$B$4,IF(I134>164,"伪名",""),IF(AND(E134>信息总览!$B$4,E134<26,G134>164),"伪名","")))) | X134: =IF(I134<140,0,IF(E134>23,0,I134-G134)) -> 18
A135: =W135 | B135: 78074598 | C135: Leonardo Fernández | D135: 26 | E135: 25 | F135: 129 | G135: 140 | H135: =IFERROR(VLOOKUP(B135,球员对应球队!A:D,4,FALSE)-G135,"") -> 0 | I135: 142 | J135: AM/RC | K135: 乌拉圭 | L135: Barcelona | M135: =VLOOKUP(L135,信息总览!C:E,3,FALSE) -> 超级 | P135: =IF(F135<115,1,INT((F135-95)/10)) -> 3 | Q135: =IF(G135<115,1,INT((G135-95)/10)) -> 4 | R135: =IF(I135<115,1,INT((I135-95)/10)) -> 4 | S135: =IF(E135>信息总览!$B$4,Q135,IF(I135<140,Q135,(Q135+R135)/2)) -> 4 | T135: =IF(AND(J135="GK",W135<>""),0.1,IF(S135=1,0.1,IF((S135+V135)/2=1,0.1,IF(W135="8M",0.15,IF(W135="7M",0.13,IF(W135="伪名",0.11,IF(E135>信息总览!$B$4,IF(INT((G135-95)/10)>5,0.09,0.07),IF(INT((I135-95)/10)>5,0.09,0.07)))))))) -> 0.07 | U135: =S135*T135 -> 0.28 | V135: =IF(E135>25,IF(F135<115,1,INT((F135-95)/10)),(IF(F135<115,1,INT((F135-95)/10))+IF(I135<115,1,INT((I135-95)/10)))/2) -> 3.5 | W135: =IF(V135>=8,"8M",IF(V135>=7,"7M",IF(E135<=信息总览!$B$4,IF(I135>164,"伪名",""),IF(AND(E135>信息总览!$B$4,E135<26,G135>164),"伪名","")))) | X135: =IF(I135<140,0,IF(E135>23,0,I135-G135)) -> 0
A136: =W136 | B136: 2000295603 | C136: Marc Bernal | E136: 18 | F136: 125 | G136: 135 | H136: =IFERROR(VLOOKUP(B136,球员对应球队!A:D,4,FALSE)-G136,"") -> 0 | I136: 154 | J136: DM/MC | K136: 西班牙 | L136: Barcelona | M136: =VLOOKUP(L136,信息总览!C:E,3,FALSE) -> 超级 | P136: =IF(F136<115,1,INT((F136-95)/10)) -> 3 | Q136: =IF(G136<115,1,INT((G136-95)/10)) -> 4 | R136: =IF(I136<115,1,INT((I136-95)/10)) -> 5 | S136: =IF(E136>信息总览!$B$4,Q136,IF(I136<140,Q136,(Q136+R136)/2)) -> 4.5 | T136: =IF(AND(J136="GK",W136<>""),0.1,IF(S136=1,0.1,IF((S136+V136)/2=1,0.1,IF(W136="8M",0.15,IF(W136="7M",0.13,IF(W136="伪名",0.11,IF(E136>信息总览!$B$4,IF(INT((G136-95)/10)>5,0.09,0.07),IF(INT((I136-95)/10)>5,0.09,0.07)))))))) -> 0.07 | U136: =S136*T136 -> 0.315 | V136: =IF(E136>25,IF(F136<115,1,INT((F136-95)/10)),(IF(F136<115,1,INT((F136-95)/10))+IF(I136<115,1,INT((I136-95)/10)))/2) -> 4 | W136: =IF(V136>=8,"8M",IF(V136>=7,"7M",IF(E136<=信息总览!$B$4,IF(I136>164,"伪名",""),IF(AND(E136>信息总览!$B$4,E136<26,G136>164),"伪名","")))) | X136: =IF(I136<140,0,IF(E136>23,0,I136-G136)) -> 19
A137: =W137 -> 伪名 | B137: 2000296497 | C137: Pau Cubarsí | E137: 18 | F137: 154 | G137: 164 | H137: =IFERROR(VLOOKUP(B137,球员对应球队!A:D,4,FALSE)-G137,"") -> 0 | I137: 174 | J137: D/C | K137: 西班牙 | L137: Barcelona | M137: =VLOOKUP(L137,信息总览!C:E,3,FALSE) -> 超级 | P137: =IF(F137<115,1,INT((F137-95)/10)) -> 5 | Q137: =IF(G137<115,1,INT((G137-95)/10)) -> 6 | R137: =IF(I137<115,1,INT((I137-95)/10)) -> 7 | S137: =IF(E137>信息总览!$B$4,Q137,IF(I137<140,Q137,(Q137+R137)/2)) -> 6.5 | T137: =IF(AND(J137="GK",W137<>""),0.1,IF(S137=1,0.1,IF((S137+V137)/2=1,0.1,IF(W137="8M",0.15,IF(W137="7M",0.13,IF(W137="伪名",0.11,IF(E137>信息总览!$B$4,IF(INT((G137-95)/10)>5,0.09,0.07),IF(INT((I137-95)/10)>5,0.09,0.07)))))))) -> 0.11 | U137: =S137*T137 -> 0.715 | V137: =IF(E137>25,IF(F137<115,1,INT((F137-95)/10)),(IF(F137<115,1,INT((F137-95)/10))+IF(I137<115,1,INT((I137-95)/10)))/2) -> 6 | W137: =IF(V137>=8,"8M",IF(V137>=7,"7M",IF(E137<=信息总览!$B$4,IF(I137>164,"伪名",""),IF(AND(E137>信息总览!$B$4,E137<26,G137>164),"伪名","")))) -> 伪名 | X137: =IF(I137<140,0,IF(E137>23,0,I137-G137)) -> 10
A138: =W138 -> 伪名 | B138: 86066853 | C138: Piero Hincapié | E138: 23 | F138: 152 | G138: 163 | H138: =IFERROR(VLOOKUP(B138,球员对应球队!A:D,4,FALSE)-G138,"") -> 0 | I138: 168 | J138: D/WB/LC | K138: 厄瓜多尔 | L138: Barcelona | M138: =VLOOKUP(L138,信息总览!C:E,3,FALSE) -> 超级 | P138: =IF(F138<115,1,INT((F138-95)/10)) -> 5 | Q138: =IF(G138<115,1,INT((G138-95)/10)) -> 6 | R138: =IF(I138<115,1,INT((I138-95)/10)) -> 7 | S138: =IF(E138>信息总览!$B$4,Q138,IF(I138<140,Q138,(Q138+R138)/2)) -> 6.5 | T138: =IF(AND(J138="GK",W138<>""),0.1,IF(S138=1,0.1,IF((S138+V138)/2=1,0.1,IF(W138="8M",0.15,IF(W138="7M",0.13,IF(W138="伪名",0.11,IF(E138>信息总览!$B$4,IF(INT((G138-95)/10)>5,0.09,0.07),IF(INT((I138-95)/10)>5,0.09,0.07)))))))) -> 0.11 | U138: =S138*T138 -> 0.715 | V138: =IF(E138>25,IF(F138<115,1,INT((F138-95)/10)),(IF(F138<115,1,INT((F138-95)/10))+IF(I138<115,1,INT((I138-95)/10)))/2) -> 6 | W138: =IF(V138>=8,"8M",IF(V138>=7,"7M",IF(E138<=信息总览!$B$4,IF(I138>164,"伪名",""),IF(AND(E138>信息总览!$B$4,E138<26,G138>164),"伪名","")))) -> 伪名 | X138: =IF(I138<140,0,IF(E138>23,0,I138-G138)) -> 5
A139: =W139 | B139: 2000088490 | C139: Roony Bardghji | E139: 18 | F139: 121 | G139: 128 | H139: =IFERROR(VLOOKUP(B139,球员对应球队!A:D,4,FALSE)-G139,"") -> 0 | I139: 145 | J139: AM/R | K139: 瑞典 | L139: Barcelona | M139: =VLOOKUP(L139,信息总览!C:E,3,FALSE) -> 超级 | P139: =IF(F139<115,1,INT((F139-95)/10)) -> 2 | Q139: =IF(G139<115,1,INT((G139-95)/10)) -> 3 | R139: =IF(I139<115,1,INT((I139-95)/10)) -> 5 | S139: =IF(E139>信息总览!$B$4,Q139,IF(I139<140,Q139,(Q139+R139)/2)) -> 4 | T139: =IF(AND(J139="GK",W139<>""),0.1,IF(S139=1,0.1,IF((S139+V139)/2=1,0.1,IF(W139="8M",0.15,IF(W139="7M",0.13,IF(W139="伪名",0.11,IF(E139>信息总览!$B$4,IF(INT((G139-95)/10)>5,0.09,0.07),IF(INT((I139-95)/10)>5,0.09,0.07)))))))) -> 0.07 | U139: =S139*T139 -> 0.28 | V139: =IF(E139>25,IF(F139<115,1,INT((F139-95)/10)),(IF(F139<115,1,INT((F139-95)/10))+IF(I139<115,1,INT((I139-95)/10)))/2) -> 3.5 | W139: =IF(V139>=8,"8M",IF(V139>=7,"7M",IF(E139<=信息总览!$B$4,IF(I139>164,"伪名",""),IF(AND(E139>信息总览!$B$4,E139<26,G139>164),"伪名","")))) | X139: =IF(I139<140,0,IF(E139>23,0,I139-G139)) -> 17
A140: =W140 | B140: 78085068 | C140: Ronald Araujo | E140: 26 | F140: 153 | G140: 153 | H140: =IFERROR(VLOOKUP(B140,球员对应球队!A:D,4,FALSE)-G140,"") -> 0 | I140: 175 | J140: D/RC | K140: 乌拉圭 | L140: Barcelona | M140: =VLOOKUP(L140,信息总览!C:E,3,FALSE) -> 超级 | P140: =IF(F140<115,1,INT((F140-95)/10)) -> 5 | Q140: =IF(G140<115,1,INT((G140-95)/10)) -> 5 | R140: =IF(I140<115,1,INT((I140-95)/10)) -> 8 | S140: =IF(E140>信息总览!$B$4,Q140,IF(I140<140,Q140,(Q140+R140)/2)) -> 5 | T140: =IF(AND(J140="GK",W140<>""),0.1,IF(S140=1,0.1,IF((S140+V140)/2=1,0.1,IF(W140="8M",0.15,IF(W140="7M",0.13,IF(W140="伪名",0.11,IF(E140>信息总览!$B$4,IF(INT((G140-95)/10)>5,0.09,0.07),IF(INT((I140-95)/10)>5,0.09,0.07)))))))) -> 0.07 | U140: =S140*T140 -> 0.35 | V140: =IF(E140>25,IF(F140<115,1,INT((F140-95)/10)),(IF(F140<115,1,INT((F140-95)/10))+IF(I140<115,1,INT((I140-95)/10)))/2) -> 5 | W140: =IF(V140>=8,"8M",IF(V140>=7,"7M",IF(E140<=信息总览!$B$4,IF(I140>164,"伪名",""),IF(AND(E140>信息总览!$B$4,E140<26,G140>164),"伪名","")))) | X140: =IF(I140<140,0,IF(E140>23,0,I140-G140)) -> 0
A141: =W141 | B141: 2000101061 | C141: Gerard Martín | E141: 23 | F141: 140 | G141: 140 | H141: =IFERROR(VLOOKUP(B141,球员对应球队!A:D,4,FALSE)-G141,"") -> 0 | I141: 150 | J141: D/WB LC | K141: Spain | L141: Barcelona | M141: =VLOOKUP(L141,信息总览!C:E,3,FALSE) -> 超级 | P141: =IF(F141<115,1,INT((F141-95)/10)) -> 4 | Q141: =IF(G141<115,1,INT((G141-95)/10)) -> 4 | R141: =IF(I141<115,1,INT((I141-95)/10)) -> 5 | S141: =IF(E141>信息总览!$B$4,Q141,IF(I141<140,Q141,(Q141+R141)/2)) -> 4.5 | T141: =IF(AND(J141="GK",W141<>""),0.1,IF(S141=1,0.1,IF((S141+V141)/2=1,0.1,IF(W141="8M",0.15,IF(W141="7M",0.13,IF(W141="伪名",0.11,IF(E141>信息总览!$B$4,IF(INT((G141-95)/10)>5,0.09,0.07),IF(INT((I141-95)/10)>5,0.09,0.07)))))))) -> 0.07 | U141: =S141*T141 -> 0.315 | V141: =IF(E141>25,IF(F141<115,1,INT((F141-95)/10)),(IF(F141<115,1,INT((F141-95)/10))+IF(I141<115,1,INT((I141-95)/10)))/2) -> 4.5 | W141: =IF(V141>=8,"8M",IF(V141>=7,"7M",IF(E141<=信息总览!$B$4,IF(I141>164,"伪名",""),IF(AND(E141>信息总览!$B$4,E141<26,G141>164),"伪名","")))) | X141: =IF(I141<140,0,IF(E141>23,0,I141-G141)) -> 10
A142: =W142 | B142: 2000312673 | C142: Jesús Rodriguez | E142: 19 | F142: 134 | G142: 140 | H142: =IFERROR(VLOOKUP(B142,球员对应球队!A:D,4,FALSE)-G142,"") -> 0 | I142: 156 | J142: M/AMLC | K142: 西班牙 | L142: Barcelona | M142: =VLOOKUP(L142,信息总览!C:E,3,FALSE) -> 超级 | P142: =IF(F142<115,1,INT((F142-95)/10)) -> 3 | Q142: =IF(G142<115,1,INT((G142-95)/10)) -> 4 | R142: =IF(I142<115,1,INT((I142-95)/10)) -> 6 | S142: =IF(E142>信息总览!$B$4,Q142,IF(I142<140,Q142,(Q142+R142)/2)) -> 5 | T142: =IF(AND(J142="GK",W142<>""),0.1,IF(S142=1,0.1,IF((S142+V142)/2=1,0.1,IF(W142="8M",0.15,IF(W142="7M",0.13,IF(W142="伪名",0.11,IF(E142>信息总览!$B$4,IF(INT((G142-95)/10)>5,0.09,0.07),IF(INT((I142-95)/10)>5,0.09,0.07)))))))) -> 0.09 | U142: =S142*T142 -> 0.45 | V142: =IF(E142>25,IF(F142<115,1,INT((F142-95)/10)),(IF(F142<115,1,INT((F142-95)/10))+IF(I142<115,1,INT((I142-95)/10)))/2) -> 4.5 | W142: =IF(V142>=8,"8M",IF(V142>=7,"7M",IF(E142<=信息总览!$B$4,IF(I142>164,"伪名",""),IF(AND(E142>信息总览!$B$4,E142<26,G142>164),"伪名","")))) | X142: =IF(I142<140,0,IF(E142>23,0,I142-G142)) -> 16
A143: =W143 | B143: 2000183245 | C143: Martim Fernandes | E143: 19 | F143: 130 | G143: 134 | H143: =IFERROR(VLOOKUP(B143,球员对应球队!A:D,4,FALSE)-G143,"") -> 0 | I143: 144 | J143: D/WB/R | K143: 葡萄牙 | L143: Barcelona | M143: =VLOOKUP(L143,信息总览!C:E,3,FALSE) -> 超级 | P143: =IF(F143<115,1,INT((F143-95)/10)) -> 3 | Q143: =IF(G143<115,1,INT((G143-95)/10)) -> 3 | R143: =IF(I143<115,1,INT((I143-95)/10)) -> 4 | S143: =IF(E143>信息总览!$B$4,Q143,IF(I143<140,Q143,(Q143+R143)/2)) -> 3.5 | T143: =IF(AND(J143="GK",W143<>""),0.1,IF(S143=1,0.1,IF((S143+V143)/2=1,0.1,IF(W143="8M",0.15,IF(W143="7M",0.13,IF(W143="伪名",0.11,IF(E143>信息总览!$B$4,IF(INT((G143-95)/10)>5,0.09,0.07),IF(INT((I143-95)/10)>5,0.09,0.07)))))))) -> 0.07 | U143: =S143*T143 -> 0.245 | V143: =IF(E143>25,IF(F143<115,1,INT((F143-95)/10)),(IF(F143<115,1,INT((F143-95)/10))+IF(I143<115,1,INT((I143-95)/10)))/2) -> 3.5 | W143: =IF(V143>=8,"8M",IF(V143>=7,"7M",IF(E143<=信息总览!$B$4,IF(I143>164,"伪名",""),IF(AND(E143>信息总览!$B$4,E143<26,G143>164),"伪名","")))) | X143: =IF(I143<140,0,IF(E143>23,0,I143-G143)) -> 10
A144: =W144 | B144: 67277845 | C144: Borja Sainz | E144: 24 | F144: 142 | G144: 154 | H144: =IFERROR(VLOOKUP(B144,球员对应球队!A:D,4,FALSE)-G144,"") -> 0 | I144: 154 | J144: AM/L | K144: Spain,Pays Basque | L144: Barcelona | M144: =VLOOKUP(L144,信息总览!C:E,3,FALSE) -> 超级 | P144: =IF(F144<115,1,INT((F144-95)/10)) -> 4 | Q144: =IF(G144<115,1,INT((G144-95)/10)) -> 5 | R144: =IF(I144<115,1,INT((I144-95)/10)) -> 5 | S144: =IF(E144>信息总览!$B$4,Q144,IF(I144<140,Q144,(Q144+R144)/2)) -> 5 | T144: =IF(AND(J144="GK",W144<>""),0.1,IF(S144=1,0.1,IF((S144+V144)/2=1,0.1,IF(W144="8M",0.15,IF(W144="7M",0.13,IF(W144="伪名",0.11,IF(E144>信息总览!$B$4,IF(INT((G144-95)/10)>5,0.09,0.07),IF(INT((I144-95)/10)>5,0.09,0.07)))))))) -> 0.07 | U144: =S144*T144 -> 0.35 | V144: =IF(E144>25,IF(F144<115,1,INT((F144-95)/10)),(IF(F144<115,1,INT((F144-95)/10))+IF(I144<115,1,INT((I144-95)/10)))/2) -> 4.5 | W144: =IF(V144>=8,"8M",IF(V144>=7,"7M",IF(E144<=信息总览!$B$4,IF(I144>164,"伪名",""),IF(AND(E144>信息总览!$B$4,E144<26,G144>164),"伪名","")))) | X144: =IF(I144<140,0,IF(E144>23,0,I144-G144)) -> 0
A145: =W145 -> 8M | B145: 19242277 | C145: Raphinha | E145: 28 | F145: 175 | G145: 175 | H145: =IFERROR(VLOOKUP(B145,球员对应球队!A:D,4,FALSE)-G145,"") -> 0 | I145: 177 | J145: M/AMRL | K145: 巴西 | L145: Barcelona | M145: =VLOOKUP(L145,信息总览!C:E,3,FALSE) -> 超级 | P145: =IF(F145<115,1,INT((F145-95)/10)) -> 8 | Q145: =IF(G145<115,1,INT((G145-95)/10)) -> 8 | R145: =IF(I145<115,1,INT((I145-95)/10)) -> 8 | S145: =IF(E145>信息总览!$B$4,Q145,IF(I145<140,Q145,(Q145+R145)/2)) -> 8 | T145: =IF(AND(J145="GK",W145<>""),0.1,IF(S145=1,0.1,IF((S145+V145)/2=1,0.1,IF(W145="8M",0.15,IF(W145="7M",0.13,IF(W145="伪名",0.11,IF(E145>信息总览!$B$4,IF(INT((G145-95)/10)>5,0.09,0.07),IF(INT((I145-95)/10)>5,0.09,0.07)))))))) -> 0.15 | U145: =S145*T145 -> 1.2 | V145: =IF(E145>25,IF(F145<115,1,INT((F145-95)/10)),(IF(F145<115,1,INT((F145-95)/10))+IF(I145<115,1,INT((I145-95)/10)))/2) -> 8 | W145: =IF(V145>=8,"8M",IF(V145>=7,"7M",IF(E145<=信息总览!$B$4,IF(I145>164,"伪名",""),IF(AND(E145>信息总览!$B$4,E145<26,G145>164),"伪名","")))) -> 8M | X145: =IF(I145<140,0,IF(E145>23,0,I145-G145)) -> 0
A146: =W146 | B146: 2000307251 | C146: Karetsas, Konstantinos | E146: 17 | F146: 113 | G146: 113 | H146: =IFERROR(VLOOKUP(B146,球员对应球队!A:D,4,FALSE)-G146,"") -> 0 | I146: 145 | J146: AM/C | K146: 希腊 | L146: Barcelona | M146: =VLOOKUP(L146,信息总览!C:E,3,FALSE) -> 超级 | P146: =IF(F146<115,1,INT((F146-95)/10)) -> 1 | Q146: =IF(G146<115,1,INT((G146-95)/10)) -> 1 | R146: =IF(I146<115,1,INT((I146-95)/10)) -> 5 | S146: =IF(E146>信息总览!$B$4,Q146,IF(I146<140,Q146,(Q146+R146)/2)) -> 3 | T146: =IF(AND(J146="GK",W146<>""),0.1,IF(S146=1,0.1,IF((S146+V146)/2=1,0.1,IF(W146="8M",0.15,IF(W146="7M",0.13,IF(W146="伪名",0.11,IF(E146>信息总览!$B$4,IF(INT((G146-95)/10)>5,0.09,0.07),IF(INT((I146-95)/10)>5,0.09,0.07)))))))) -> 0.07 | U146: =S146*T146 -> 0.21 | V146: =IF(E146>25,IF(F146<115,1,INT((F146-95)/10)),(IF(F146<115,1,INT((F146-95)/10))+IF(I146<115,1,INT((I146-95)/10)))/2) -> 3 | W146: =IF(V146>=8,"8M",IF(V146>=7,"7M",IF(E146<=信息总览!$B$4,IF(I146>164,"伪名",""),IF(AND(E146>信息总览!$B$4,E146<26,G146>164),"伪名","")))) | X146: =IF(I146<140,0,IF(E146>23,0,I146-G146)) -> 32
A147: =W147 | B147: 28128173 | C147: William Osula | E147: 22 | F147: 126 | G147: 126 | H147: =IFERROR(VLOOKUP(B147,球员对应球队!A:D,4,FALSE)-G147,"") -> 0 | I147: 145 | J147: S RL | K147: Denmark,Nigeria,England | L147: Barcelona | M147: =VLOOKUP(L147,信息总览!C:E,3,FALSE) -> 超级 | P147: =IF(F147<115,1,INT((F147-95)/10)) -> 3 | Q147: =IF(G147<115,1,INT((G147-95)/10)) -> 3 | R147: =IF(I147<115,1,INT((I147-95)/10)) -> 5 | S147: =IF(E147>信息总览!$B$4,Q147,IF(I147<140,Q147,(Q147+R147)/2)) -> 4 | T147: =IF(AND(J147="GK",W147<>""),0.1,IF(S147=1,0.1,IF((S147+V147)/2=1,0.1,IF(W147="8M",0.15,IF(W147="7M",0.13,IF(W147="伪名",0.11,IF(E147>信息总览!$B$4,IF(INT((G147-95)/10)>5,0.09,0.07),IF(INT((I147-95)/10)>5,0.09,0.07)))))))) -> 0.07 | U147: =S147*T147 -> 0.28 | V147: =IF(E147>25,IF(F147<115,1,INT((F147-95)/10)),(IF(F147<115,1,INT((F147-95)/10))+IF(I147<115,1,INT((I147-95)/10)))/2) -> 4 | W147: =IF(V147>=8,"8M",IF(V147>=7,"7M",IF(E147<=信息总览!$B$4,IF(I147>164,"伪名",""),IF(AND(E147>信息总览!$B$4,E147<26,G147>164),"伪名","")))) | X147: =IF(I147<140,0,IF(E147>23,0,I147-G147)) -> 19
A148: =W148 | B148: 91194540 | C148: Anton Stach | E148: 26 | F148: 142 | G148: 142 | H148: =IFERROR(VLOOKUP(B148,球员对应球队!A:D,4,FALSE)-G148,"") -> 0 | I148: 148 | J148: DM/MC | K148: Germany | L148: Barcelona | M148: =VLOOKUP(L148,信息总览!C:E,3,FALSE) -> 超级 | P148: =IF(F148<115,1,INT((F148-95)/10)) -> 4 | Q148: =IF(G148<115,1,INT((G148-95)/10)) -> 4 | R148: =IF(I148<115,1,INT((I148-95)/10)) -> 5 | S148: =IF(E148>信息总览!$B$4,Q148,IF(I148<140,Q148,(Q148+R148)/2)) -> 4 | T148: =IF(AND(J148="GK",W148<>""),0.1,IF(S148=1,0.1,IF((S148+V148)/2=1,0.1,IF(W148="8M",0.15,IF(W148="7M",0.13,IF(W148="伪名",0.11,IF(E148>信息总览!$B$4,IF(INT((G148-95)/10)>5,0.09,0.07),IF(INT((I148-95)/10)>5,0.09,0.07)))))))) -> 0.07 | U148: =S148*T148 -> 0.28 | V148: =IF(E148>25,IF(F148<115,1,INT((F148-95)/10)),(IF(F148<115,1,INT((F148-95)/10))+IF(I148<115,1,INT((I148-95)/10)))/2) -> 4 | W148: =IF(V148>=8,"8M",IF(V148>=7,"7M",IF(E148<=信息总览!$B$4,IF(I148>164,"伪名",""),IF(AND(E148>信息总览!$B$4,E148<26,G148>164),"伪名","")))) | X148: =IF(I148<140,0,IF(E148>23,0,I148-G148)) -> 0
A149: =W149 | B149: 2000339863 | C149: Caleb Yirenkyi | E149: 19 | F149: 110 | G149: 110 | I149: 150 | J149: DM/M C | K149: Ghana | L149: Barcelona | M149: =VLOOKUP(L149,信息总览!C:E,3,FALSE) -> 超级 | P149: =IF(F149<115,1,INT((F149-95)/10)) -> 1 | Q149: =IF(G149<115,1,INT((G149-95)/10)) -> 1 | R149: =IF(I149<115,1,INT((I149-95)/10)) -> 5 | S149: =IF(E149>信息总览!$B$4,Q149,IF(I149<140,Q149,(Q149+R149)/2)) -> 3 | T149: =IF(AND(J149="GK",W149<>""),0.1,IF(S149=1,0.1,IF((S149+V149)/2=1,0.1,IF(W149="8M",0.15,IF(W149="7M",0.13,IF(W149="伪名",0.11,IF(E149>信息总览!$B$4,IF(INT((G149-95)/10)>5,0.09,0.07),IF(INT((I149-95)/10)>5,0.09,0.07)))))))) -> 0.07 | U149: =S149*T149 -> 0.21 | V149: =IF(E149>25,IF(F149<115,1,INT((F149-95)/10)),(IF(F149<115,1,INT((F149-95)/10))+IF(I149<115,1,INT((I149-95)/10)))/2) -> 3 | W149: =IF(V149>=8,"8M",IF(V149>=7,"7M",IF(E149<=信息总览!$B$4,IF(I149>164,"伪名",""),IF(AND(E149>信息总览!$B$4,E149<26,G149>164),"伪名","")))) | X149: =IF(I149<140,0,IF(E149>23,0,I149-G149)) -> 40
A150: =W150 -> 8M | B150: 19058734 | C150: Alisson | E150: 32 | F150: 180 | G150: 180 | H150: =IFERROR(VLOOKUP(B150,球员对应球队!A:D,4,FALSE)-G150,"") -> 0 | I150: 182 | J150: GK | K150: 巴西 | L150: Bayer 04 | M150: =VLOOKUP(L150,信息总览!C:E,3,FALSE) -> 超级 | P150: =IF(F150<115,1,INT((F150-95)/10)) -> 8 | Q150: =IF(G150<115,1,INT((G150-95)/10)) -> 8 | R150: =IF(I150<115,1,INT((I150-95)/10)) -> 8 | S150: =IF(E150>信息总览!$B$4,Q150,IF(I150<140,Q150,(Q150+R150)/2)) -> 8 | T150: =IF(AND(J150="GK",W150<>""),0.1,IF(S150=1,0.1,IF((S150+V150)/2=1,0.1,IF(W150="8M",0.15,IF(W150="7M",0.13,IF(W150="伪名",0.11,IF(E150>信息总览!$B$4,IF(INT((G150-95)/10)>5,0.09,0.07),IF(INT((I150-95)/10)>5,0.09,0.07)))))))) -> 0.1 | U150: =S150*T150 -> 0.8 | V150: =IF(E150>25,IF(F150<115,1,INT((F150-95)/10)),(IF(F150<115,1,INT((F150-95)/10))+IF(I150<115,1,INT((I150-95)/10)))/2) -> 8 | W150: =IF(V150>=8,"8M",IF(V150>=7,"7M",IF(E150<=信息总览!$B$4,IF(I150>164,"伪名",""),IF(AND(E150>信息总览!$B$4,E150<26,G150>164),"伪名","")))) -> 8M | X150: =IF(I150<140,0,IF(E150>23,0,I150-G150)) -> 0
A151: =W151 | B151: 48042658 | C151: Bryan Mbeumo | E151: 25 | F151: 155 | G151: 160 | H151: =IFERROR(VLOOKUP(B151,球员对应球队!A:D,4,FALSE)-G151,"") -> 0 | I151: 160 | J151: M/AMRL/ST | K151: 喀麦隆 | L151: Bayer 04 | M151: =VLOOKUP(L151,信息总览!C:E,3,FALSE) -> 超级 | P151: =IF(F151<115,1,INT((F151-95)/10)) -> 6 | Q151: =IF(G151<115,1,INT((G151-95)/10)) -> 6 | R151: =IF(I151<115,1,INT((I151-95)/10)) -> 6 | S151: =IF(E151>信息总览!$B$4,Q151,IF(I151<140,Q151,(Q151+R151)/2)) -> 6 | T151: =IF(AND(J151="GK",W151<>""),0.1,IF(S151=1,0.1,IF((S151+V151)/2=1,0.1,IF(W151="8M",0.15,IF(W151="7M",0.13,IF(W151="伪名",0.11,IF(E151>信息总览!$B$4,IF(INT((G151-95)/10)>5,0.09,0.07),IF(INT((I151-95)/10)>5,0.09,0.07)))))))) -> 0.09 | U151: =S151*T151 -> 0.54 | V151: =IF(E151>25,IF(F151<115,1,INT((F151-95)/10)),(IF(F151<115,1,INT((F151-95)/10))+IF(I151<115,1,INT((I151-95)/10)))/2) -> 6 | W151: =IF(V151>=8,"8M",IF(V151>=7,"7M",IF(E151<=信息总览!$B$4,IF(I151>164,"伪名",""),IF(AND(E151>信息总览!$B$4,E151<26,G151>164),"伪名","")))) | X151: =IF(I151<140,0,IF(E151>23,0,I151-G151)) -> 0
A152: =W152 | B152: 2000385886 | C152: Diego León | E152: 18 | F152: 101 | G152: 101 | H152: =IFERROR(VLOOKUP(B152,球员对应球队!A:D,4,FALSE)-G152,"") -> 0 | I152: 160 | J152: D/WB/L | K152: 巴拉圭 | L152: Bayer 04 | M152: =VLOOKUP(L152,信息总览!C:E,3,FALSE) -> 超级 | P152: =IF(F152<115,1,INT((F152-95)/10)) -> 1 | Q152: =IF(G152<115,1,INT((G152-95)/10)) -> 1 | R152: =IF(I152<115,1,INT((I152-95)/10)) -> 6 | S152: =IF(E152>信息总览!$B$4,Q152,IF(I152<140,Q152,(Q152+R152)/2)) -> 3.5 | T152: =IF(AND(J152="GK",W152<>""),0.1,IF(S152=1,0.1,IF((S152+V152)/2=1,0.1,IF(W152="8M",0.15,IF(W152="7M",0.13,IF(W152="伪名",0.11,IF(E152>信息总览!$B$4,IF(INT((G152-95)/10)>5,0.09,0.07),IF(INT((I152-95)/10)>5,0.09,0.07)))))))) -> 0.09 | U152: =S152*T152 -> 0.315 | V152: =IF(E152>25,IF(F152<115,1,INT((F152-95)/10)),(IF(F152<115,1,INT((F152-95)/10))+IF(I152<115,1,INT((I152-95)/10)))/2) -> 3.5 | W152: =IF(V152>=8,"8M",IF(V152>=7,"7M",IF(E152<=信息总览!$B$4,IF(I152>164,"伪名",""),IF(AND(E152>信息总览!$B$4,E152<26,G152>164),"伪名","")))) | X152: =IF(I152<140,0,IF(E152>23,0,I152-G152)) -> 59
A153: =W153 | B153: 83105845 | C153: Diogo Dalot | E153: 26 | F153: 146 | G153: 146 | H153: =IFERROR(VLOOKUP(B153,球员对应球队!A:D,4,FALSE)-G153,"") -> 0 | I153: 155 | J153: D/WB/RL | K153: 葡萄牙 | L153: Bayer 04 | M153: =VLOOKUP(L153,信息总览!C:E,3,FALSE) -> 超级 | P153: =IF(F153<115,1,INT((F153-95)/10)) -> 5 | Q153: =IF(G153<115,1,INT((G153-95)/10)) -> 5 | R153: =IF(I153<115,1,INT((I153-95)/10)) -> 6 | S153: =IF(E153>信息总览!$B$4,Q153,IF(I153<140,Q153,(Q153+R153)/2)) -> 5 | T153: =IF(AND(J153="GK",W153<>""),0.1,IF(S153=1,0.1,IF((S153+V153)/2=1,0.1,IF(W153="8M",0.15,IF(W153="7M",0.13,IF(W153="伪名",0.11,IF(E153>信息总览!$B$4,IF(INT((G153-95)/10)>5,0.09,0.07),IF(INT((I153-95)/10)>5,0.09,0.07)))))))) -> 0.07 | U153: =S153*T153 -> 0.35 | V153: =IF(E153>25,IF(F153<115,1,INT((F153-95)/10)),(IF(F153<115,1,INT((F153-95)/10))+IF(I153<115,1,INT((I153-95)/10)))/2) -> 5 | W153: =IF(V153>=8,"8M",IF(V153>=7,"7M",IF(E153<=信息总览!$B$4,IF(I153>164,"伪名",""),IF(AND(E153>信息总览!$B$4,E153<26,G153>164),"伪名","")))) | X153: =IF(I153<140,0,IF(E153>23,0,I153-G153)) -> 0
A154: =W154 | B154: 37060922 | C154: Joshua Zirkzee | E154: 24 | F154: 143 | G154: 143 | H154: =IFERROR(VLOOKUP(B154,球员对应球队!A:D,4,FALSE)-G154,"") -> 0 | I154: 160 | J154: ST | K154: 荷兰 | L154: Bayer 04 | M154: =VLOOKUP(L154,信息总览!C:E,3,FALSE) -> 超级 | P154: =IF(F154<115,1,INT((F154-95)/10)) -> 4 | Q154: =IF(G154<115,1,INT((G154-95)/10)) -> 4 | R154: =IF(I154<115,1,INT((I154-95)/10)) -> 6 | S154: =IF(E154>信息总览!$B$4,Q154,IF(I154<140,Q154,(Q154+R154)/2)) -> 5 | T154: =IF(AND(J154="GK",W154<>""),0.1,IF(S154=1,0.1,IF((S154+V154)/2=1,0.1,IF(W154="8M",0.15,IF(W154="7M",0.13,IF(W154="伪名",0.11,IF(E154>信息总览!$B$4,IF(INT((G154-95)/10)>5,0.09,0.07),IF(INT((I154-95)/10)>5,0.09,0.07)))))))) -> 0.09 | U154: =S154*T154 -> 0.45 | V154: =IF(E154>25,IF(F154<115,1,INT((F154-95)/10)),(IF(F154<115,1,INT((F154-95)/10))+IF(I154<115,1,INT((I154-95)/10)))/2) -> 5 | W154: =IF(V154>=8,"8M",IF(V154>=7,"7M",IF(E154<=信息总览!$B$4,IF(I154>164,"伪名",""),IF(AND(E154>信息总览!$B$4,E154<26,G154>164),"伪名","")))) | X154: =IF(I154<140,0,IF(E154>23,0,I154-G154)) -> 0
A155: =W155 | B155: 28116558 | C155: Largie Ramazani | E155: 24 | F155: 134 | G155: 134 | H155: =IFERROR(VLOOKUP(B155,球员对应球队!A:D,4,FALSE)-G155,"") -> 0 | I155: 155 | J155: AMRL/ST | K155: 比利时 | L155: Bayer 04 | M155: =VLOOKUP(L155,信息总览!C:E,3,FALSE) -> 超级 | P155: =IF(F155<115,1,INT((F155-95)/10)) -> 3 | Q155: =IF(G155<115,1,INT((G155-95)/10)) -> 3 | R155: =IF(I155<115,1,INT((I155-95)/10)) -> 6 | S155: =IF(E155>信息总览!$B$4,Q155,IF(I155<140,Q155,(Q155+R155)/2)) -> 4.5 | T155: =IF(AND(J155="GK",W155<>""),0.1,IF(S155=1,0.1,IF((S155+V155)/2=1,0.1,IF(W155="8M",0.15,IF(W155="7M",0.13,IF(W155="伪名",0.11,IF(E155>信息总览!$B$4,IF(INT((G155-95)/10)>5,0.09,0.07),IF(INT((I155-95)/10)>5,0.09,0.07)))))))) -> 0.09 | U155: =S155*T155 -> 0.405 | V155: =IF(E155>25,IF(F155<115,1,INT((F155-95)/10)),(IF(F155<115,1,INT((F155-95)/10))+IF(I155<115,1,INT((I155-95)/10)))/2) -> 4.5 | W155: =IF(V155>=8,"8M",IF(V155>=7,"7M",IF(E155<=信息总览!$B$4,IF(I155>164,"伪名",""),IF(AND(E155>信息总览!$B$4,E155<26,G155>164),"伪名","")))) | X155: =IF(I155<140,0,IF(E155>23,0,I155-G155)) -> 0
A156: =W156 | B156: 14167329 | C156: Lisandro Martínez | E156: 27 | F156: 152 | G156: 152 | H156: =IFERROR(VLOOKUP(B156,球员对应球队!A:D,4,FALSE)-G156,"") -> 0 | I156: 160 | J156: D/LC | K156: 阿根廷 | L156: Bayer 04 | M156: =VLOOKUP(L156,信息总览!C:E,3,FALSE) -> 超级 | P156: =IF(F156<115,1,INT((F156-95)/10)) -> 5 | Q156: =IF(G156<115,1,INT((G156-95)/10)) -> 5 | R156: =IF(I156<115,1,INT((I156-95)/10)) -> 6 | S156: =IF(E156>信息总览!$B$4,Q156,IF(I156<140,Q156,(Q156+R156)/2)) -> 5 | T156: =IF(AND(J156="GK",W156<>""),0.1,IF(S156=1,0.1,IF((S156+V156)/2=1,0.1,IF(W156="8M",0.15,IF(W156="7M",0.13,IF(W156="伪名",0.11,IF(E156>信息总览!$B$4,IF(INT((G156-95)/10)>5,0.09,0.07),IF(INT((I156-95)/10)>5,0.09,0.07)))))))) -> 0.07 | U156: =S156*T156 -> 0.35 | V156: =IF(E156>25,IF(F156<115,1,INT((F156-95)/10)),(IF(F156<115,1,INT((F156-95)/10))+IF(I156<115,1,INT((I156-95)/10)))/2) -> 5 | W156: =IF(V156>=8,"8M",IF(V156>=7,"7M",IF(E156<=信息总览!$B$4,IF(I156>164,"伪名",""),IF(AND(E156>信息总览!$B$4,E156<26,G156>164),"伪名","")))) | X156: =IF(I156<140,0,IF(E156>23,0,I156-G156)) -> 0
A157: =W157 | B157: 2000153212 | C157: Liu-Shao Ziyang | E157: 19 | F157: 90 | G157: 90 | H157: =IFERROR(VLOOKUP(B157,球员对应球队!A:D,4,FALSE)-G157,"") -> 0 | I157: 111 | J157: GK | K157: 中国 | L157: Bayer 04 | M157: =VLOOKUP(L157,信息总览!C:E,3,FALSE) -> 超级 | P157: =IF(F157<115,1,INT((F157-95)/10)) -> 1 | Q157: =IF(G157<115,1,INT((G157-95)/10)) -> 1 | R157: =IF(I157<115,1,INT((I157-95)/10)) -> 1 | S157: =IF(E157>信息总览!$B$4,Q157,IF(I157<140,Q157,(Q157+R157)/2)) -> 1 | T157: =IF(AND(J157="GK",W157<>""),0.1,IF(S157=1,0.1,IF((S157+V157)/2=1,0.1,IF(W157="8M",0.15,IF(W157="7M",0.13,IF(W157="伪名",0.11,IF(E157>信息总览!$B$4,IF(INT((G157-95)/10)>5,0.09,0.07),IF(INT((I157-95)/10)>5,0.09,0.07)))))))) -> 0.1 | U157: =S157*T157 -> 0.1 | V157: =IF(E157>25,IF(F157<115,1,INT((F157-95)/10)),(IF(F157<115,1,INT((F157-95)/10))+IF(I157<115,1,INT((I157-95)/10)))/2) -> 1 | W157: =IF(V157>=8,"8M",IF(V157>=7,"7M",IF(E157<=信息总览!$B$4,IF(I157>164,"伪名",""),IF(AND(E157>信息总览!$B$4,E157<26,G157>164),"伪名","")))) | X157: =IF(I157<140,0,IF(E157>23,0,I157-G157)) -> 0
A158: =W158 | B158: 29076105 | C158: Luke Shaw | E158: 30 | F158: 152 | G158: 152 | H158: =IFERROR(VLOOKUP(B158,球员对应球队!A:D,4,FALSE)-G158,"") -> 0 | I158: 162 | J158: D/WB/LC | K158: 英格兰 | L158: Bayer 04 | M158: =VLOOKUP(L158,信息总览!C:E,3,FALSE) -> 超级 | P158: =IF(F158<115,1,INT((F158-95)/10)) -> 5 | Q158: =IF(G158<115,1,INT((G158-95)/10)) -> 5 | R158: =IF(I158<115,1,INT((I158-95)/10)) -> 6 | S158: =IF(E158>信息总览!$B$4,Q158,IF(I158<140,Q158,(Q158+R158)/2)) -> 5 | T158: =IF(AND(J158="GK",W158<>""),0.1,IF(S158=1,0.1,IF((S158+V158)/2=1,0.1,IF(W158="8M",0.15,IF(W158="7M",0.13,IF(W158="伪名",0.11,IF(E158>信息总览!$B$4,IF(INT((G158-95)/10)>5,0.09,0.07),IF(INT((I158-95)/10)>5,0.09,0.07)))))))) -> 0.07 | U158: =S158*T158 -> 0.35 | V158: =IF(E158>25,IF(F158<115,1,INT((F158-95)/10)),(IF(F158<115,1,INT((F158-95)/10))+IF(I158<115,1,INT((I158-95)/10)))/2) -> 5 | W158: =IF(V158>=8,"8M",IF(V158>=7,"7M",IF(E158<=信息总览!$B$4,IF(I158>164,"伪名",""),IF(AND(E158>信息总览!$B$4,E158<26,G158>164),"伪名","")))) | X158: =IF(I158<140,0,IF(E158>23,0,I158-G158)) -> 0
A159: =W159 | B159: 78084541 | C159: Manuel Ugarte | E159: 24 | F159: 145 | G159: 151 | H159: =IFERROR(VLOOKUP(B159,球员对应球队!A:D,4,FALSE)-G159,"") -> 0 | I159: 158 | J159: DM/MC | K159: 乌拉圭 | L159: Bayer 04 | M159: =VLOOKUP(L159,信息总览!C:E,3,FALSE) -> 超级 | P159: =IF(F159<115,1,INT((F159-95)/10)) -> 5 | Q159: =IF(G159<115,1,INT((G159-95)/10)) -> 5 | R159: =IF(I159<115,1,INT((I159-95)/10)) -> 6 | S159: =IF(E159>信息总览!$B$4,Q159,IF(I159<140,Q159,(Q159+R159)/2)) -> 5.5 | T159: =IF(AND(J159="GK",W159<>""),0.1,IF(S159=1,0.1,IF((S159+V159)/2=1,0.1,IF(W159="8M",0.15,IF(W159="7M",0.13,IF(W159="伪名",0.11,IF(E159>信息总览!$B$4,IF(INT((G159-95)/10)>5,0.09,0.07),IF(INT((I159-95)/10)>5,0.09,0.07)))))))) -> 0.09 | U159: =S159*T159 -> 0.495 | V159: =IF(E159>25,IF(F159<115,1,INT((F159-95)/10)),(IF(F159<115,1,INT((F159-95)/10))+IF(I159<115,1,INT((I159-95)/10)))/2) -> 5.5 | W159: =IF(V159>=8,"8M",IF(V159>=7,"7M",IF(E159<=信息总览!$B$4,IF(I159>164,"伪名",""),IF(AND(E159>信息总览!$B$4,E159<26,G159>164),"伪名","")))) | X159: =IF(I159<140,0,IF(E159>23,0,I159-G159)) -> 0
A160: =W160 | B160: 28103590 | C160: Mason Mount | E160: 26 | F160: 150 | G160: 150 | H160: =IFERROR(VLOOKUP(B160,球员对应球队!A:D,4,FALSE)-G160,"") -> 0 | I160: 165 | J160: M/AMRLC | K160: 英格兰 | L160: Bayer 04 | M160: =VLOOKUP(L160,信息总览!C:E,3,FALSE) -> 超级 | P160: =IF(F160<115,1,INT((F160-95)/10)) -> 5 | Q160: =IF(G160<115,1,INT((G160-95)/10)) -> 5 | R160: =IF(I160<115,1,INT((I160-95)/10)) -> 7 | S160: =IF(E160>信息总览!$B$4,Q160,IF(I160<140,Q160,(Q160+R160)/2)) -> 5 | T160: =IF(AND(J160="GK",W160<>""),0.1,IF(S160=1,0.1,IF((S160+V160)/2=1,0.1,IF(W160="8M",0.15,IF(W160="7M",0.13,IF(W160="伪名",0.11,IF(E160>信息总览!$B$4,IF(INT((G160-95)/10)>5,0.09,0.07),IF(INT((I160-95)/10)>5,0.09,0.07)))))))) -> 0.07 | U160: =S160*T160 -> 0.35 | V160: =IF(E160>25,IF(F160<115,1,INT((F160-95)/10)),(IF(F160<115,1,INT((F160-95)/10))+IF(I160<115,1,INT((I160-95)/10)))/2) -> 5 | W160: =IF(V160>=8,"8M",IF(V160>=7,"7M",IF(E160<=信息总览!$B$4,IF(I160>164,"伪名",""),IF(AND(E160>信息总览!$B$4,E160<26,G160>164),"伪名","")))) | X160: =IF(I160<140,0,IF(E160>23,0,I160-G160)) -> 0
A161: =W161 | B161: 19334410 | C161: Matheus Cunha | E161: 26 | F161: 152 | G161: 152 | H161: =IFERROR(VLOOKUP(B161,球员对应球队!A:D,4,FALSE)-G161,"") -> 0 | I161: 162 | J161: AMRLC/ST | K161: 巴西 | L161: Bayer 04 | M161: =VLOOKUP(L161,信息总览!C:E,3,FALSE) -> 超级 | P161: =IF(F161<115,1,INT((F161-95)/10)) -> 5 | Q161: =IF(G161<115,1,INT((G161-95)/10)) -> 5 | R161: =IF(I161<115,1,INT((I161-95)/10)) -> 6 | S161: =IF(E161>信息总览!$B$4,Q161,IF(I161<140,Q161,(Q161+R161)/2)) -> 5 | T161: =IF(AND(J161="GK",W161<>""),0.1,IF(S161=1,0.1,IF((S161+V161)/2=1,0.1,IF(W161="8M",0.15,IF(W161="7M",0.13,IF(W161="伪名",0.11,IF(E161>信息总览!$B$4,IF(INT((G161-95)/10)>5,0.09,0.07),IF(INT((I161-95)/10)>5,0.09,0.07)))))))) -> 0.07 | U161: =S161*T161 -> 0.35 | V161: =IF(E161>25,IF(F161<115,1,INT((F161-95)/10)),(IF(F161<115,1,INT((F161-95)/10))+IF(I161<115,1,INT((I161-95)/10)))/2) -> 5 | W161: =IF(V161>=8,"8M",IF(V161>=7,"7M",IF(E161<=信息总览!$B$4,IF(I161>164,"伪名",""),IF(AND(E161>信息总览!$B$4,E161<26,G161>164),"伪名","")))) | X161: =IF(I161<140,0,IF(E161>23,0,I161-G161)) -> 0
... A185: =W185 | B185: 92103754 | C185: Jamie Leweling | E185: 24 | F185: 142 | G185: 142 | H185: =IFERROR(VLOOKUP(B185,球员对应球队!A:D,4,FALSE)-G185,"") -> 0 | I185: 152 | J185: AM RL | K185: Germany,Ghana,France | L185: Benfica | M185: =VLOOKUP(L185,信息总览!C:E,3,FALSE) -> 乙级 | P185: =IF(F185<115,1,INT((F185-95)/10)) -> 4 | Q185: =IF(G185<115,1,INT((G185-95)/10)) -> 4 | R185: =IF(I185<115,1,INT((I185-95)/10)) -> 5 | S185: =IF(E185>信息总览!$B$4,Q185,IF(I185<140,Q185,(Q185+R185)/2)) -> 4.5 | T185: =IF(AND(J185="GK",W185<>""),0.1,IF(S185=1,0.1,IF((S185+V185)/2=1,0.1,IF(W185="8M",0.15,IF(W185="7M",0.13,IF(W185="伪名",0.11,IF(E185>信息总览!$B$4,IF(INT((G185-95)/10)>5,0.09,0.07),IF(INT((I185-95)/10)>5,0.09,0.07)))))))) -> 0.07 | U185: =S185*T185 -> 0.315 | V185: =IF(E185>25,IF(F185<115,1,INT((F185-95)/10)),(IF(F185<115,1,INT((F185-95)/10))+IF(I185<115,1,INT((I185-95)/10)))/2) -> 4.5 | W185: =IF(V185>=8,"8M",IF(V185>=7,"7M",IF(E185<=信息总览!$B$4,IF(I185>164,"伪名",""),IF(AND(E185>信息总览!$B$4,E185<26,G185>164),"伪名","")))) | X185: =IF(I185<140,0,IF(E185>23,0,I185-G185)) -> 0
A186: =W186 | B186: 29218024 | C186: Hayden Hackney | E186: 23 | F186: 134 | G186: 134 | I186: 145 | J186: DM/M C | K186: England,Scotland | L186: Benfica | M186: =VLOOKUP(L186,信息总览!C:E,3,FALSE) -> 乙级 | P186: =IF(F186<115,1,INT((F186-95)/10)) -> 3 | Q186: =IF(G186<115,1,INT((G186-95)/10)) -> 3 | R186: =IF(I186<115,1,INT((I186-95)/10)) -> 5 | S186: =IF(E186>信息总览!$B$4,Q186,IF(I186<140,Q186,(Q186+R186)/2)) -> 4 | T186: =IF(AND(J186="GK",W186<>""),0.1,IF(S186=1,0.1,IF((S186+V186)/2=1,0.1,IF(W186="8M",0.15,IF(W186="7M",0.13,IF(W186="伪名",0.11,IF(E186>信息总览!$B$4,IF(INT((G186-95)/10)>5,0.09,0.07),IF(INT((I186-95)/10)>5,0.09,0.07)))))))) -> 0.07 | U186: =S186*T186 -> 0.28 | V186: =IF(E186>25,IF(F186<115,1,INT((F186-95)/10)),(IF(F186<115,1,INT((F186-95)/10))+IF(I186<115,1,INT((I186-95)/10)))/2) -> 4 | W186: =IF(V186>=8,"8M",IF(V186>=7,"7M",IF(E186<=信息总览!$B$4,IF(I186>164,"伪名",""),IF(AND(E186>信息总览!$B$4,E186<26,G186>164),"伪名","")))) | X186: =IF(I186<140,0,IF(E186>23,0,I186-G186)) -> 11
A187: =W187 | B187: 29179807 | C187: Jayden Bogle | E187: 25 | F187: 136 | G187: 136 | I187: 142 | J187: D/WB R | K187: England | L187: Benfica | M187: =VLOOKUP(L187,信息总览!C:E,3,FALSE) -> 乙级 | P187: =IF(F187<115,1,INT((F187-95)/10)) -> 4 | Q187: =IF(G187<115,1,INT((G187-95)/10)) -> 4 | R187: =IF(I187<115,1,INT((I187-95)/10)) -> 4 | S187: =IF(E187>信息总览!$B$4,Q187,IF(I187<140,Q187,(Q187+R187)/2)) -> 4 | T187: =IF(AND(J187="GK",W187<>""),0.1,IF(S187=1,0.1,IF((S187+V187)/2=1,0.1,IF(W187="8M",0.15,IF(W187="7M",0.13,IF(W187="伪名",0.11,IF(E187>信息总览!$B$4,IF(INT((G187-95)/10)>5,0.09,0.07),IF(INT((I187-95)/10)>5,0.09,0.07)))))))) -> 0.07 | U187: =S187*T187 -> 0.28 | V187: =IF(E187>25,IF(F187<115,1,INT((F187-95)/10)),(IF(F187<115,1,INT((F187-95)/10))+IF(I187<115,1,INT((I187-95)/10)))/2) -> 4 | W187: =IF(V187>=8,"8M",IF(V187>=7,"7M",IF(E187<=信息总览!$B$4,IF(I187>164,"伪名",""),IF(AND(E187>信息总览!$B$4,E187<26,G187>164),"伪名","")))) | X187: =IF(I187<140,0,IF(E187>23,0,I187-G187)) -> 0
A188: =W188 | B188: 67217491 | C188: Andrei Raţiu | E188: 27 | F188: 147 | G188: 147 | H188: =IFERROR(VLOOKUP(B188,球员对应球队!A:D,4,FALSE)-G188,"") -> 0 | I188: 150 | J188: D/WB/M/R | K188: Romania | L188: Boca | M188: =VLOOKUP(L188,信息总览!C:E,3,FALSE) -> 乙级 | P188: =IF(F188<115,1,INT((F188-95)/10)) -> 5 | Q188: =IF(G188<115,1,INT((G188-95)/10)) -> 5 | R188: =IF(I188<115,1,INT((I188-95)/10)) -> 5 | S188: =IF(E188>信息总览!$B$4,Q188,IF(I188<140,Q188,(Q188+R188)/2)) -> 5 | T188: =IF(AND(J188="GK",W188<>""),0.1,IF(S188=1,0.1,IF((S188+V188)/2=1,0.1,IF(W188="8M",0.15,IF(W188="7M",0.13,IF(W188="伪名",0.11,IF(E188>信息总览!$B$4,IF(INT((G188-95)/10)>5,0.09,0.07),IF(INT((I188-95)/10)>5,0.09,0.07)))))))) -> 0.07 | U188: =S188*T188 -> 0.35 | V188: =IF(E188>25,IF(F188<115,1,INT((F188-95)/10)),(IF(F188<115,1,INT((F188-95)/10))+IF(I188<115,1,INT((I188-95)/10)))/2) -> 5 | W188: =IF(V188>=8,"8M",IF(V188>=7,"7M",IF(E188<=信息总览!$B$4,IF(I188>164,"伪名",""),IF(AND(E188>信息总览!$B$4,E188<26,G188>164),"伪名","")))) | X188: =IF(I188<140,0,IF(E188>23,0,I188-G188)) -> 0
A189: =W189 | B189: 28104130 | C189: Caoimhin Kelleher | E189: 26 | F189: 145 | G189: 145 | H189: =IFERROR(VLOOKUP(B189,球员对应球队!A:D,4,FALSE)-G189,"") -> 0 | I189: 158 | J189: GK | K189: 爱尔兰 | L189: Boca | M189: =VLOOKUP(L189,信息总览!C:E,3,FALSE) -> 乙级 | P189: =IF(F189<115,1,INT((F189-95)/10)) -> 5 | Q189: =IF(G189<115,1,INT((G189-95)/10)) -> 5 | R189: =IF(I189<115,1,INT((I189-95)/10)) -> 6 | S189: =IF(E189>信息总览!$B$4,Q189,IF(I189<140,Q189,(Q189+R189)/2)) -> 5 | T189: =IF(AND(J189="GK",W189<>""),0.1,IF(S189=1,0.1,IF((S189+V189)/2=1,0.1,IF(W189="8M",0.15,IF(W189="7M",0.13,IF(W189="伪名",0.11,IF(E189>信息总览!$B$4,IF(INT((G189-95)/10)>5,0.09,0.07),IF(INT((I189-95)/10)>5,0.09,0.07)))))))) -> 0.07 | U189: =S189*T189 -> 0.35 | V189: =IF(E189>25,IF(F189<115,1,INT((F189-95)/10)),(IF(F189<115,1,INT((F189-95)/10))+IF(I189<115,1,INT((I189-95)/10)))/2) -> 5 | W189: =IF(V189>=8,"8M",IF(V189>=7,"7M",IF(E189<=信息总览!$B$4,IF(I189>164,"伪名",""),IF(AND(E189>信息总览!$B$4,E189<26,G189>164),"伪名","")))) | X189: =IF(I189<140,0,IF(E189>23,0,I189-G189)) -> 0
A190: =W190 -> 伪名 | B190: 2000220048 | C190: Chema Andrés | E190: 20 | F190: 130 | G190: 149 | H190: =IFERROR(VLOOKUP(B190,球员对应球队!A:D,4,FALSE)-G190,"") -> 0 | I190: 165 | J190: DM/MC | K190: 西班牙 | L190: Boca | M190: =VLOOKUP(L190,信息总览!C:E,3,FALSE) -> 乙级 | P190: =IF(F190<115,1,INT((F190-95)/10)) -> 3 | Q190: =IF(G190<115,1,INT((G190-95)/10)) -> 5 | R190: =IF(I190<115,1,INT((I190-95)/10)) -> 7 | S190: =IF(E190>信息总览!$B$4,Q190,IF(I190<140,Q190,(Q190+R190)/2)) -> 6 | T190: =IF(AND(J190="GK",W190<>""),0.1,IF(S190=1,0.1,IF((S190+V190)/2=1,0.1,IF(W190="8M",0.15,IF(W190="7M",0.13,IF(W190="伪名",0.11,IF(E190>信息总览!$B$4,IF(INT((G190-95)/10)>5,0.09,0.07),IF(INT((I190-95)/10)>5,0.09,0.07)))))))) -> 0.11 | U190: =S190*T190 -> 0.66 | V190: =IF(E190>25,IF(F190<115,1,INT((F190-95)/10)),(IF(F190<115,1,INT((F190-95)/10))+IF(I190<115,1,INT((I190-95)/10)))/2) -> 5 | W190: =IF(V190>=8,"8M",IF(V190>=7,"7M",IF(E190<=信息总览!$B$4,IF(I190>164,"伪名",""),IF(AND(E190>信息总览!$B$4,E190<26,G190>164),"伪名","")))) -> 伪名 | X190: =IF(I190<140,0,IF(E190>23,0,I190-G190)) -> 16
A191: =W191 | B191: 2000140844 | C191: David Ozoh | E191: 20 | F191: 118 | G191: 133 | H191: =IFERROR(VLOOKUP(B191,球员对应球队!A:D,4,FALSE)-G191,"") -> 0 | I191: 150 | J191: DM/MC | K191: 英格兰 | L191: Boca | M191: =VLOOKUP(L191,信息总览!C:E,3,FALSE) -> 乙级 | P191: =IF(F191<115,1,INT((F191-95)/10)) -> 2 | Q191: =IF(G191<115,1,INT((G191-95)/10)) -> 3 | R191: =IF(I191<115,1,INT((I191-95)/10)) -> 5 | S191: =IF(E191>信息总览!$B$4,Q191,IF(I191<140,Q191,(Q191+R191)/2)) -> 4 | T191: =IF(AND(J191="GK",W191<>""),0.1,IF(S191=1,0.1,IF((S191+V191)/2=1,0.1,IF(W191="8M",0.15,IF(W191="7M",0.13,IF(W191="伪名",0.11,IF(E191>信息总览!$B$4,IF(INT((G191-95)/10)>5,0.09,0.07),IF(INT((I191-95)/10)>5,0.09,0.07)))))))) -> 0.07 | U191: =S191*T191 -> 0.28 | V191: =IF(E191>25,IF(F191<115,1,INT((F191-95)/10)),(IF(F191<115,1,INT((F191-95)/10))+IF(I191<115,1,INT((I191-95)/10)))/2) -> 3.5 | W191: =IF(V191>=8,"8M",IF(V191>=7,"7M",IF(E191<=信息总览!$B$4,IF(I191>164,"伪名",""),IF(AND(E191>信息总览!$B$4,E191<26,G191>164),"伪名","")))) | X191: =IF(I191<140,0,IF(E191>23,0,I191-G191)) -> 17
A192: =W192 -> 8M | B192: 29179241 | C192: Erling Haaland | E192: 25 | F192: 184 | G192: 195 | H192: =IFERROR(VLOOKUP(B192,球员对应球队!A:D,4,FALSE)-G192,"") -> 0 | I192: 195 | J192: ST | K192: 挪威 | L192: Boca | M192: =VLOOKUP(L192,信息总览!C:E,3,FALSE) -> 乙级 | P192: =IF(F192<115,1,INT((F192-95)/10)) -> 8 | Q192: =IF(G192<115,1,INT((G192-95)/10)) -> 10 | R192: =IF(I192<115,1,INT((I192-95)/10)) -> 10 | S192: =IF(E192>信息总览!$B$4,Q192,IF(I192<140,Q192,(Q192+R192)/2)) -> 10 | T192: =IF(AND(J192="GK",W192<>""),0.1,IF(S192=1,0.1,IF((S192+V192)/2=1,0.1,IF(W192="8M",0.15,IF(W192="7M",0.13,IF(W192="伪名",0.11,IF(E192>信息总览!$B$4,IF(INT((G192-95)/10)>5,0.09,0.07),IF(INT((I192-95)/10)>5,0.09,0.07)))))))) -> 0.15 | U192: =S192*T192 -> 1.5 | V192: =IF(E192>25,IF(F192<115,1,INT((F192-95)/10)),(IF(F192<115,1,INT((F192-95)/10))+IF(I192<115,1,INT((I192-95)/10)))/2) -> 9 | W192: =IF(V192>=8,"8M",IF(V192>=7,"7M",IF(E192<=信息总览!$B$4,IF(I192>164,"伪名",""),IF(AND(E192>信息总览!$B$4,E192<26,G192>164),"伪名","")))) -> 8M | X192: =IF(I192<140,0,IF(E192>23,0,I192-G192)) -> 0
A193: =W193 | B193: 2000087459 | C193: Jan-Carlo Simić | E193: 20 | F193: 115 | G193: 130 | H193: =IFERROR(VLOOKUP(B193,球员对应球队!A:D,4,FALSE)-G193,"") -> 0 | I193: 150 | J193: D/C | K193: 塞尔维亚 | L193: Boca | M193: =VLOOKUP(L193,信息总览!C:E,3,FALSE) -> 乙级 | P193: =IF(F193<115,1,INT((F193-95)/10)) -> 2 | Q193: =IF(G193<115,1,INT((G193-95)/10)) -> 3 | R193: =IF(I193<115,1,INT((I193-95)/10)) -> 5 | S193: =IF(E193>信息总览!$B$4,Q193,IF(I193<140,Q193,(Q193+R193)/2)) -> 4 | T193: =IF(AND(J193="GK",W193<>""),0.1,IF(S193=1,0.1,IF((S193+V193)/2=1,0.1,IF(W193="8M",0.15,IF(W193="7M",0.13,IF(W193="伪名",0.11,IF(E193>信息总览!$B$4,IF(INT((G193-95)/10)>5,0.09,0.07),IF(INT((I193-95)/10)>5,0.09,0.07)))))))) -> 0.07 | U193: =S193*T193 -> 0.28 | V193: =IF(E193>25,IF(F193<115,1,INT((F193-95)/10)),(IF(F193<115,1,INT((F193-95)/10))+IF(I193<115,1,INT((I193-95)/10)))/2) -> 3.5 | W193: =IF(V193>=8,"8M",IF(V193>=7,"7M",IF(E193<=信息总览!$B$4,IF(I193>164,"伪名",""),IF(AND(E193>信息总览!$B$4,E193<26,G193>164),"伪名","")))) | X193: =IF(I193<140,0,IF(E193>23,0,I193-G193)) -> 20
A194: =W194 | B194: 2000222926 | C194: Jeff Ekhator | E194: 18 | F194: 121 | G194: 121 | H194: =IFERROR(VLOOKUP(B194,球员对应球队!A:D,4,FALSE)-G194,"") -> 0 | I194: 160 | J194: ST | K194: Italy,Nigeria | L194: Boca | M194: =VLOOKUP(L194,信息总览!C:E,3,FALSE) -> 乙级 | P194: =IF(F194<115,1,INT((F194-95)/10)) -> 2 | Q194: =IF(G194<115,1,INT((G194-95)/10)) -> 2 | R194: =IF(I194<115,1,INT((I194-95)/10)) -> 6 | S194: =IF(E194>信息总览!$B$4,Q194,IF(I194<140,Q194,(Q194+R194)/2)) -> 4 | T194: =IF(AND(J194="GK",W194<>""),0.1,IF(S194=1,0.1,IF((S194+V194)/2=1,0.1,IF(W194="8M",0.15,IF(W194="7M",0.13,IF(W194="伪名",0.11,IF(E194>信息总览!$B$4,IF(INT((G194-95)/10)>5,0.09,0.07),IF(INT((I194-95)/10)>5,0.09,0.07)))))))) -> 0.09 | U194: =S194*T194 -> 0.36 | V194: =IF(E194>25,IF(F194<115,1,INT((F194-95)/10)),(IF(F194<115,1,INT((F194-95)/10))+IF(I194<115,1,INT((I194-95)/10)))/2) -> 4 | W194: =IF(V194>=8,"8M",IF(V194>=7,"7M",IF(E194<=信息总览!$B$4,IF(I194>164,"伪名",""),IF(AND(E194>信息总览!$B$4,E194<26,G194>164),"伪名","")))) | X194: =IF(I194<140,0,IF(E194>23,0,I194-G194)) -> 39
A195: =W195 -> 伪名 | B195: 2000409386 | C195: José Reyes | E195: 17 | F195: 95 | G195: 116 | H195: =IFERROR(VLOOKUP(B195,球员对应球队!A:D,4,FALSE)-G195,"") -> 0 | I195: 170 | J195: AMRL/ST | K195: Spain | L195: Boca | M195: =VLOOKUP(L195,信息总览!C:E,3,FALSE) -> 乙级 | P195: =IF(F195<115,1,INT((F195-95)/10)) -> 1 | Q195: =IF(G195<115,1,INT((G195-95)/10)) -> 2 | R195: =IF(I195<115,1,INT((I195-95)/10)) -> 7 | S195: =IF(E195>信息总览!$B$4,Q195,IF(I195<140,Q195,(Q195+R195)/2)) -> 4.5 | T195: =IF(AND(J195="GK",W195<>""),0.1,IF(S195=1,0.1,IF((S195+V195)/2=1,0.1,IF(W195="8M",0.15,IF(W195="7M",0.13,IF(W195="伪名",0.11,IF(E195>信息总览!$B$4,IF(INT((G195-95)/10)>5,0.09,0.07),IF(INT((I195-95)/10)>5,0.09,0.07)))))))) -> 0.11 | U195: =S195*T195 -> 0.495 | V195: =IF(E195>25,IF(F195<115,1,INT((F195-95)/10)),(IF(F195<115,1,INT((F195-95)/10))+IF(I195<115,1,INT((I195-95)/10)))/2) -> 4 | W195: =IF(V195>=8,"8M",IF(V195>=7,"7M",IF(E195<=信息总览!$B$4,IF(I195>164,"伪名",""),IF(AND(E195>信息总览!$B$4,E195<26,G195>164),"伪名","")))) -> 伪名 | X195: =IF(I195<140,0,IF(E195>23,0,I195-G195)) -> 54
A196: =W196 | B196: 79034187 | C196: Julio Enciso | E196: 21 | F196: 139 | G196: 145 | H196: =IFERROR(VLOOKUP(B196,球员对应球队!A:D,4,FALSE)-G196,"") -> 0 | I196: 162 | J196: AM/RLC | K196: 阿根廷 | L196: Boca | M196: =VLOOKUP(L196,信息总览!C:E,3,FALSE) -> 乙级 | P196: =IF(F196<115,1,INT((F196-95)/10)) -> 4 | Q196: =IF(G196<115,1,INT((G196-95)/10)) -> 5 | R196: =IF(I196<115,1,INT((I196-95)/10)) -> 6 | S196: =IF(E196>信息总览!$B$4,Q196,IF(I196<140,Q196,(Q196+R196)/2)) -> 5.5 | T196: =IF(AND(J196="GK",W196<>""),0.1,IF(S196=1,0.1,IF((S196+V196)/2=1,0.1,IF(W196="8M",0.15,IF(W196="7M",0.13,IF(W196="伪名",0.11,IF(E196>信息总览!$B$4,IF(INT((G196-95)/10)>5,0.09,0.07),IF(INT((I196-95)/10)>5,0.09,0.07)))))))) -> 0.09 | U196: =S196*T196 -> 0.495 | V196: =IF(E196>25,IF(F196<115,1,INT((F196-95)/10)),(IF(F196<115,1,INT((F196-95)/10))+IF(I196<115,1,INT((I196-95)/10)))/2) -> 5 | W196: =IF(V196>=8,"8M",IF(V196>=7,"7M",IF(E196<=信息总览!$B$4,IF(I196>164,"伪名",""),IF(AND(E196>信息总览!$B$4,E196<26,G196>164),"伪名","")))) | X196: =IF(I196<140,0,IF(E196>23,0,I196-G196)) -> 17
A197: =W197 -> 伪名 | B197: 2000102845 | C197: Mika Godts | E197: 20 | F197: 131 | G197: 138 | H197: =IFERROR(VLOOKUP(B197,球员对应球队!A:D,4,FALSE)-G197,"") -> 0 | I197: 168 | J197: AM/RLC | K197: 比利时 | L197: Boca | M197: =VLOOKUP(L197,信息总览!C:E,3,FALSE) -> 乙级 | P197: =IF(F197<115,1,INT((F197-95)/10)) -> 3 | Q197: =IF(G197<115,1,INT((G197-95)/10)) -> 4 | R197: =IF(I197<115,1,INT((I197-95)/10)) -> 7 | S197: =IF(E197>信息总览!$B$4,Q197,IF(I197<140,Q197,(Q197+R197)/2)) -> 5.5 | T197: =IF(AND(J197="GK",W197<>""),0.1,IF(S197=1,0.1,IF((S197+V197)/2=1,0.1,IF(W197="8M",0.15,IF(W197="7M",0.13,IF(W197="伪名",0.11,IF(E197>信息总览!$B$4,IF(INT((G197-95)/10)>5,0.09,0.07),IF(INT((I197-95)/10)>5,0.09,0.07)))))))) -> 0.11 | U197: =S197*T197 -> 0.605 | V197: =IF(E197>25,IF(F197<115,1,INT((F197-95)/10)),(IF(F197<115,1,INT((F197-95)/10))+IF(I197<115,1,INT((I197-95)/10)))/2) -> 5 | W197: =IF(V197>=8,"8M",IF(V197>=7,"7M",IF(E197<=信息总览!$B$4,IF(I197>164,"伪名",""),IF(AND(E197>信息总览!$B$4,E197<26,G197>164),"伪名","")))) -> 伪名 | X197: =IF(I197<140,0,IF(E197>23,0,I197-G197)) -> 30
A198: =W198 | B198: 43617061 | C198: Nicolò Bertola | E198: 22 | F198: 131 | G198: 136 | H198: =IFERROR(VLOOKUP(B198,球员对应球队!A:D,4,FALSE)-G198,"") -> 0 | I198: 152 | J198: D/C | K198: Italy | L198: Boca | M198: =VLOOKUP(L198,信息总览!C:E,3,FALSE) -> 乙级 | P198: =IF(F198<115,1,INT((F198-95)/10)) -> 3 | Q198: =IF(G198<115,1,INT((G198-95)/10)) -> 4 | R198: =IF(I198<115,1,INT((I198-95)/10)) -> 5 | S198: =IF(E198>信息总览!$B$4,Q198,IF(I198<140,Q198,(Q198+R198)/2)) -> 4.5 | T198: =IF(AND(J198="GK",W198<>""),0.1,IF(S198=1,0.1,IF((S198+V198)/2=1,0.1,IF(W198="8M",0.15,IF(W198="7M",0.13,IF(W198="伪名",0.11,IF(E198>信息总览!$B$4,IF(INT((G198-95)/10)>5,0.09,0.07),IF(INT((I198-95)/10)>5,0.09,0.07)))))))) -> 0.07 | U198: =S198*T198 -> 0.315 | V198: =IF(E198>25,IF(F198<115,1,INT((F198-95)/10)),(IF(F198<115,1,INT((F198-95)/10))+IF(I198<115,1,INT((I198-95)/10)))/2) -> 4 | W198: =IF(V198>=8,"8M",IF(V198>=7,"7M",IF(E198<=信息总览!$B$4,IF(I198>164,"伪名",""),IF(AND(E198>信息总览!$B$4,E198<26,G198>164),"伪名","")))) | X198: =IF(I198<140,0,IF(E198>23,0,I198-G198)) -> 16
A199: =W199 | B199: 2000180847 | C199: Noël Aséko | E199: 19 | F199: 116 | G199: 122 | H199: =IFERROR(VLOOKUP(B199,球员对应球队!A:D,4,FALSE)-G199,"") -> 0 | I199: 160 | J199: DM/MC | K199: Germany,Equatorial Guinea | L199: Boca | M199: =VLOOKUP(L199,信息总览!C:E,3,FALSE) -> 乙级 | P199: =IF(F199<115,1,INT((F199-95)/10)) -> 2 | Q199: =IF(G199<115,1,INT((G199-95)/10)) -> 2 | R199: =IF(I199<115,1,INT((I199-95)/10)) -> 6 | S199: =IF(E199>信息总览!$B$4,Q199,IF(I199<140,Q199,(Q199+R199)/2)) -> 4 | T199: =IF(AND(J199="GK",W199<>""),0.1,IF(S199=1,0.1,IF((S199+V199)/2=1,0.1,IF(W199="8M",0.15,IF(W199="7M",0.13,IF(W199="伪名",0.11,IF(E199>信息总览!$B$4,IF(INT((G199-95)/10)>5,0.09,0.07),IF(INT((I199-95)/10)>5,0.09,0.07)))))))) -> 0.09 | U199: =S199*T199 -> 0.36 | V199: =IF(E199>25,IF(F199<115,1,INT((F199-95)/10)),(IF(F199<115,1,INT((F199-95)/10))+IF(I199<115,1,INT((I199-95)/10)))/2) -> 4 | W199: =IF(V199>=8,"8M",IF(V199>=7,"7M",IF(E199<=信息总览!$B$4,IF(I199>164,"伪名",""),IF(AND(E199>信息总览!$B$4,E199<26,G199>164),"伪名","")))) | X199: =IF(I199<140,0,IF(E199>23,0,I199-G199)) -> 38
... A263: =W263 | B263: 2000169799 | C263: John Mellberg | E263: 18 | F263: 109 | G263: 124 | H263: =IFERROR(VLOOKUP(B263,球员对应球队!A:D,4,FALSE)-G263,"") -> 0 | I263: 160 | J263: D/C | K263: 瑞典 | L263: Celtic | M263: =VLOOKUP(L263,信息总览!C:E,3,FALSE) -> 甲级 | P263: =IF(F263<115,1,INT((F263-95)/10)) -> 1 | Q263: =IF(G263<115,1,INT((G263-95)/10)) -> 2 | R263: =IF(I263<115,1,INT((I263-95)/10)) -> 6 | S263: =IF(E263>信息总览!$B$4,Q263,IF(I263<140,Q263,(Q263+R263)/2)) -> 4 | T263: =IF(AND(J263="GK",W263<>""),0.1,IF(S263=1,0.1,IF((S263+V263)/2=1,0.1,IF(W263="8M",0.15,IF(W263="7M",0.13,IF(W263="伪名",0.11,IF(E263>信息总览!$B$4,IF(INT((G263-95)/10)>5,0.09,0.07),IF(INT((I263-95)/10)>5,0.09,0.07)))))))) -> 0.09 | U263: =S263*T263 -> 0.36 | V263: =IF(E263>25,IF(F263<115,1,INT((F263-95)/10)),(IF(F263<115,1,INT((F263-95)/10))+IF(I263<115,1,INT((I263-95)/10)))/2) -> 3.5 | W263: =IF(V263>=8,"8M",IF(V263>=7,"7M",IF(E263<=信息总览!$B$4,IF(I263>164,"伪名",""),IF(AND(E263>信息总览!$B$4,E263<26,G263>164),"伪名","")))) | X263: =IF(I263<140,0,IF(E263>23,0,I263-G263)) -> 36
A264: =W264 | B264: 67215284 | C264: Marc Cucurella | D264: 27 | E264: 26 | F264: 150 | G264: 150 | H264: =IFERROR(VLOOKUP(B264,球员对应球队!A:D,4,FALSE)-G264,"") -> 0 | I264: 164 | J264: D/WB/M/LC | K264: 西班牙 | L264: Celtic | M264: =VLOOKUP(L264,信息总览!C:E,3,FALSE) -> 甲级 | P264: =IF(F264<115,1,INT((F264-95)/10)) -> 5 | Q264: =IF(G264<115,1,INT((G264-95)/10)) -> 5 | R264: =IF(I264<115,1,INT((I264-95)/10)) -> 6 | S264: =IF(E264>信息总览!$B$4,Q264,IF(I264<140,Q264,(Q264+R264)/2)) -> 5 | T264: =IF(AND(J264="GK",W264<>""),0.1,IF(S264=1,0.1,IF((S264+V264)/2=1,0.1,IF(W264="8M",0.15,IF(W264="7M",0.13,IF(W264="伪名",0.11,IF(E264>信息总览!$B$4,IF(INT((G264-95)/10)>5,0.09,0.07),IF(INT((I264-95)/10)>5,0.09,0.07)))))))) -> 0.07 | U264: =S264*T264 -> 0.35 | V264: =IF(E264>25,IF(F264<115,1,INT((F264-95)/10)),(IF(F264<115,1,INT((F264-95)/10))+IF(I264<115,1,INT((I264-95)/10)))/2) -> 5 | W264: =IF(V264>=8,"8M",IF(V264>=7,"7M",IF(E264<=信息总览!$B$4,IF(I264>164,"伪名",""),IF(AND(E264>信息总览!$B$4,E264<26,G264>164),"伪名","")))) | X264: =IF(I264<140,0,IF(E264>23,0,I264-G264)) -> 0
A265: =W265 | B265: 28110176 | C265: Nathan Trott | E265: 26 | F265: 122 | G265: 122 | H265: =IFERROR(VLOOKUP(B265,球员对应球队!A:D,4,FALSE)-G265,"") -> 0 | I265: 129 | J265: GK | K265: England,Bermuda | L265: Celtic | M265: =VLOOKUP(L265,信息总览!C:E,3,FALSE) -> 甲级 | P265: =IF(F265<115,1,INT((F265-95)/10)) -> 2 | Q265: =IF(G265<115,1,INT((G265-95)/10)) -> 2 | R265: =IF(I265<115,1,INT((I265-95)/10)) -> 3 | S265: =IF(E265>信息总览!$B$4,Q265,IF(I265<140,Q265,(Q265+R265)/2)) -> 2 | T265: =IF(AND(J265="GK",W265<>""),0.1,IF(S265=1,0.1,IF((S265+V265)/2=1,0.1,IF(W265="8M",0.15,IF(W265="7M",0.13,IF(W265="伪名",0.11,IF(E265>信息总览!$B$4,IF(INT((G265-95)/10)>5,0.09,0.07),IF(INT((I265-95)/10)>5,0.09,0.07)))))))) -> 0.07 | U265: =S265*T265 -> 0.14 | V265: =IF(E265>25,IF(F265<115,1,INT((F265-95)/10)),(IF(F265<115,1,INT((F265-95)/10))+IF(I265<115,1,INT((I265-95)/10)))/2) -> 2 | W265: =IF(V265>=8,"8M",IF(V265>=7,"7M",IF(E265<=信息总览!$B$4,IF(I265>164,"伪名",""),IF(AND(E265>信息总览!$B$4,E265<26,G265>164),"伪名","")))) | X265: =IF(I265<140,0,IF(E265>23,0,I265-G265)) -> 0
A266: =W266 | B266: 28115792 | C266: Neco Williams | E266: 24 | F266: 135 | G266: 141 | H266: =IFERROR(VLOOKUP(B266,球员对应球队!A:D,4,FALSE)-G266,"") -> 0 | I266: 150 | J266: D/WB/RL | K266: 威尔士 | L266: Celtic | M266: =VLOOKUP(L266,信息总览!C:E,3,FALSE) -> 甲级 | P266: =IF(F266<115,1,INT((F266-95)/10)) -> 4 | Q266: =IF(G266<115,1,INT((G266-95)/10)) -> 4 | R266: =IF(I266<115,1,INT((I266-95)/10)) -> 5 | S266: =IF(E266>信息总览!$B$4,Q266,IF(I266<140,Q266,(Q266+R266)/2)) -> 4.5 | T266: =IF(AND(J266="GK",W266<>""),0.1,IF(S266=1,0.1,IF((S266+V266)/2=1,0.1,IF(W266="8M",0.15,IF(W266="7M",0.13,IF(W266="伪名",0.11,IF(E266>信息总览!$B$4,IF(INT((G266-95)/10)>5,0.09,0.07),IF(INT((I266-95)/10)>5,0.09,0.07)))))))) -> 0.07 | U266: =S266*T266 -> 0.315 | V266: =IF(E266>25,IF(F266<115,1,INT((F266-95)/10)),(IF(F266<115,1,INT((F266-95)/10))+IF(I266<115,1,INT((I266-95)/10)))/2) -> 4.5 | W266: =IF(V266>=8,"8M",IF(V266>=7,"7M",IF(E266<=信息总览!$B$4,IF(I266>164,"伪名",""),IF(AND(E266>信息总览!$B$4,E266<26,G266>164),"伪名","")))) | X266: =IF(I266<140,0,IF(E266>23,0,I266-G266)) -> 0
A267: =W267 | B267: 35017377 | C267: Oliver Baumann | E267: 35 | F267: 148 | G267: 148 | H267: =IFERROR(VLOOKUP(B267,球员对应球队!A:D,4,FALSE)-G267,"") -> 0 | I267: 150 | J267: GK | K267: 德国 | L267: Celtic | M267: =VLOOKUP(L267,信息总览!C:E,3,FALSE) -> 甲级 | P267: =IF(F267<115,1,INT((F267-95)/10)) -> 5 | Q267: =IF(G267<115,1,INT((G267-95)/10)) -> 5 | R267: =IF(I267<115,1,INT((I267-95)/10)) -> 5 | S267: =IF(E267>信息总览!$B$4,Q267,IF(I267<140,Q267,(Q267+R267)/2)) -> 5 | T267: =IF(AND(J267="GK",W267<>""),0.1,IF(S267=1,0.1,IF((S267+V267)/2=1,0.1,IF(W267="8M",0.15,IF(W267="7M",0.13,IF(W267="伪名",0.11,IF(E267>信息总览!$B$4,IF(INT((G267-95)/10)>5,0.09,0.07),IF(INT((I267-95)/10)>5,0.09,0.07)))))))) -> 0.07 | U267: =S267*T267 -> 0.35 | V267: =IF(E267>25,IF(F267<115,1,INT((F267-95)/10)),(IF(F267<115,1,INT((F267-95)/10))+IF(I267<115,1,INT((I267-95)/10)))/2) -> 5 | W267: =IF(V267>=8,"8M",IF(V267>=7,"7M",IF(E267<=信息总览!$B$4,IF(I267>164,"伪名",""),IF(AND(E267>信息总览!$B$4,E267<26,G267>164),"伪名","")))) | X267: =IF(I267<140,0,IF(E267>23,0,I267-G267)) -> 0
A268: =W268 -> 伪名 | B268: 2000049425 | C268: Omar El Hilali | E268: 21 | F268: 140 | G268: 147 | H268: =IFERROR(VLOOKUP(B268,球员对应球队!A:D,4,FALSE)-G268,"") -> 0 | I268: 165 | J268: D/WB/R | K268: 摩纳哥 | L268: Celtic | M268: =VLOOKUP(L268,信息总览!C:E,3,FALSE) -> 甲级 | P268: =IF(F268<115,1,INT((F268-95)/10)) -> 4 | Q268: =IF(G268<115,1,INT((G268-95)/10)) -> 5 | R268: =IF(I268<115,1,INT((I268-95)/10)) -> 7 | S268: =IF(E268>信息总览!$B$4,Q268,IF(I268<140,Q268,(Q268+R268)/2)) -> 6 | T268: =IF(AND(J268="GK",W268<>""),0.1,IF(S268=1,0.1,IF((S268+V268)/2=1,0.1,IF(W268="8M",0.15,IF(W268="7M",0.13,IF(W268="伪名",0.11,IF(E268>信息总览!$B$4,IF(INT((G268-95)/10)>5,0.09,0.07),IF(INT((I268-95)/10)>5,0.09,0.07)))))))) -> 0.11 | U268: =S268*T268 -> 0.66 | V268: =IF(E268>25,IF(F268<115,1,INT((F268-95)/10)),(IF(F268<115,1,INT((F268-95)/10))+IF(I268<115,1,INT((I268-95)/10)))/2) -> 5.5 | W268: =IF(V268>=8,"8M",IF(V268>=7,"7M",IF(E268<=信息总览!$B$4,IF(I268>164,"伪名",""),IF(AND(E268>信息总览!$B$4,E268<26,G268>164),"伪名","")))) -> 伪名 | X268: =IF(I268<140,0,IF(E268>23,0,I268-G268)) -> 18
A269: =W269 -> 伪名 | B269: 2000047221 | C269: Omari Hutchinson | E269: 21 | F269: 137 | G269: 144 | H269: =IFERROR(VLOOKUP(B269,球员对应球队!A:D,4,FALSE)-G269,"") -> 0 | I269: 165 | J269: AM/RLC | K269: England,Jamaica | L269: Celtic | M269: =VLOOKUP(L269,信息总览!C:E,3,FALSE) -> 甲级 | P269: =IF(F269<115,1,INT((F269-95)/10)) -> 4 | Q269: =IF(G269<115,1,INT((G269-95)/10)) -> 4 | R269: =IF(I269<115,1,INT((I269-95)/10)) -> 7 | S269: =IF(E269>信息总览!$B$4,Q269,IF(I269<140,Q269,(Q269+R269)/2)) -> 5.5 | T269: =IF(AND(J269="GK",W269<>""),0.1,IF(S269=1,0.1,IF((S269+V269)/2=1,0.1,IF(W269="8M",0.15,IF(W269="7M",0.13,IF(W269="伪名",0.11,IF(E269>信息总览!$B$4,IF(INT((G269-95)/10)>5,0.09,0.07),IF(INT((I269-95)/10)>5,0.09,0.07)))))))) -> 0.11 | U269: =S269*T269 -> 0.605 | V269: =IF(E269>25,IF(F269<115,1,INT((F269-95)/10)),(IF(F269<115,1,INT((F269-95)/10))+IF(I269<115,1,INT((I269-95)/10)))/2) -> 5.5 | W269: =IF(V269>=8,"8M",IF(V269>=7,"7M",IF(E269<=信息总览!$B$4,IF(I269>164,"伪名",""),IF(AND(E269>信息总览!$B$4,E269<26,G269>164),"伪名","")))) -> 伪名 | X269: =IF(I269<140,0,IF(E269>23,0,I269-G269)) -> 21
A270: =W270 | B270: 37074900 | C270: Sepp van den Berg | E270: 23 | F270: 141 | G270: 147 | H270: =IFERROR(VLOOKUP(B270,球员对应球队!A:D,4,FALSE)-G270,"") -> 0 | I270: 156 | J270: D/C | K270: 荷兰 | L270: Celtic | M270: =VLOOKUP(L270,信息总览!C:E,3,FALSE) -> 甲级 | P270: =IF(F270<115,1,INT((F270-95)/10)) -> 4 | Q270: =IF(G270<115,1,INT((G270-95)/10)) -> 5 | R270: =IF(I270<115,1,INT((I270-95)/10)) -> 6 | S270: =IF(E270>信息总览!$B$4,Q270,IF(I270<140,Q270,(Q270+R270)/2)) -> 5.5 | T270: =IF(AND(J270="GK",W270<>""),0.1,IF(S270=1,0.1,IF((S270+V270)/2=1,0.1,IF(W270="8M",0.15,IF(W270="7M",0.13,IF(W270="伪名",0.11,IF(E270>信息总览!$B$4,IF(INT((G270-95)/10)>5,0.09,0.07),IF(INT((I270-95)/10)>5,0.09,0.07)))))))) -> 0.09 | U270: =S270*T270 -> 0.495 | V270: =IF(E270>25,IF(F270<115,1,INT((F270-95)/10)),(IF(F270<115,1,INT((F270-95)/10))+IF(I270<115,1,INT((I270-95)/10)))/2) -> 5 | W270: =IF(V270>=8,"8M",IF(V270>=7,"7M",IF(E270<=信息总览!$B$4,IF(I270>164,"伪名",""),IF(AND(E270>信息总览!$B$4,E270<26,G270>164),"伪名","")))) | X270: =IF(I270<140,0,IF(E270>23,0,I270-G270)) -> 9
A271: =W271 -> 伪名 | B271: 28121564 | C271: Mason Greenwood | E271: 23 | F271: 156 | G271: 167 | H271: =IFERROR(VLOOKUP(B271,球员对应球队!A:D,4,FALSE)-G271,"") -> 0 | I271: 167 | J271: AMR/ST | K271: 英格兰 | L271: Celtic | M271: =VLOOKUP(L271,信息总览!C:E,3,FALSE) -> 甲级 | P271: =IF(F271<115,1,INT((F271-95)/10)) -> 6 | Q271: =IF(G271<115,1,INT((G271-95)/10)) -> 7 | R271: =IF(I271<115,1,INT((I271-95)/10)) -> 7 | S271: =IF(E271>信息总览!$B$4,Q271,IF(I271<140,Q271,(Q271+R271)/2)) -> 7 | T271: =IF(AND(J271="GK",W271<>""),0.1,IF(S271=1,0.1,IF((S271+V271)/2=1,0.1,IF(W271="8M",0.15,IF(W271="7M",0.13,IF(W271="伪名",0.11,IF(E271>信息总览!$B$4,IF(INT((G271-95)/10)>5,0.09,0.07),IF(INT((I271-95)/10)>5,0.09,0.07)))))))) -> 0.11 | U271: =S271*T271 -> 0.77 | V271: =IF(E271>25,IF(F271<115,1,INT((F271-95)/10)),(IF(F271<115,1,INT((F271-95)/10))+IF(I271<115,1,INT((I271-95)/10)))/2) -> 6.5 | W271: =IF(V271>=8,"8M",IF(V271>=7,"7M",IF(E271<=信息总览!$B$4,IF(I271>164,"伪名",""),IF(AND(E271>信息总览!$B$4,E271<26,G271>164),"伪名","")))) -> 伪名 | X271: =IF(I271<140,0,IF(E271>23,0,I271-G271)) -> 0
A272: =W272 -> 伪名 | B272: 37071197 | C272: Ryan Gravenberch | E272: 23 | F272: 159 | G272: 166 | H272: =IFERROR(VLOOKUP(B272,球员对应球队!A:D,4,FALSE)-G272,"") -> 0 | I272: 169 | J272: DM/M/AM/C | K272: 荷兰 | L272: Celtic | M272: =VLOOKUP(L272,信息总览!C:E,3,FALSE) -> 甲级 | P272: =IF(F272<115,1,INT((F272-95)/10)) -> 6 | Q272: =IF(G272<115,1,INT((G272-95)/10)) -> 7 | R272: =IF(I272<115,1,INT((I272-95)/10)) -> 7 | S272: =IF(E272>信息总览!$B$4,Q272,IF(I272<140,Q272,(Q272+R272)/2)) -> 7 | T272: =IF(AND(J272="GK",W272<>""),0.1,IF(S272=1,0.1,IF((S272+V272)/2=1,0.1,IF(W272="8M",0.15,IF(W272="7M",0.13,IF(W272="伪名",0.11,IF(E272>信息总览!$B$4,IF(INT((G272-95)/10)>5,0.09,0.07),IF(INT((I272-95)/10)>5,0.09,0.07)))))))) -> 0.11 | U272: =S272*T272 -> 0.77 | V272: =IF(E272>25,IF(F272<115,1,INT((F272-95)/10)),(IF(F272<115,1,INT((F272-95)/10))+IF(I272<115,1,INT((I272-95)/10)))/2) -> 6.5 | W272: =IF(V272>=8,"8M",IF(V272>=7,"7M",IF(E272<=信息总览!$B$4,IF(I272>164,"伪名",""),IF(AND(E272>信息总览!$B$4,E272<26,G272>164),"伪名","")))) -> 伪名 | X272: =IF(I272<140,0,IF(E272>23,0,I272-G272)) -> 3
A273: =W273 | B273: 48042717 | C273: Ibrahim Sangaré | E273: 27 | F273: 145 | G273: 145 | H273: =IFERROR(VLOOKUP(B273,球员对应球队!A:D,4,FALSE)-G273,"") -> 0 | I273: 149 | J273: DM/MC | K273: Ivory Coast | L273: Celtic | M273: =VLOOKUP(L273,信息总览!C:E,3,FALSE) -> 甲级 | P273: =IF(F273<115,1,INT((F273-95)/10)) -> 5 | Q273: =IF(G273<115,1,INT((G273-95)/10)) -> 5 | R273: =IF(I273<115,1,INT((I273-95)/10)) -> 5 | S273: =IF(E273>信息总览!$B$4,Q273,IF(I273<140,Q273,(Q273+R273)/2)) -> 5 | T273: =IF(AND(J273="GK",W273<>""),0.1,IF(S273=1,0.1,IF((S273+V273)/2=1,0.1,IF(W273="8M",0.15,IF(W273="7M",0.13,IF(W273="伪名",0.11,IF(E273>信息总览!$B$4,IF(INT((G273-95)/10)>5,0.09,0.07),IF(INT((I273-95)/10)>5,0.09,0.07)))))))) -> 0.07 | U273: =S273*T273 -> 0.35 | V273: =IF(E273>25,IF(F273<115,1,INT((F273-95)/10)),(IF(F273<115,1,INT((F273-95)/10))+IF(I273<115,1,INT((I273-95)/10)))/2) -> 5 | W273: =IF(V273>=8,"8M",IF(V273>=7,"7M",IF(E273<=信息总览!$B$4,IF(I273>164,"伪名",""),IF(AND(E273>信息总览!$B$4,E273<26,G273>164),"伪名","")))) | X273: =IF(I273<140,0,IF(E273>23,0,I273-G273)) -> 0
A274: =W274 | B274: 12078756 | C274: Ousmane Diakité | E274: 25 | F274: 122 | G274: 122 | I274: 140 | J274: DM C | K274: Mali | L274: Celtic | M274: =VLOOKUP(L274,信息总览!C:E,3,FALSE) -> 甲级 | P274: =IF(F274<115,1,INT((F274-95)/10)) -> 2 | Q274: =IF(G274<115,1,INT((G274-95)/10)) -> 2 | R274: =IF(I274<115,1,INT((I274-95)/10)) -> 4 | S274: =IF(E274>信息总览!$B$4,Q274,IF(I274<140,Q274,(Q274+R274)/2)) -> 2 | T274: =IF(AND(J274="GK",W274<>""),0.1,IF(S274=1,0.1,IF((S274+V274)/2=1,0.1,IF(W274="8M",0.15,IF(W274="7M",0.13,IF(W274="伪名",0.11,IF(E274>信息总览!$B$4,IF(INT((G274-95)/10)>5,0.09,0.07),IF(INT((I274-95)/10)>5,0.09,0.07)))))))) -> 0.07 | U274: =S274*T274 -> 0.14 | V274: =IF(E274>25,IF(F274<115,1,INT((F274-95)/10)),(IF(F274<115,1,INT((F274-95)/10))+IF(I274<115,1,INT((I274-95)/10)))/2) -> 3 | W274: =IF(V274>=8,"8M",IF(V274>=7,"7M",IF(E274<=信息总览!$B$4,IF(I274>164,"伪名",""),IF(AND(E274>信息总览!$B$4,E274<26,G274>164),"伪名","")))) | X274: =IF(I274<140,0,IF(E274>23,0,I274-G274)) -> 0
A275: =W275 | B275: 2000188173 | C275: Assan Ouédraogo | E275: 19 | F275: 135 | G275: 135 | H275: =IFERROR(VLOOKUP(B275,球员对应球队!A:D,4,FALSE)-G275,"") -> 0 | I275: 163 | J275: M/AMLC | K275: 荷兰 | L275: Chelsea | M275: =VLOOKUP(L275,信息总览!C:E,3,FALSE) -> 超级 | P275: =IF(F275<115,1,INT((F275-95)/10)) -> 4 | Q275: =IF(G275<115,1,INT((G275-95)/10)) -> 4 | R275: =IF(I275<115,1,INT((I275-95)/10)) -> 6 | S275: =IF(E275>信息总览!$B$4,Q275,IF(I275<140,Q275,(Q275+R275)/2)) -> 5 | T275: =IF(AND(J275="GK",W275<>""),0.1,IF(S275=1,0.1,IF((S275+V275)/2=1,0.1,IF(W275="8M",0.15,IF(W275="7M",0.13,IF(W275="伪名",0.11,IF(E275>信息总览!$B$4,IF(INT((G275-95)/10)>5,0.09,0.07),IF(INT((I275-95)/10)>5,0.09,0.07)))))))) -> 0.09 | U275: =S275*T275 -> 0.45 | V275: =IF(E275>25,IF(F275<115,1,INT((F275-95)/10)),(IF(F275<115,1,INT((F275-95)/10))+IF(I275<115,1,INT((I275-95)/10)))/2) -> 5 | W275: =IF(V275>=8,"8M",IF(V275>=7,"7M",IF(E275<=信息总览!$B$4,IF(I275>164,"伪名",""),IF(AND(E275>信息总览!$B$4,E275<26,G275>164),"伪名","")))) | X275: =IF(I275<140,0,IF(E275>23,0,I275-G275)) -> 28
A276: =W276 | B276: 19326796 | C276: Éderson | E276: 26 | F276: 157 | G276: 157 | H276: =IFERROR(VLOOKUP(B276,球员对应球队!A:D,4,FALSE)-G276,"") -> 0 | I276: 166 | J276: DM/MC | K276: 巴西 | L276: Chelsea | M276: =VLOOKUP(L276,信息总览!C:E,3,FALSE) -> 超级 | P276: =IF(F276<115,1,INT((F276-95)/10)) -> 6 | Q276: =IF(G276<115,1,INT((G276-95)/10)) -> 6 | R276: =IF(I276<115,1,INT((I276-95)/10)) -> 7 | S276: =IF(E276>信息总览!$B$4,Q276,IF(I276<140,Q276,(Q276+R276)/2)) -> 6 | T276: =IF(AND(J276="GK",W276<>""),0.1,IF(S276=1,0.1,IF((S276+V276)/2=1,0.1,IF(W276="8M",0.15,IF(W276="7M",0.13,IF(W276="伪名",0.11,IF(E276>信息总览!$B$4,IF(INT((G276-95)/10)>5,0.09,0.07),IF(INT((I276-95)/10)>5,0.09,0.07)))))))) -> 0.09 | U276: =S276*T276 -> 0.54 | V276: =IF(E276>25,IF(F276<115,1,INT((F276-95)/10)),(IF(F276<115,1,INT((F276-95)/10))+IF(I276<115,1,INT((I276-95)/10)))/2) -> 6 | W276: =IF(V276>=8,"8M",IF(V276>=7,"7M",IF(E276<=信息总览!$B$4,IF(I276>164,"伪名",""),IF(AND(E276>信息总览!$B$4,E276<26,G276>164),"伪名","")))) | X276: =IF(I276<140,0,IF(E276>23,0,I276-G276)) -> 0
A277: =W277 -> 7M | B277: 28120042 | C277: Cole Palmer | E277: 23 | F277: 173 | G277: 173 | H277: =IFERROR(VLOOKUP(B277,球员对应球队!A:D,4,FALSE)-G277,"") -> 0 | I277: 173 | J277: AM/RLC | K277: 英格兰 | L277: Chelsea | M277: =VLOOKUP(L277,信息总览!C:E,3,FALSE) -> 超级 | P277: =IF(F277<115,1,INT((F277-95)/10)) -> 7 | Q277: =IF(G277<115,1,INT((G277-95)/10)) -> 7 | R277: =IF(I277<115,1,INT((I277-95)/10)) -> 7 | S277: =IF(E277>信息总览!$B$4,Q277,IF(I277<140,Q277,(Q277+R277)/2)) -> 7 | T277: =IF(AND(J277="GK",W277<>""),0.1,IF(S277=1,0.1,IF((S277+V277)/2=1,0.1,IF(W277="8M",0.15,IF(W277="7M",0.13,IF(W277="伪名",0.11,IF(E277>信息总览!$B$4,IF(INT((G277-95)/10)>5,0.09,0.07),IF(INT((I277-95)/10)>5,0.09,0.07)))))))) -> 0.13 | U277: =S277*T277 -> 0.91 | V277: =IF(E277>25,IF(F277<115,1,INT((F277-95)/10)),(IF(F277<115,1,INT((F277-95)/10))+IF(I277<115,1,INT((I277-95)/10)))/2) -> 7 | W277: =IF(V277>=8,"8M",IF(V277>=7,"7M",IF(E277<=信息总览!$B$4,IF(I277>164,"伪名",""),IF(AND(E277>信息总览!$B$4,E277<26,G277>164),"伪名","")))) -> 7M | X277: =IF(I277<140,0,IF(E277>23,0,I277-G277)) -> 0
A278: =W278 -> 伪名 | B278: 18115012 | C278: Roméo Lavia | E278: 21 | F278: 140 | G278: 151 | H278: =IFERROR(VLOOKUP(B278,球员对应球队!A:D,4,FALSE)-G278,"") -> 0 | I278: 174 | J278: DM/MC | K278: 比利时 | L278: Chelsea | M278: =VLOOKUP(L278,信息总览!C:E,3,FALSE) -> 超级 | P278: =IF(F278<115,1,INT((F278-95)/10)) -> 4 | Q278: =IF(G278<115,1,INT((G278-95)/10)) -> 5 | R278: =IF(I278<115,1,INT((I278-95)/10)) -> 7 | S278: =IF(E278>信息总览!$B$4,Q278,IF(I278<140,Q278,(Q278+R278)/2)) -> 6 | T278: =IF(AND(J278="GK",W278<>""),0.1,IF(S278=1,0.1,IF((S278+V278)/2=1,0.1,IF(W278="8M",0.15,IF(W278="7M",0.13,IF(W278="伪名",0.11,IF(E278>信息总览!$B$4,IF(INT((G278-95)/10)>5,0.09,0.07),IF(INT((I278-95)/10)>5,0.09,0.07)))))))) -> 0.11 | U278: =S278*T278 -> 0.66 | V278: =IF(E278>25,IF(F278<115,1,INT((F278-95)/10)),(IF(F278<115,1,INT((F278-95)/10))+IF(I278<115,1,INT((I278-95)/10)))/2) -> 5.5 | W278: =IF(V278>=8,"8M",IF(V278>=7,"7M",IF(E278<=信息总览!$B$4,IF(I278>164,"伪名",""),IF(AND(E278>信息总览!$B$4,E278<26,G278>164),"伪名","")))) -> 伪名 | X278: =IF(I278<140,0,IF(E278>23,0,I278-G278)) -> 23
A279: =W279 | B279: 49038942 | C279: Benoît Badiashile | E279: 24 | F279: 147 | G279: 153 | H279: =IFERROR(VLOOKUP(B279,球员对应球队!A:D,4,FALSE)-G279,"") -> 0 | I279: 163 | J279: D/C | K279: 法国 | L279: Chelsea | M279: =VLOOKUP(L279,信息总览!C:E,3,FALSE) -> 超级 | P279: =IF(F279<115,1,INT((F279-95)/10)) -> 5 | Q279: =IF(G279<115,1,INT((G279-95)/10)) -> 5 | R279: =IF(I279<115,1,INT((I279-95)/10)) -> 6 | S279: =IF(E279>信息总览!$B$4,Q279,IF(I279<140,Q279,(Q279+R279)/2)) -> 5.5 | T279: =IF(AND(J279="GK",W279<>""),0.1,IF(S279=1,0.1,IF((S279+V279)/2=1,0.1,IF(W279="8M",0.15,IF(W279="7M",0.13,IF(W279="伪名",0.11,IF(E279>信息总览!$B$4,IF(INT((G279-95)/10)>5,0.09,0.07),IF(INT((I279-95)/10)>5,0.09,0.07)))))))) -> 0.09 | U279: =S279*T279 -> 0.495 | V279: =IF(E279>25,IF(F279<115,1,INT((F279-95)/10)),(IF(F279<115,1,INT((F279-95)/10))+IF(I279<115,1,INT((I279-95)/10)))/2) -> 5.5 | W279: =IF(V279>=8,"8M",IF(V279>=7,"7M",IF(E279<=信息总览!$B$4,IF(I279>164,"伪名",""),IF(AND(E279>信息总览!$B$4,E279<26,G279>164),"伪名","")))) | X279: =IF(I279<140,0,IF(E279>23,0,I279-G279)) -> 0
A280: =W280 | B280: 67030171 | C280: David De Gea | E280: 34 | F280: 151 | G280: 151 | H280: =IFERROR(VLOOKUP(B280,球员对应球队!A:D,4,FALSE)-G280,"") -> 0 | I280: 178 | J280: GK | K280: 西班牙 | L280: Chelsea | M280: =VLOOKUP(L280,信息总览!C:E,3,FALSE) -> 超级 | P280: =IF(F280<115,1,INT((F280-95)/10)) -> 5 | Q280: =IF(G280<115,1,INT((G280-95)/10)) -> 5 | R280: =IF(I280<115,1,INT((I280-95)/10)) -> 8 | S280: =IF(E280>信息总览!$B$4,Q280,IF(I280<140,Q280,(Q280+R280)/2)) -> 5 | T280: =IF(AND(J280="GK",W280<>""),0.1,IF(S280=1,0.1,IF((S280+V280)/2=1,0.1,IF(W280="8M",0.15,IF(W280="7M",0.13,IF(W280="伪名",0.11,IF(E280>信息总览!$B$4,IF(INT((G280-95)/10)>5,0.09,0.07),IF(INT((I280-95)/10)>5,0.09,0.07)))))))) -> 0.07 | U280: =S280*T280 -> 0.35 | V280: =IF(E280>25,IF(F280<115,1,INT((F280-95)/10)),(IF(F280<115,1,INT((F280-95)/10))+IF(I280<115,1,INT((I280-95)/10)))/2) -> 5 | W280: =IF(V280>=8,"8M",IF(V280>=7,"7M",IF(E280<=信息总览!$B$4,IF(I280>164,"伪名",""),IF(AND(E280>信息总览!$B$4,E280<26,G280>164),"伪名","")))) | X280: =IF(I280<140,0,IF(E280>23,0,I280-G280)) -> 0
A281: =W281 | B281: 29079830 | C281: Jacob Murphy | E281: 30 | F281: 140 | G281: 140 | H281: =IFERROR(VLOOKUP(B281,球员对应球队!A:D,4,FALSE)-G281,"") -> 0 | I281: 140 | J281: M/AMRL | K281: 英格兰 | L281: Chelsea | M281: =VLOOKUP(L281,信息总览!C:E,3,FALSE) -> 超级 | P281: =IF(F281<115,1,INT((F281-95)/10)) -> 4 | Q281: =IF(G281<115,1,INT((G281-95)/10)) -> 4 | R281: =IF(I281<115,1,INT((I281-95)/10)) -> 4 | S281: =IF(E281>信息总览!$B$4,Q281,IF(I281<140,Q281,(Q281+R281)/2)) -> 4 | T281: =IF(AND(J281="GK",W281<>""),0.1,IF(S281=1,0.1,IF((S281+V281)/2=1,0.1,IF(W281="8M",0.15,IF(W281="7M",0.13,IF(W281="伪名",0.11,IF(E281>信息总览!$B$4,IF(INT((G281-95)/10)>5,0.09,0.07),IF(INT((I281-95)/10)>5,0.09,0.07)))))))) -> 0.07 | U281: =S281*T281 -> 0.28 | V281: =IF(E281>25,IF(F281<115,1,INT((F281-95)/10)),(IF(F281<115,1,INT((F281-95)/10))+IF(I281<115,1,INT((I281-95)/10)))/2) -> 4 | W281: =IF(V281>=8,"8M",IF(V281>=7,"7M",IF(E281<=信息总览!$B$4,IF(I281>164,"伪名",""),IF(AND(E281>信息总览!$B$4,E281<26,G281>164),"伪名","")))) | X281: =IF(I281<140,0,IF(E281>23,0,I281-G281)) -> 0
A282: =W282 | B282: 27104982 | C282: Jens Stage | E282: 28 | F282: 142 | G282: 142 | H282: =IFERROR(VLOOKUP(B282,球员对应球队!A:D,4,FALSE)-G282,"") -> 0 | I282: 145 | J282: DM/MRC | K282: 丹麦 | L282: Chelsea | M282: =VLOOKUP(L282,信息总览!C:E,3,FALSE) -> 超级 | P282: =IF(F282<115,1,INT((F282-95)/10)) -> 4 | Q282: =IF(G282<115,1,INT((G282-95)/10)) -> 4 | R282: =IF(I282<115,1,INT((I282-95)/10)) -> 5 | S282: =IF(E282>信息总览!$B$4,Q282,IF(I282<140,Q282,(Q282+R282)/2)) -> 4 | T282: =IF(AND(J282="GK",W282<>""),0.1,IF(S282=1,0.1,IF((S282+V282)/2=1,0.1,IF(W282="8M",0.15,IF(W282="7M",0.13,IF(W282="伪名",0.11,IF(E282>信息总览!$B$4,IF(INT((G282-95)/10)>5,0.09,0.07),IF(INT((I282-95)/10)>5,0.09,0.07)))))))) -> 0.07 | U282: =S282*T282 -> 0.28 | V282: =IF(E282>25,IF(F282<115,1,INT((F282-95)/10)),(IF(F282<115,1,INT((F282-95)/10))+IF(I282<115,1,INT((I282-95)/10)))/2) -> 4 | W282: =IF(V282>=8,"8M",IF(V282>=7,"7M",IF(E282<=信息总览!$B$4,IF(I282>164,"伪名",""),IF(AND(E282>信息总览!$B$4,E282<26,G282>164),"伪名","")))) | X282: =IF(I282<140,0,IF(E282>23,0,I282-G282)) -> 0
A283: =W283 -> 伪名 | B283: 28126247 | C283: Liam Delap | E283: 22 | F283: 141 | G283: 152 | H283: =IFERROR(VLOOKUP(B283,球员对应球队!A:D,4,FALSE)-G283,"") -> 0 | I283: 175 | J283: AMR/ST | K283: 英格兰 | L283: Chelsea | M283: =VLOOKUP(L283,信息总览!C:E,3,FALSE) -> 超级 | P283: =IF(F283<115,1,INT((F283-95)/10)) -> 4 | Q283: =IF(G283<115,1,INT((G283-95)/10)) -> 5 | R283: =IF(I283<115,1,INT((I283-95)/10)) -> 8 | S283: =IF(E283>信息总览!$B$4,Q283,IF(I283<140,Q283,(Q283+R283)/2)) -> 6.5 | T283: =IF(AND(J283="GK",W283<>""),0.1,IF(S283=1,0.1,IF((S283+V283)/2=1,0.1,IF(W283="8M",0.15,IF(W283="7M",0.13,IF(W283="伪名",0.11,IF(E283>信息总览!$B$4,IF(INT((G283-95)/10)>5,0.09,0.07),IF(INT((I283-95)/10)>5,0.09,0.07)))))))) -> 0.11 | U283: =S283*T283 -> 0.715 | V283: =IF(E283>25,IF(F283<115,1,INT((F283-95)/10)),(IF(F283<115,1,INT((F283-95)/10))+IF(I283<115,1,INT((I283-95)/10)))/2) -> 6 | W283: =IF(V283>=8,"8M",IF(V283>=7,"7M",IF(E283<=信息总览!$B$4,IF(I283>164,"伪名",""),IF(AND(E283>信息总览!$B$4,E283<26,G283>164),"伪名","")))) -> 伪名 | X283: =IF(I283<140,0,IF(E283>23,0,I283-G283)) -> 23
A284: =W284 | B284: 76049803 | C284: Luis Díaz | E284: 28 | F284: 162 | G284: 162 | H284: =IFERROR(VLOOKUP(B284,球员对应球队!A:D,4,FALSE)-G284,"") -> 0 | I284: 170 | J284: AM/RL | K284: 哥伦比亚 | L284: Chelsea | M284: =VLOOKUP(L284,信息总览!C:E,3,FALSE) -> 超级 | P284: =IF(F284<115,1,INT((F284-95)/10)) -> 6 | Q284: =IF(G284<115,1,INT((G284-95)/10)) -> 6 | R284: =IF(I284<115,1,INT((I284-95)/10)) -> 7 | S284: =IF(E284>信息总览!$B$4,Q284,IF(I284<140,Q284,(Q284+R284)/2)) -> 6 | T284: =IF(AND(J284="GK",W284<>""),0.1,IF(S284=1,0.1,IF((S284+V284)/2=1,0.1,IF(W284="8M",0.15,IF(W284="7M",0.13,IF(W284="伪名",0.11,IF(E284>信息总览!$B$4,IF(INT((G284-95)/10)>5,0.09,0.07),IF(INT((I284-95)/10)>5,0.09,0.07)))))))) -> 0.09 | U284: =S284*T284 -> 0.54 | V284: =IF(E284>25,IF(F284<115,1,INT((F284-95)/10)),(IF(F284<115,1,INT((F284-95)/10))+IF(I284<115,1,INT((I284-95)/10)))/2) -> 6 | W284: =IF(V284>=8,"8M",IF(V284>=7,"7M",IF(E284<=信息总览!$B$4,IF(I284>164,"伪名",""),IF(AND(E284>信息总览!$B$4,E284<26,G284>164),"伪名","")))) | X284: =IF(I284<140,0,IF(E284>23,0,I284-G284)) -> 0
A285: =W285 | B285: 2000107103 | C285: Mamadou Sarr | E285: 19 | F285: 130 | G285: 136 | H285: =IFERROR(VLOOKUP(B285,球员对应球队!A:D,4,FALSE)-G285,"") -> 0 | I285: 160 | J285: DC/DM | K285: 法国 | L285: Chelsea | M285: =VLOOKUP(L285,信息总览!C:E,3,FALSE) -> 超级 | P285: =IF(F285<115,1,INT((F285-95)/10)) -> 3 | Q285: =IF(G285<115,1,INT((G285-95)/10)) -> 4 | R285: =IF(I285<115,1,INT((I285-95)/10)) -> 6 | S285: =IF(E285>信息总览!$B$4,Q285,IF(I285<140,Q285,(Q285+R285)/2)) -> 5 | T285: =IF(AND(J285="GK",W285<>""),0.1,IF(S285=1,0.1,IF((S285+V285)/2=1,0.1,IF(W285="8M",0.15,IF(W285="7M",0.13,IF(W285="伪名",0.11,IF(E285>信息总览!$B$4,IF(INT((G285-95)/10)>5,0.09,0.07),IF(INT((I285-95)/10)>5,0.09,0.07)))))))) -> 0.09 | U285: =S285*T285 -> 0.45 | V285: =IF(E285>25,IF(F285<115,1,INT((F285-95)/10)),(IF(F285<115,1,INT((F285-95)/10))+IF(I285<115,1,INT((I285-95)/10)))/2) -> 4.5 | W285: =IF(V285>=8,"8M",IF(V285>=7,"7M",IF(E285<=信息总览!$B$4,IF(I285>164,"伪名",""),IF(AND(E285>信息总览!$B$4,E285<26,G285>164),"伪名","")))) | X285: =IF(I285<140,0,IF(E285>23,0,I285-G285)) -> 24
...

Sheet 成长人
A1: 俱乐部 | B1: 姓名 | C1: 年龄 | D1: CA | E1: PA | F1: 当前CA
A2: AS Roma | B2: Curtis Jones | C2: 24 | D2: 153 | E2: 162 | F2: 159
A3: AS Roma | B3: Dário Essugo | C3: 20 | D3: 127 | E3: 170 | F3: 134
A4: AS Roma | B4: Estêvão | C4: 18 | D4: 143 | E4: 188 | F4: 152
A5: AS Roma | B5: Franco Mastantuono | C5: 17 | D5: 142 | E5: 171 | F5: 149
A6: AS Roma | B6: Jacobo Ramón | C6: 20 | D6: 130 | E6: 150 | F6: 135
A7: AS Roma | B7: Marc Guéhi | C7: 25 | D7: 160 | E7: 168 | F7: 167
A8: As Roma | B8: Saël Kumbedi | C8: 20 | D8: 122 | E8: 160 | F8: 128
A9: As Roma | B9: Nicolò Savona | C9: 22 | D9: 142 | E9: 155 | F9: 148
A10: Aston Villa | B10: Abdukodir Khusanov | C10: 21 | D10: 140 | E10: 173 | F10: 147
A11: Aston Villa | B11: Abdul Fatawu | C11: 21 | D11: 137 | E11: 160 | F11: 143
A12: Aston Villa | B12: Amadou Onana | C12: 23 | D12: 145 | E12: 160 | F12: 151
A13: Aston Villa | B13: Filip Jörgensen | C13: 23 | D13: 144 | E13: 169 | F13: 151
... A430: West Ham | B430: Rio Ngumoha | C430: 16 | D430: 145 | E430: 164 | F430: 151

Sheet 解约

Sheet 消费
A1: 球队 | B1: 球员编号 | C1: 球员英文名 | D1: 年龄 | E1: 提升后CA值 | F1: PA值 | G1: 名单中CA | H1: 差值

Sheet 选秀

Sheet 交易
A1: 出售球队 | B1: 球员名 | C1: 年龄 | D1: CA | E1: PA | F1: 购买球队 | G1: 转入球队英文名 | H1: 是否存在在目前名单 | I1: 价格 | J1: 帖子链接 | K1: 成交信息

Sheet 强制
A1: 球员 | B1: 年龄 | C1: CA | D1: PA | E1: 是否在队 | F1: 现实转入
A2: Rodrigo Mendoza | B2: =VLOOKUP(A2,联赛名单!$C:$E,3,FALSE) -> 20 | C2: =VLOOKUP(A2,联赛名单!$C:$I,5,FALSE) -> 136 | D2: =VLOOKUP(A2,联赛名单!$C:$I,6,FALSE) -> 0 | E2: 是
A3: Adam Armstrong | B3: 28 | C3: 126 | D3: 138 | F3: Wolves
A4: Obed Vargas | B4: 19 | C4: 115 | D4: 155 | F4: Atlético
A5: Luca Netz | B5: 22 | C5: 122 | D5: 140 | F5: Nott'm Forest
A6: Jonas Adjetey | B6: 21 | C6: 118 | D6: 144 | F6: Wolfsburg
A7: Jørgen Strand Larsen | B7: =VLOOKUP(A7,联赛名单!$C:$E,3,FALSE) -> 25 | C7: =VLOOKUP(A7,联赛名单!$C:$I,5,FALSE) -> 140 | D7: =VLOOKUP(A7,联赛名单!$C:$I,6,FALSE) -> 0 | E7: 是
A8: Darryl Bakola | B8: =VLOOKUP(A8,联赛名单!$C:$E,3,FALSE) -> 17 | C8: =VLOOKUP(A8,联赛名单!$C:$I,5,FALSE) -> 90 | D8: =VLOOKUP(A8,联赛名单!$C:$I,6,FALSE) -> 0 | E8: 是
A9: Ademola Lookman | B9: =VLOOKUP(A9,联赛名单!$C:$E,3,FALSE) -> 27 | C9: =VLOOKUP(A9,联赛名单!$C:$I,5,FALSE) -> 160 | D9: =VLOOKUP(A9,联赛名单!$C:$I,6,FALSE) | E9: 是
A10: Armel Bella-Kotchap | B10: 23 | C10: 124 | D10: 143 | F10: Hellas Verona
A11: Alphadjo Cissè | B11: 18 | C11: 100 | D11: 158 | F11: AC Milan
A12: Álvaro Fidalgo | B12: 28 | C12: 144 | D12: 145 | F12: Real Betis
A13: Kader Meïté | B13: 17 | C13: 105 | D13: 151 | F13: Al-Hilal
A14: Oleksandr Zinchenko | B14: 28 | C14: 149 | D14: 165 | F14: ajax
A15: Tim Drexler | B15: 20 | C15: 115 | D15: 146 | F15: Salzburg
A16: Oscar Bobb | B16: =VLOOKUP(A16,联赛名单!$C:$E,3,FALSE) -> 22 | C16: =VLOOKUP(A16,联赛名单!$C:$I,5,FALSE) -> 138 | D16: =VLOOKUP(A16,联赛名单!$C:$I,6,FALSE) -> 0 | E16: 是
A17: Alex Freeman | B17: =VLOOKUP(A17,联赛名单!$C:$E,3,FALSE) -> 20 | C17: =VLOOKUP(A17,联赛名单!$C:$I,5,FALSE) -> 131 | D17: =VLOOKUP(A17,联赛名单!$C:$I,6,FALSE) -> 0 | E17: 是
A18: Lucas Paquetá | B18: 27 | C18: 140 | D18: 161 | F18: Flamengo
A19: Adama Traoré | B19: =VLOOKUP(A19,联赛名单!$C:$E,3,FALSE) -> 29 | C19: =VLOOKUP(A19,联赛名单!$C:$I,5,FALSE) -> 137 | D19: =VLOOKUP(A19,联赛名单!$C:$I,6,FALSE) -> 0 | E19: 是
A20: Tammy Abraham | B20: 27 | C20: 142 | D20: 155 | F20: Aston Villa
A21: Rayan | B21: =VLOOKUP(A21,联赛名单!$C:$E,3,FALSE) -> 16 | C21: =VLOOKUP(A21,联赛名单!$C:$I,5,FALSE) -> 128 | D21: =VLOOKUP(A21,联赛名单!$C:$I,6,FALSE) -> 0 | E21: 是
A22: Dro Fernández | B22: 17 | C22: 105 | D22: 172 | F22: PSG
A23: Giovane | B23: 21 | C23: 125 | D23: 149 | F23: Napoli
A24: Félix Lemaréchal | B24: 21 | C24: 130 | D24: 153 | F24: Club Brugge
A25: Quinten Timber | B25: 24 | C25: 146 | D25: 156
A26: Souza | B26: =VLOOKUP(A26,联赛名单!$C:$E,3,FALSE) -> 19 | C26: =VLOOKUP(A26,联赛名单!$C:$I,5,FALSE) -> 132 | D26: =VLOOKUP(A26,联赛名单!$C:$I,6,FALSE) -> 0 | E26: 是
A27: Raúl Moro | B27: 22 | C27: 135 | D27: 152
A28: Sander Tangvik | B28: 22 | C28: 118 | D28: 143
A29: Andrés Gómez | B29: 22 | C29: 128 | D29: 148
A30: Alex Tóth | B30: 19 | C30: 111 | D30: 140 | F30: Bournemouth
A31: Marc Guéhi | B31: =VLOOKUP(A31,联赛名单!$C:$E,3,FALSE) -> 25 | C31: =VLOOKUP(A31,联赛名单!$C:$I,5,FALSE) -> 167 | D31: =VLOOKUP(A31,联赛名单!$C:$I,6,FALSE) -> 0 | E31: 是
A32: Eivind Helland | B32: =VLOOKUP(A32,联赛名单!$C:$E,3,FALSE) -> 20 | C32: =VLOOKUP(A32,联赛名单!$C:$I,5,FALSE) -> 120 | D32: =VLOOKUP(A32,联赛名单!$C:$I,6,FALSE) -> 0 | E32: 是
A33: Giacomo Raspadori | B33: 25 | C33: 144 | D33: 151 | F33: Atalanta
A34: Robinio Vaz | B34: =VLOOKUP(A34,联赛名单!$C:$E,3,FALSE) -> 18 | C34: =VLOOKUP(A34,联赛名单!$C:$I,5,FALSE) -> 142 | D34: =VLOOKUP(A34,联赛名单!$C:$I,6,FALSE) -> 0 | E34: 是
A35: Conor Gallagher | B35: =VLOOKUP(A35,联赛名单!$C:$E,3,FALSE) -> 25 | C35: =VLOOKUP(A35,联赛名单!$C:$I,5,FALSE) -> 160 | D35: =VLOOKUP(A35,联赛名单!$C:$I,6,FALSE) -> 0 | E35: 是
A36: Ibrahima Sissoko | B36: =VLOOKUP(A36,联赛名单!$C:$E,3,FALSE) -> #N/A | C36: =VLOOKUP(A36,联赛名单!$C:$I,5,FALSE) -> #N/A | D36: =VLOOKUP(A36,联赛名单!$C:$I,6,FALSE) -> #N/A | E36: 是
A37: Brian Madjo | B37: =VLOOKUP(A37,联赛名单!$C:$E,3,FALSE) -> 16 | C37: =VLOOKUP(A37,联赛名单!$C:$I,5,FALSE) -> 95 | D37: =VLOOKUP(A37,联赛名单!$C:$I,6,FALSE) -> 0 | E37: 是
A38: Kaye Furo | B38: 18 | C38: 110 | D38: 150 | F38: Brentford
A39: Kenneth Taylor | B39: 23 | C39: 142 | D39: 156 | F39: lazio
A40: Antoine Semenyo | B40: =VLOOKUP(A40,联赛名单!$C:$E,3,FALSE) -> 25 | C40: =VLOOKUP(A40,联赛名单!$C:$I,5,FALSE) -> 158 | D40: =VLOOKUP(A40,联赛名单!$C:$I,6,FALSE) -> 0 | E40: 是
A41: Umar Sadiq | B41: 28 | C41: 134 | D41: 159 | F41: Valencia
A42: Mattéo Guendouzi | B42: 26 | C42: 152 | D42: 158
A43: Petar Ratkov | B43: 21 | C43: 118 | D43: 143 | F43: lazio
A44: Rafiu Durosinmi | B44: =VLOOKUP(A44,联赛名单!$C:$E,3,FALSE) -> 22 | C44: =VLOOKUP(A44,联赛名单!$C:$I,5,FALSE) -> 132 | D44: =VLOOKUP(A44,联赛名单!$C:$I,6,FALSE) -> 0 | E44: 是
A45: Taty Castellanos | B45: 26 | C45: 147 | D45: 152 | F45: Pisa
A46: Luís Guilherme | B46: =VLOOKUP(A46,联赛名单!$C:$E,3,FALSE) -> 19 | C46: =VLOOKUP(A46,联赛名单!$C:$I,5,FALSE) -> 143 | D46: =VLOOKUP(A46,联赛名单!$C:$I,6,FALSE) -> 0 | E46: 是
A47: Pascal Groß | B47: 34 | C47: 153 | D47: 155 | F47: Brighton
A48: Brennan Johnson | B48: =VLOOKUP(A48,联赛名单!$C:$E,3,FALSE) -> 22 | C48: =VLOOKUP(A48,联赛名单!$C:$I,5,FALSE) -> 148 | D48: =VLOOKUP(A48,联赛名单!$C:$I,6,FALSE) -> 0 | E48: 是
A49: Younes Ebnoutalib | B49: 21 | C49: 120 | D49: 140 | F49: Frankfurt
A50: Amadou Haidara | B50: 27 | C50: 138 | D50: 150 | F50: Lens
A51: Saël Kumbedi | B51: =VLOOKUP(A51,联赛名单!$C:$E,3,FALSE) -> 20 | C51: =VLOOKUP(A51,联赛名单!$C:$I,5,FALSE) -> 133 | D51: =VLOOKUP(A51,联赛名单!$C:$I,6,FALSE) -> 0 | E51: 是
A52: Love Arrhov | B52: 17 | C52: 102 | D52: 158 | F52: Frankfurt
A53: Ayoube Amaimouni-Echghouyab | B53: 20 | C53: 110 | D53: 135 | F53: Frankfurt
A54: Rafa Silva | B54: 32 | C54: 150 | D54: 158
A55: Ifeanyi Ndukwe | B55: 17 | C55: 87 | D55: 135 | F55: liverpool

Sheet 步骤
A1: 赛季末list
A2: 升降级 | B2: 完成
A3: 成长球员 | B3: 完成
A4: 交易球员 | B4: 212完成
A5: 消费
A6: 解约 | B6: 212完成
A7: 暗标 | B7: 完成
A8: 海捞
A9: 奖励工资帽

Sheet 球员对应球队
A1: UID | B1: 球员名 | C1: 年龄 | D1: CA | E1: PA | F1: 国籍 | G1: 球队 | H1: 位置 | I1: 联赛名单有无
A2: 29137172 | B2: Aaron Ramsdale | C2: 27 | D2: 142 | E2: 160 | F2: England | G2: FLA | H2: GK | I2: =IF(COUNTIF(联赛名单!B:B,A2)=0,"联赛名单里没有","")
A3: 2000168014 | B3: Abdukodir Khusanov | C3: 21 | D3: 147 | E3: 173 | F3: Uzbekistan | G3: Aston Villa | H3: D RC | I3: =IF(COUNTIF(联赛名单!B:B,A3)=0,"联赛名单里没有","")
A4: 13211267 | B4: Abdul Fatawu | C4: 21 | D4: 143 | E4: 160 | F4: Ghana | G4: Aston Villa | H4: M/AM R | I4: =IF(COUNTIF(联赛名单!B:B,A4)=0,"联赛名单里没有","")
A5: 67228634 | B5: Achraf Hakimi | C5: 26 | D5: 176 | E5: 179 | F5: Morocco,Spain | G5: Borussia Dortmund | H5: D/WB R | I5: =IF(COUNTIF(联赛名单!B:B,A5)=0,"联赛名单里没有","")
A6: 67174729 | B6: Adama Traoré | C6: 29 | D6: 137 | E6: 154 | F6: Spain,Mali | G6: FC Schalke 04 | H6: M/AM RL | I6: =IF(COUNTIF(联赛名单!B:B,A6)=0,"联赛名单里没有","")
A7: 14241914 | B7: Alan Varela | C7: 24 | D7: 156 | E7: 156 | F7: Argentina | G7: FC Schalke 04 | H7: DM/M C | I7: =IF(COUNTIF(联赛名单!B:B,A7)=0,"联赛名单里没有","")
A8: 67296654 | B8: Alejandro Balde | C8: 21 | D8: 160 | E8: 170 | F8: Spain,Guinea-Bissau,Dominican Republic | G8: Barcelona | H8: D/WB L | I8: =IF(COUNTIF(联赛名单!B:B,A8)=0,"联赛名单里没有","")
A9: 2000035036 | B9: Alejandro Garnacho | C9: 21 | D9: 159 | E9: 170 | F9: Argentina,Spain | G9: Tottenham Hotspur | H9: AM RL | I9: =IF(COUNTIF(联赛名单!B:B,A9)=0,"联赛名单里没有","")
A10: 62097693 | B10: Aleksandar Vukotić | C10: 30 | D10: 122 | E10: 125 | F10: Serbia,Bosnia and Herzegovina | G10: Everton | H10: D C | I10: =IF(COUNTIF(联赛名单!B:B,A10)=0,"联赛名单里没有","")
A11: 43252460 | B11: Alessandro Bastoni | C11: 26 | D11: 162 | E11: 169 | F11: Italy | G11: Blu-neri Milano | H11: D C | I11: =IF(COUNTIF(联赛名单!B:B,A11)=0,"联赛名单里没有","")
A12: 43270682 | B12: Alessandro Buongiorno | C12: 26 | D12: 155 | E12: 162 | F12: Italy | G12: Parthenope | H12: D C | I12: =IF(COUNTIF(联赛名单!B:B,A12)=0,"联赛名单里没有","")
A13: 43295108 | B13: Alessandro Plizzari | C13: 25 | D13: 114 | E13: 145 | F13: Italy | G13: Parthenope | H13: GK | I13: =IF(COUNTIF(联赛名单!B:B,A13)=0,"联赛名单里没有","")
... A1003: 2000395118 | B1003: Uchenna Ogundu | C1003: 19 | D1003: 134 | E1003: 160 | F1003: Nigeria | G1003: Manchester City | H1003: S R | I1003: =IF(COUNTIF(联赛名单!B:B,A1003)=0,"联赛名单里没有","")
A1004: 2000012523 | B1004: V.Tobias | C1004: 21 | D1004: 125 | E1004: 142 | F1004: Brazil,Spain | G1004: Sportklub Sturm Graz | H1004: D/WB R
A1005: 2000033291 | B1005: Valentín Barco | C1005: 21 | D1005: 141 | E1005: 158 | F1005: Argentina,Italy | G1005: Futebol Clube do Porto | H1005: D/WB/M LC
A1006: 2000077331 | B1006: Valentín Gómez | C1006: 22 | D1006: 130 | E1006: 154 | F1006: Argentina,Spain | G1006: Futebol Clube do Porto | H1006: D C
A1007: 19409448 | B1007: Vanderson | C1007: 24 | D1007: 141 | E1007: 148 | F1007: Brazil | G1007: Brighton & Hove Albion | H1007: D/WB/M R
A1008: 2000241044 | B1008: Vasilije Adžić | C1008: 19 | D1008: 134 | E1008: 160 | F1008: Montenegro | G1008: Sportklub Sturm Graz | H1008: M/AM LC
A1009: 2000288469 | B1009: Veljko Milosavljević | C1009: 18 | D1009: 112 | E1009: 144 | F1009: Serbia | G1009: Zhejiang FC | H1009: D C
A1010: 53174131 | B1010: Victor Boniface | C1010: 24 | D1010: 142 | E1010: 160 | F1010: Nigeria | G1010: Inter Miami CF | H1010: AM/S C
A1011: 2000202295 | B1011: Victor Froholdt | C1011: 19 | D1011: 153 | E1011: 157 | F1011: Denmark | G1011: Arsenal | H1011: DM/M C
A1012: 13158205 | B1012: Victor Osimhen | C1012: 26 | D1012: 160 | E1012: 170 | F1012: Nigeria | G1012: VfB Stuttgart | H1012: S
A1013: 2000179712 | B1013: Warren Zaïre-Emery | C1013: 19 | D1013: 156 | E1013: 170 | F1013: France | G1013: Inter Miami CF | H1013: DM/M RC
A1014: 2000083915 | B1014: Wesley | C1014: 21 | D1014: 148 | E1014: 153 | F1014: Brazil | G1014: Sport Lisboa e Benfica | H1014: D/WB RL
A1015: 2000375648 | B1015: Wisdom Mike | C1015: 16 | D1015: 108 | E1015: 160 | F1015: Germany,Nigeria | G1015: Leicester City | H1015: M/AM RL
... A1026: 2000443913 | B1026: Zé Lucas | C1026: 17 | D1026: 115 | E1026: 148 | F1026: Brazil | G1026: Sport Lisboa e Benfica | H1026: DM/M C

Sheet 疑似下海
A1: 名额 | B1: 编​号 | C1: 姓​名 | D1: 原年龄 | E1: 年​龄 | F1: 初始CA | G1: 当前CA | H1: PA | I1: 位​置 | J1: 国籍 | K1: 俱​乐部 | L1: 新俱乐部
B2: 2000385385 | C2: Gabriel Mec | E2: 17 | F2: 103 | G2: 103 | H2: 158 | I2: AM/RLC | J2: 巴西 | K2: A. Madrid
B3: 2000333587 | C3: Victor Orakpo | E3: 19 | F3: 108 | G3: 108 | H3: 158 | I3: ST | J3: 尼日利亚 | K3: A. Madrid
B4: 100773 | C4: Wang Dalei | E4: 36 | F4: 106 | G4: 106 | H4: 118 | I4: GK | J4: 中国 | K4: AC Milan
B5: 2000269520 | C5: Aaron Bouwman | E5: 17 | F5: 95 | G5: 95 | H5: 160 | I5: D/C | J5: 荷兰 | K5: Ajax
B6: 2000257577 | C6: Ayodele Thomas | E6: 18 | F6: 106 | G6: 106 | H6: 160 | I6: AM/L | J6: 荷兰 | K6: Ajax
B7: 37076262 | C7: Luciano Valente | E7: 21 | F7: 133 | G7: 133 | H7: 151 | I7: M/AMRLC | J7: 荷兰 | K7: Ajax
B8: 20000070509 | C8: Tjark Ernst | E8: 22 | F8: 120 | G8: 120 | H8: 142 | I8: GK | J8: 德国 | K8: Ajax
B9: 19184434 | C9: Carlos Coronel | E9: 28 | F9: 127 | G9: 127 | H9: 140 | I9: GK | J9: 巴拉圭 | K9: Ajax
B10: 2000303600 | C10: wang yu dong | E10: 18 | F10: 99 | G10: 99 | H10: 130 | I10: AMRL/ST | J10: 中国 | K10: Ajax
B11: 2000328963 | C11: Bogdan Popov | E11: 18 | F11: 114 | G11: 119 | H11: 150 | I11: ST | J11: 乌克兰 | K11: Arsenal
B12: 2000068412 | C12: Franjo Ivanović | E12: 21 | F12: 132 | G12: 137 | H12: 150 | I12: AMLC/ST | J12: 克罗地亚 | K12: Arsenal
B13: 49039003 | C13: Logan Evans Costa | E13: 24 | F13: 143 | G13: 143 | H13: 152 | K13: Bournemouth
B14: 37060600 | C14: Ferdi Erenay Kadıoğlu | E14: 25 | F14: 145 | G14: 150 | H14: 153 | I14: D/WB/RL | J14: 土耳其 | K14: Brighton
B15: 49048380 | C15: Georginio Rutter | E15: 23 | F15: 147 | G15: 153 | H15: 161 | I15: AMRC/ST | J15: 法国 | K15: Brighton
B16: 2000056845 | C16: James Beadle | E16: 21 | F16: 120 | G16: 120 | H16: 160 | I16: GK | J16: 0 | K16: Brighton
B17: 5108155 | C17: Jason Sean Steele | E17: 34 | F17: 141 | G17: 141 | H17: 145 | I17: GK | J17: 0 | K17: Brighton
B18: 28009441 | C18: Kyle Walker | E18: 35 | F18: 147 | G18: 147 | H18: 164 | I18: D/WB/R | J18: 英格兰 | K18: Brighton
B19: 29036189 | C19: Lewis Dunk | E19: 33 | F19: 147 | G19: 147 | H19: 154 | I19: D/C | J19: 英格兰 | K19: Brighton
B20: 37071145 | C20: Mats Henrik Berne Wieffer | E20: 25 | F20: 143 | G20: 148 | H20: 150 | I20: D/DM/M/C | J20: 荷兰 | K20: Brighton
B21: 29090530 | C21: Solly March | E21: 30 | F21: 149 | G21: 149 | H21: 149 | I21: WB/M/AM/RL | J21: 英格兰 | K21: Brighton
B22: 2000227373 | C22: Stefanos Tzimas | E22: 19 | F22: 126 | G22: 130 | H22: 141 | I22: ST | J22: 希腊 | K22: Brighton
B23: 2000243128 | C23: Gonzalo Petit | E23: 18 | F23: 115 | G23: 115 | H23: 160 | I23: ST | J23: 乌拉圭 | K23: Celtic
B24: 14077011 | C24: Nicolás Domínguez | E24: 27 | F24: 144 | G24: 144 | H24: 152 | I24: DM/MC | J24: 0 | K24: Celtic
C25: Rodrigo De Paul | E25: 31 | F25: 156 | G25: 156 | H25: 160 | I25: DM/M/C | J25: 阿根廷 | K25: Celtic
B26: 29116247 | C26: Ivan Toney | E26: 29 | F26: 150 | G26: 150 | H26: 155 | I26: ST | J26: 英格兰 | K26: CQ TL Loong
B27: 2000065824 | C27: Mio Backhaus | E27: 21 | F27: 125 | G27: 130 | H27: 152 | I27: GK | J27: 0 | K27: Everton
B28: 2000395140 | C28: Pau Cabanes | E28: 20 | F28: 125 | G28: 125 | H28: 156 | I28: AML/ST | J28: 西班牙 | K28: Everton
B29: 19348862 | C29: Kaio Jorge | E29: 23 | F29: 135 | G29: 135 | H29: 149 | K29: Everton
B30: 2000497719 | C30: Adil Hamdani | E30: 16 | F30: 84 | G30: 84 | H30: 143 | I30: AM/RL | J30: 法国 | K30: Fenerbahçe
B31: 43108998 | C31: Andrea Compagno | E31: 29 | F31: 135 | G31: 135 | H31: 140 | I31: ST | J31: 意大利 | K31: Fenerbahçe
B32: 63025710 | C32: Denis Vavro | E32: 29 | F32: 136 | G32: 136 | H32: 144 | I32: D/C | J32: 斯洛伐克 | K32: Fenerbahçe
B33: 2000072022 | C33: Igor Matanović | E33: 22 | F33: 125 | G33: 125 | H33: 145 | I33: ST | J33: 0 | K33: Fenerbahçe
B34: 18108540 | C34: Jonathan David | E34: 25 | F34: 150 | G34: 150 | H34: 154 | I34: AMRLC/ST | J34: 加拿大 | K34: Fenerbahçe
B35: 2000361948 | C35: Noah Codjo-Evora | E35: 17 | F35: 65 | G35: 65 | H35: 150 | I35: ST | J35: 法国 | K35: Fenerbahçe
B36: 36141840 | C36: Sotiris Alexandropoulos | E36: 23 | F36: 115 | G36: 115 | H36: 138 | I36: DM/MC | J36: 希腊 | K36: Fenerbahçe
B37: 2000452786 | C37: Yunus Azrak | E37: 16 | F37: 75 | G37: 75 | H37: 160 | I37: AM/RL | J37: 土耳其 | K37: Fenerbahçe
B38: 2000504183 | C38: Ziyad Baha | E38: 15 | F38: 73 | G38: 73 | H38: 140 | I38: ST | J38: 摩洛哥 | K38: Fenerbahçe
B39: 20049604 | C39: Ricardo Pepi | E39: 22 | F39: 139 | G39: 139 | H39: 155 | I39: ST | J39: 0 | K39: Juventus
B40: 2000212944 | C40: Mahamadou Diawara | E40: 20 | F40: 121 | G40: 121 | H40: 160 | I40: MC | J40: 法国 | K40: Lazio
B41: 47102376 | C41: Toluwalase Arokodare | E41: 24 | F41: 126 | G41: 126 | H41: 138 | I41: ST | J41: 0 | K41: Lazio
B42: 2000100062 | C42: Badredine Bouanani | E42: 20 | F42: 130 | G42: 130 | H42: 154 | I42: AM/R | J42: 0 | K42: Leeds
A43: 伪名 | B43: 37076355 | C43: Bart Verbruggen | E43: 22 | F43: 140 | G43: 140 | H43: 165 | I43: GK | J43: 0 | K43: Leeds
B44: 12081007 | C44: El Bilal Touré | E44: 23 | F44: 133 | G44: 133 | H44: 153 | I44: ST | J44: 0 | K44: Leeds
B45: 67248170 | C45: Jorge Cuenca | E45: 25 | F45: 135 | G45: 135 | H45: 150 | I45: D/C | J45: 西班牙 | K45: Leeds
B46: 2000020257 | C46: Jusef Erabi | E46: 22 | F46: 116 | G46: 116 | H46: 132 | I46: ST | J46: 瑞典 | K46: Leeds
B47: 2000105004 | C47: Leon Grgić | E47: 19 | F47: 116 | G47: 116 | H47: 154 | I47: AMR/ST | J47: 0 | K47: Leeds
B48: 33001438 | C48: Lukás Hrádecký | E48: 35 | F48: 140 | G48: 140 | H48: 144 | I48: GK | J48: 0 | K48: Leeds
B49: 29142052 | C49: Max Kilman | E49: 28 | F49: 135 | G49: 135 | H49: 150 | I49: D/C | J49: 0 | K49: Leeds
B50: 2000210544 | C50: Nathan Lowe | E50: 19 | F50: 110 | G50: 110 | H50: 140 | I50: MC | J50: 0 | K50: Leeds
B51: 43270517 | C51: Nicolò Zaniolo | E51: 25 | F51: 133 | G51: 133 | H51: 145 | I51: AM/RLC | J51: 意大利 | K51: Leeds
B52: 37059452 | C52: Pascal Struijk | E52: 25 | F52: 137 | G52: 137 | H52: 142 | I52: D/LC | J52: 0 | K52: Leeds
B53: 2000407507 | C53: Andre Harriman-Annous | E53: 17 | F53: 86 | G53: 86 | H53: 150 | I53: M/AMC/ST | J53: 0 | K53: Leicester
B54: 2000216555 | C54: Josh Nichols | E54: 18 | F54: 108 | G54: 113 | H54: 150 | I54: D/WB/RL | J54: 0 | K54: Leicester
B55: 28106528 | C55: Dara O'Shea | E55: 26 | F55: 133 | G55: 133 | H55: 140 | I55: D/RC | J55: 爱尔兰 | K55: Man City
B56: 67276071 | C56: Miguel Gutiérrez | E56: 24 | F56: 150 | G56: 156 | H56: 160 | I56: D/WB/L | J56: 西班牙 | K56: Napoli
B57: 12548699 | C57: Max Moerstedt | E57: 19 | F57: 115 | G57: 115 | H57: 160 | I57: ST | J57: 0 | K57: Newcastle
B58: 3004565 | C58: Yapp Hung Fai | E58: 35 | F58: 86 | G58: 86 | H58: 98 | I58: GK | J58: 中国 | K58: Newcastle
B59: 29141827 | C59: Ezri Konsa | E59: 27 | F59: 148 | G59: 148 | H59: 155 | I59: D/C | J59: 0 | K59: OL
B60: 92012109 | C60: Bernd Leno | E60: 33 | F60: 146 | G60: 146 | H60: 163 | I60: GK | J60: 德国 | K60: OL
B61: 28127273 | C61: Jonathan Rowe | E61: 22 | F61: 133 | G61: 133 | H61: 152 | I61: AML/ST | J61: 英格兰 | K61: OL
B62: 29194731 | C62: William Kokolo | E62: 25 | F62: 116 | G62: 116 | H62: 125 | I62: D/WB/L | J62: 0 | K62: OL
B63: 2000224667 | C63: Arthur Avom Ebong | E63: 20 | F63: 123 | G63: 123 | H63: 160 | I63: MC | J63: 喀麦隆 | K63: Paris SG
B64: 2000497044 | C64: David Boly | E64: 16 | F64: 88 | G64: 88 | H64: 160 | I64: D/R | J64: 法国 | K64: Paris SG
B65: 12081410 | C65: Ange Ahoussou | E65: 21 | F65: 115 | G65: 115 | H65: 145 | I65: D/L | J65: 0 | K65: R. Madrid
B66: 2000027898 | C66: Shea Charles | E66: 21 | F66: 128 | G66: 128 | H66: 160 | I66: DM | J66: 0 | K66: R. Madrid
B67: 2000251820 | C67: Jonah Kusi-Asare | E67: 18 | F67: 102 | G67: 102 | H67: 160 | I67: ST | J67: 0 | K67: Schalke 04
B68: 2000288733 | C68: Mahamadou Sangaré | E68: 18 | F68: 88 | G68: 88 | H68: 140 | I68: ST | J68: 法国 | K68: Sporting CP
B69: 2000031536 | C69: Soungoutou Magassa | E69: 21 | F69: 124 | G69: 124 | H69: 156 | I69: DM/DC | J69: 法国 | K69: Sporting CP
B70: 49053443 | C70: Lorenz Assignon | E70: 25 | F70: 134 | G70: 134 | H70: 140 | I70: D/WB/R | J70: 0 | K70: Sunderland
B71: 2000338374 | C71: Samuele Inácio | E71: 17 | F71: 87 | G71: 87 | H71: 160 | I71: M/AMC | J71: 意大利 | K71: Tottenham
A74: 名额 | B74: 编​号 | C74: 存档有无 | D74: 姓​名 | E74: 年​龄 | F74: 初始CA | G74: 当前CA | H74: PA | I74: 位​置 | J74: 国籍 | K74: 俱乐部 | L74: 级​别 | M74: 初始身价 | N74: 当前身价 | O74: 潜力身价 | P74: 身价 | Q74: 系数 | R74: 工资 | S74: 初始 | T74: 名额
B75: 2000130977 | C75: 存档没有 | D75: Antoine Mendy | E75: 21 | F75: 110 | G75: 110 | H75: 130 | I75: D/RC | J75: 塞内加尔 | K75: A. Madrid | L75: 甲级 | M75: 1 | N75: 1 | O75: 3 | P75: 1 | Q75: 0.1 | R75: 0.1 | S75: 2 | U75: 0
B76: 2000369658 | C76: 存档没有 | D76: Davinchi | E76: 17 | F76: 110 | G76: 110 | H76: 156 | I76: D/WB/L | J76: 西班牙 | K76: AS Roma | L76: 甲级 | M76: 1 | N76: 1 | O76: 6 | P76: 3.5 | Q76: 0.09 | R76: 0.315 | S76: 3.5 | U76: 46
B77: 67229630 | C77: 存档没有 | D77: Youssef En-Nesyri | E77: 28 | F77: 140 | G77: 140 | H77: 159 | I77: ST | J77: 摩洛哥 | K77: AS Roma | L77: 甲级 | M77: 4 | N77: 4 | O77: 6 | P77: 4 | Q77: 0.07 | R77: 0.28 | S77: 4 | U77: 0
B78: 14110846 | C78: 存档没有 | D78: Exequiel Palacios | E78: 26 | F78: 156 | G78: 156 | H78: 160 | I78: DM/MC | J78: 阿根廷 | K78: Benfica | L78: 乙级 | M78: 6 | N78: 6 | O78: 6 | P78: 6 | Q78: 0.09 | R78: 0.54 | S78: 6 | U78: 0
B79: 2000019418 | C79: 存档没有 | D79: Jorge Pascual | E79: 20 | F79: 129 | G79: 129 | H79: 150 | I79: ST | J79: 荷兰 | K79: Benfica | L79: 乙级 | M79: 3 | N79: 3 | O79: 5 | P79: 4 | Q79: 0.07 | R79: 0.28 | S79: 4 | U79: 21
B80: 51067947 | C80: 存档没有 | D80: Santiago Giménez | E80: 24 | F80: 143 | G80: 154 | H80: 154 | I80: ST | J80: 墨西哥 | K80: Benfica | L80: 乙级 | M80: 4 | N80: 5 | O80: 5 | P80: 5 | Q80: 0.07 | R80: 0.35 | S80: 4.5 | U80: 0
B81: 70104691 | C81: 存档没有 | D81: Orhan Nahırcı | E81: 25 | F81: 100 | G81: 100 | H81: 115 | I81: DM/DC | J81: 土耳其 | K81: Benfica | L81: 乙级 | M81: 1 | N81: 1 | O81: 2 | P81: 1 | Q81: 0.1 | R81: 0.1 | S81: 1.5 | U81: 0
B82: 76038475 | C82: 存档没有 | D82: Jefferson Lerma | E82: 30 | F82: 138 | G82: 138 | H82: 148 | I82: DM/MC | J82: 0 | K82: Celtic | L82: 甲级 | M82: 4 | N82: 4 | O82: 5 | P82: 4 | Q82: 0.07 | R82: 0.28 | S82: 4 | U82: 0
B83: 2000506319 | C83: 存档没有 | D83: Enea Bernasconi | E83: 16 | F83: 40 | G83: 40 | H83: 76 | I83: D C | K83: Como | L83: 乙级 | M83: 1 | N83: 1 | O83: 1 | P83: 1 | Q83: 0.1 | R83: 0.1 | S83: 1 | U83: 0
B84: 76047347 | C84: 存档没有 | D84: Luis Sinisterra | E84: 26 | F84: 140 | G84: 140 | H84: 152 | I84: AM/RL | J84: 哥伦比亚 | K84: CQ TL Loong | L84: 甲级 | M84: 4 | N84: 4 | O84: 5 | P84: 4 | Q84: 0.07 | R84: 0.28 | S84: 4 | U84: 0
B85: 27014576 | C85: 存档没有 | D85: Frederik Riis Rønnow | E85: 32 | F85: 143 | G85: 143 | H85: 145 | I85: GK | J85: 丹麦 | K85: Crystal Palace | L85: 甲级 | M85: 4 | N85: 4 | O85: 5 | P85: 4 | Q85: 0.07 | R85: 0.28 | S85: 4 | U85: 0
B86: 29147447 | C86: 存档没有 | D86: Matty Cash | E86: 27 | F86: 143 | G86: 143 | H86: 148 | I86: D/WB/R | J86: 0 | K86: Crystal Palace | L86: 甲级 | M86: 4 | N86: 4 | O86: 5 | P86: 4 | Q86: 0.07 | R86: 0.28 | S86: 4 | U86: 0
B87: 13181623 | C87: 存档没有 | D87: Pathé Ciss | E87: 31 | F87: 142 | G87: 142 | H87: 142 | I87: DM/MC | J87: 0 | K87: Crystal Palace | L87: 甲级 | M87: 4 | N87: 4 | O87: 4 | P87: 4 | Q87: 0.07 | R87: 0.28 | S87: 4 | U87: 0
B88: 16130398 | C88: 存档没有 | D88: Philipp Lienhart | E88: 28 | F88: 142 | G88: 142 | H88: 147 | I88: D/C | J88: 奥地利 | K88: Crystal Palace | L88: 甲级 | M88: 4 | N88: 4 | O88: 5 | P88: 4 | Q88: 0.07 | R88: 0.28 | S88: 4 | U88: 0
B89: 71099066 | C89: 存档没有 | D89: Artem Dovbyk | E89: 28 | F89: 143 | G89: 143 | H89: 150 | I89: ST | J89: 乌克兰 | K89: Eintracht Frankfurt | L89: 甲级 | M89: 4 | N89: 4 | O89: 5 | P89: 4 | Q89: 0.07 | R89: 0.28 | S89: 4 | U89: 0
B90: 27069975 | C90: 存档没有 | D90: Joachim Andersen | E90: 29 | F90: 144 | G90: 144 | H90: 151 | I90: D/C | J90: 丹麦 | K90: Eintracht Frankfurt | L90: 甲级 | M90: 4 | N90: 4 | O90: 5 | P90: 4 | Q90: 0.07 | R90: 0.28 | S90: 4 | U90: 0
B91: 43201830 | C91: 存档没有 | D91: Lucas Torreira | E91: 29 | F91: 150 | G91: 150 | H91: 155 | I91: DM/M C | K91: Eintracht Frankfurt | L91: 甲级 | M91: 5 | N91: 5 | O91: 6 | P91: 5 | Q91: 0.07 | R91: 0.35 | S91: 5 | U91: 0
B92: 19371031 | C92: 存档没有 | D92: João Gomes | E92: 24 | F92: 138 | G92: 138 | H92: 163 | I92: DM/M C | K92: Leeds | L92: 乙级 | M92: 4 | N92: 4 | O92: 6 | P92: 5 | Q92: 0.09 | R92: 0.45 | S92: 5 | U92: 0
B93: 37039829 | C93: 存档没有 | D93: Kenny Tete | E93: 29 | F93: 140 | G93: 140 | H93: 140 | I93: D/WB R | K93: Leeds | L93: 乙级 | M93: 4 | N93: 4 | O93: 4 | P93: 4 | Q93: 0.07 | R93: 0.28 | S93: 4 | U93: 0
B94: 49053443 | C94: 存档没有 | D94: Lorenz Assignon | E94: 25 | F94: 134 | G94: 134 | H94: 140 | I94: D/WB/R | J94: 0 | K94: Leicester | L94: 乙级 | M94: 3 | N94: 3 | O94: 4 | P94: 3 | Q94: 0.07 | R94: 0.21 | S94: 3.5 | U94: 0
B95: 48037152 | C95: 存档没有 | D95: Ibrahima Sissoko | E95: 27 | F95: 130 | G95: 130 | H95: 137 | I95: DM/MC | J95: 0 | K95: Liverpool | L95: 超级 | M95: 3 | N95: 3 | O95: 4 | P95: 3 | Q95: 0.07 | R95: 0.21 | S95: 3 | U95: 0
B96: 2000252921 | C96: 存档没有 | D96: Lamine Fanne | E96: 21 | F96: 115 | G96: 115 | H96: 145 | I96: DM/MC | J96: 0 | K96: Newcastle | L96: 甲级 | M96: 2 | N96: 2 | O96: 5 | P96: 3.5 | Q96: 0.07 | R96: 0.245 | S96: 3.5 | U96: 30
B97: 2000214136 | C97: 存档没有 | D97: George Ilenikhena | E97: 18 | F97: 117 | G97: 117 | H97: 143 | I97: ST | J97: 法国 | K97: Nottm Forest | L97: 超级 | M97: 2 | N97: 2 | O97: 4 | P97: 3 | Q97: 0.07 | R97: 0.21 | S97: 3 | U97: 26
B98: 49043189 | C98: 存档没有 | D98: Georges Mikautadze | E98: 24 | F98: 147 | G98: 147 | H98: 151 | I98: ST | J98: 格鲁吉亚 | K98: Nottm Forest | L98: 超级 | M98: 5 | N98: 5 | O98: 5 | P98: 5 | Q98: 0.07 | R98: 0.35 | S98: 5 | U98: 0
B99: 2000391038 | C99: 存档没有 | D99: Jacob Ambæk | E99: 17 | F99: 107 | G99: 107 | H99: 150 | I99: ST | J99: 丹麦 | K99: Nottm Forest | L99: 超级 | M99: 1 | N99: 1 | O99: 5 | P99: 3 | Q99: 0.07 | R99: 0.21 | S99: 3 | U99: 43
A100: 伪名 | B100: 2000338014 | C100: 存档没有 | D100: Justin Lerma | E100: 17 | F100: 103 | G100: 103 | H100: 168 | I100: AM/C | J100: 0 | K100: Nottm Forest | L100: 超级 | M100: 1 | N100: 1 | O100: 7 | P100: 4 | Q100: 0.11 | R100: 0.44 | S100: 4 | T100: 伪名 | U100: 65
B101: 2000378240 | C101: 存档没有 | D101: José Neto | E101: 17 | F101: 98 | G101: 98 | H101: 164 | K101: Nottm Forest | L101: 超级 | M101: 1 | N101: 1 | O101: 6 | P101: 3.5 | Q101: 0.09 | R101: 0.315 | S101: 3.5 | U101: 66
B102: 13224511 | C102: 存档没有 | D102: Olakunle Olusegun | E102: 23 | F102: 122 | G102: 122 | H102: 132 | I102: M/AM RL | K102: RB Leipzig | L102: 甲级 | M102: 2 | N102: 2 | O102: 3 | P102: 2 | Q102: 0.07 | R102: 0.14 | S102: 2.5 | U102: 0
...

Sheet 26第一次随潜档
A1: 姓名 | B1: 位置 | C1: 国籍 | D1: CA | E1: PA | F1: 年龄
A2: Lamine Yamal | B2: M/AM R | C2: Spain,Morocco,Equatorial Guinea | D2: 165 | E2: 175 | F2: 17
A3: Endrick | B3: S R | C3: Brazil | D3: 142 | E3: 183 | F3: 18
A4: Désiré Doué | B4: AM RLC | C4: France,Ivory Coast | D4: 156 | E4: 171 | F4: 20
A5: Leny Yoro | B5: D C | C5: France | D5: 142 | E5: 178 | F5: 19
A6: Ethan Nwaneri | B6: M/AM RLC | C6: England,Nigeria | D6: 140 | E6: 177 | F6: 18
A7: Pau Cubarsí | B7: D C | C7: Spain | D7: 154 | E7: 174 | F7: 18
A8: Kenan Yıldız | B8: AM RLC | C8: Türkiye,Germany | D8: 156 | E8: 171 | F8: 20
A9: Savinho | B9: AM RL | C9: Brazil | D9: 153 | E9: 165 | F9: 21
A10: Ibrahim Mbaye | B10: AM RL | C10: France | D10: 115 | E10: 169 | F10: 17
A11: Kennet Eichhorn | B11: DM/M C | C11: Germany | D11: 102 | E11: 168 | F11: 15
A12: Jeremy Monga | B12: AM LC | C12: England,Democratic Republic of Congo | D12: 124 | E12: 166 | F12: 15
A13: Nathan De Cat | B13: DM/M C | C13: Belgium | D13: 115 | E13: 160 | F13: 16
... A65: Kaiser Barreto | B65: D R | C65: Brazil,England | D65: 48 | E65: 110 | F65: 15

Sheet 球员库
A1: FM26数据库
A2: 编​号 | B2: 姓​名 | D2: 年​龄 | E2: 初始CA | F2: 当前CA | G2: 当前PA | H2: 位置 | I2: 国籍 | J2: 俱乐部 | K2: 身高 | L2: 体重
A3: 2000130977 | B3: Antoine Mendy | D3: 21 | E3: 110 | F3: 110 | G3: 130 | H3: D/RC | I3: 塞内加尔 | J3: A. Madrid
A4: 43028661 | B4: Antonio Donnarumma | D4: 34 | E4: 106 | F4: 106 | G4: 114 | H4: GK | I4: 意大利 | J4: A. Madrid
A5: 43500130 | B5: Diego Coppola | D5: 21 | E5: 136 | F5: 136 | G5: 162 | H5: D/C | I5: 意大利 | J5: A. Madrid
A6: 2000338371 | B6: Francesco Camarda | D6: 17 | E6: 115 | F6: 115 | G6: 151 | H6: ST | I6: 意大利 | J6: A. Madrid
A7: 2000385385 | B7: Gabriel Mec | D7: 17 | E7: 100 | F7: 100 | G7: 165 | H7: AM/RLC | I7: 巴西 | J7: A. Madrid
A8: 2000208439 | B8: Gabriel Moscardo | D8: 19 | E8: 123 | F8: 123 | G8: 155 | H8: DM | I8: 巴西 | J8: A. Madrid
A9: 14030119 | B9: Gerónimo Rulli | D9: 33 | E9: 143 | F9: 143 | G9: 159 | H9: GK | I9: 阿根廷 | J9: A. Madrid
A10: 73201428 | B10: Guéla Doué | D10: 22 | E10: 131 | F10: 131 | G10: 149 | H10: D/RC | I10: 科特迪瓦 | J10: A. Madrid
A11: 53160749 | B11: Igoh Ogbu | D11: 25 | E11: 144 | F11: 144 | G11: 148 | H11: D/C | I11: 尼日利亚 | J11: A. Madrid
A12: 2000275657 | B12: Jay Robinson | D12: 18 | E12: 119 | F12: 119 | G12: 165 | H12: AM/L | I12: 英格兰 | J12: A. Madrid
A13: 2000115205 | B13: Jeanuël Belocian | D13: 20 | E13: 125 | F13: 125 | G13: 155 | H13: D/LC | I13: 法国 | J13: A. Madrid
A14: 53143395 | B14: Jørgen Strand Larsen | D14: 25 | E14: 140 | F14: 140 | G14: 150 | H14: ST | I14: 丹麦 | J14: A. Madrid
... A89: 2000207199 | B89: Souza | D89: 19 | E89: 120 | F89: 120 | G89: 160 | H89: D/L | I89: 巴西 | J89: Arsenal
A90: 2000187717 | B90: Tommy Watson | D90: 19 | E90: 122 | F90: 122 | G90: 160 | H90: AM/RL | J90: Arsenal
A91: 2000202295 | B91: Victor Froholdt | D91: 19 | E91: 147 | F91: 147 | G91: 157 | H91: AM/RLC | J91: Arsenal
A92: 2000179714 | B92: Yoram Zague | D92: 19 | E92: 112 | F92: 112 | G92: 160 | H92: D/WB/R | J92: Arsenal
A93: 67153376 | B93: Álex Grimaldo | D93: 29 | E93: 160 | F93: 160 | G93: 162 | H93: D/WB/L | I93: 西班牙 | J93: AS Roma
A94: 18097159 | B94: Alexis Saelemaekers | D94: 26 | E94: 151 | F94: 151 | G94: 153 | H94: D/WB/M/AM/R | I94: 比利时 | J94: AS Roma
A95: 83320135 | B95: António Silva | D95: 21 | E95: 141 | F95: 141 | G95: 154 | H95: D/C | I95: 葡萄牙 | J95: AS Roma
A96: 29217603 | B96: Archie Brown | D96: 23 | E96: 124 | F96: 124 | G96: 142 | H96: D/WB/L | J96: AS Roma
A97: 2000103330 | B97: Can Uzun | D97: 19 | E97: 136 | F97: 136 | G97: 174 | H97: M/AMC/ST | I97: 土耳其 | J97: AS Roma
A98: 2000369658 | B98: Davinchi | D98: 17 | E98: 110 | F98: 110 | G98: -85 | H98: D/WB/L | I98: 西班牙 | J98: AS Roma
A99: 2000027719 | B99: Diego Moreira | D99: 20 | E99: 138 | F99: 138 | G99: 161 | H99: AM/RL | J99: AS Roma
A100: 2000263999 | B100: Estêvão | D100: 18 | E100: 132 | F100: 132 | G100: 187 | H100: AM/RC | I100: 巴西 | J100: AS Roma
A101: 2000183231 | B101: Franco Mastantuono | D101: 17 | E101: 127 | F101: 127 | G101: 171 | H101: AM/RLC | I101: 阿根廷 | J101: AS Roma
A102: 43252073 | B102: Gianluigi Donnarumma | D102: 26 | E102: 167 | F102: 167 | G102: 170 | H102: GK | I102: 意大利 | J102: AS Roma
A103: 71113679 | B103: Illia Zabarnyi | D103: 22 | E103: 149 | F103: 149 | G103: 170 | H103: D/C | I103: 乌克兰 | J103: AS Roma
A104: 2000214886 | B104: Jacobo Ramón | D104: 20 | E104: 130 | F104: 130 | G104: 150 | H104: D/C | I104: 西班牙 | J104: AS Roma
A105: 91119700 | B105: Jonathan Tah | D105: 29 | E105: 156 | F105: 156 | G105: 158 | H105: D/RC | I105: 德国 | J105: AS Roma
A106: 91175718 | B106: Leo Weinkauf | D106: 29 | E106: 112 | F106: 112 | G106: 122 | H106: GK | I106: 德国 | J106: AS Roma
A107: 85103818 | B107: Ludovic Ajorque | D107: 31 | E107: 137 | F107: 137 | G107: 140 | H107: ST | J107: AS Roma
A108: 54009099 | B108: Łukasz Skorupski | D108: 34 | E108: 145 | F108: 145 | G108: 146 | H108: GK | I108: 波兰 | J108: AS Roma
A109: 28108033 | B109: Marc Guéhi | D109: 25 | E109: 156 | F109: 156 | G109: 168 | H109: D/C | I109: 英格兰 | J109: AS Roma
A110: 2000093091 | B110: Nestory Irankunda | D110: 19 | E110: 113 | F110: 113 | G110: 160 | H110: AM/RL | I110: 澳大利亚 | J110: AS Roma
A111: 28104124 | B111: Trent Alexander-Arnold | D111: 26 | E111: 163 | F111: 163 | G111: 174 | H111: D/WB/DM RC | I111: 英格兰 | J111: AS Roma
A112: 2000168014 | B112: Abdukodir Khusanov | D112: 21 | E112: 140 | F112: 140 | G112: 173 | H112: D/C | I112: 乌兹别克斯坦 | J112: Aston Villa
A113: 13211267 | B113: Abdul Fatawu | D113: 21 | E113: 137 | F113: 137 | G113: 160 | H113: M/AMRLC | I113: 加纳 | J113: Aston Villa
A114: 91207274 | B114: Amadou Onana | D114: 23 | E114: 145 | F114: 145 | G114: 160 | H114: DM/MC | I114: 比利时 | J114: Aston Villa
A115: 18110528 | B115: Charles De Ketelaere | D115: 24 | E115: 150 | F115: 150 | G115: 160 | H115: AMC/ST | I115: 比利时 | J115: Aston Villa
A116: 67283140 | B116: Filip Jörgensen | D116: 23 | E116: 144 | F116: 144 | G116: 169 | H116: GK | I116: 丹麦 | J116: Aston Villa
A117: 93065006 | B117: Gabriel Gudmundsson | D117: 26 | E117: 132 | F117: 132 | G117: 138 | H117: D/WB/M/AM/L | I117: 瑞典 | J117: Aston Villa
A118: 43500245 | B118: Giovanni Fabbian | D118: 22 | E118: 134 | F118: 134 | G118: 152 | H118: M/AMC | I118: 西班牙 | J118: Aston Villa
A119: 16003924 | B119: Heinz Lindner | D119: 35 | E119: 111 | F119: 111 | G119: 115 | H119: GK | I119: 奥地利 | J119: Aston Villa
... A130: 49054420 | B130: Youte | D130: 23 | E130: 122 | F130: 122 | G130: 138 | H130: D/C | I130: 德国 | J130: Aston Villa
A131: 2000166604 | B131: Alex Freeman | D131: 20 | E131: 113 | F131: 113 | G131: 160 | H131: D/R | J131: Atalanta
A132: 24048100 | B132: Dani Olmo | D132: 27 | E132: 165 | F132: 165 | G132: 170 | H132: M/AMRLC | I132: 西班牙 | J132: Atalanta
A133: 43391659 | B133: Elia Caprile | D133: 23 | E133: 138 | F133: 138 | G133: 152 | H133: GK | I133: 意大利 | J133: Atalanta
A134: 48032198 | B134: Evan N'Dicka | D134: 25 | E134: 154 | F134: 154 | G134: 158 | H134: D/LC | I134: 科特迪瓦 | J134: Atalanta
A135: 28049320 | B135: Harry Kane | D135: 31 | E135: 188 | F135: 188 | G135: 190 | H135: ST | I135: 英格兰 | J135: Atalanta
A136: 67153377 | B136: Jose Suarez | D136: 29 | E136: 102 | F136: 102 | G136: 120 | H136: GK | I136: 西班牙 | J136: Atalanta
A137: 2000241413 | B137: Kirill Glebov | D137: 19 | E137: 120 | F137: 120 | G137: 160 | H137: AM/RLC | J137: Atalanta
A138: 36096824 | B138: Kostas Tsimikas | D138: 29 | E138: 149 | F138: 149 | G138: 159 | H138: D/WB/L | I138: 希腊 | J138: Atalanta
A139: 2000098016 | B139: Luca Lipani | D139: 20 | E139: 114 | F139: 114 | G139: 160 | H139: DM/MC | I139: 意大利 | J139: Atalanta
A140: 2000298715 | B140: Mikey Moore | D140: 17 | E140: 124 | F140: 124 | G140: 167 | H140: AM/RLC | J140: Atalanta
A141: 2000466343 | B141: Olivier Mambwa | D141: 16 | E141: 89 | F141: 89 | G141: 160 | H141: D/L | J141: Atalanta
A142: 57178516 | B142: Radu Drăguşin | D142: 23 | E142: 141 | F142: 141 | G142: 164 | H142: D/RC | I142: 罗马尼亚 | J142: Atalanta
A143: 14094572 | B143: Rodrigo Bentancur | D143: 28 | E143: 150 | F143: 150 | G143: 164 | H143: DM/MC | I143: 乌拉圭 | J143: Atalanta
A144: 2000045246 | B144: Ruben van Bommel | D144: 20 | E144: 128 | F144: 128 | G144: 148 | H144: M/AMRLC/ST | I144: 荷兰 | J144: Atalanta
A145: 2000190479 | B145: Sam Amo-Ameyaw | D145: 19 | E145: 122 | F145: 122 | G145: 168 | H145: ST | I145: 英格兰 | J145: Atalanta
A146: 83283239 | B146: Tiago Santos | D146: 23 | E146: 140 | F146: 140 | G146: 152 | H146: D/R | I146: 葡萄牙 | J146: Atalanta
A147: 37050603 | B147: Albert Guðmundsson | D147: 28 | E147: 141 | F147: 141 | G147: 149 | H147: AMRLC/ST | I147: 冰岛 | J147: Barcelona
A148: 67296654 | B148: Alejandro Balde | D148: 21 | E148: 153 | F148: 153 | G148: 170 | H148: D/WB/M/AM/L | I148: 西班牙 | J148: Barcelona
A149: 67221484 | B149: Iñaki Peña | D149: 26 | E149: 138 | F149: 138 | G149: 150 | H149: GK | I149: 西班牙 | J149: Barcelona
A150: 27069975 | B150: Joachim Andersen | D150: 29 | E150: 144 | F150: 144 | G150: 151 | H150: D/C | I150: 丹麦 | J150: Barcelona
A151: 67277675 | B151: Joan García | D151: 24 | E151: 155 | F151: 155 | G151: 175 | H151: GK | I151: 西班牙 | J151: Barcelona
A152: 2000297306 | B152: Jofre Torrents | D152: 18 | E152: 115 | F152: 115 | G152: 164 | H152: D/WB/L | I152: 西班牙 | J152: Barcelona
A153: 2000079847 | B153: José Córdoba | D153: 24 | E153: 116 | F153: 116 | G153: 145 | H153: D/LC | I153: 巴拿马 | J153: Barcelona
A154: 16147659 | B154: Konrad Laimer | D154: 28 | E154: 152 | F154: 152 | G154: 155 | H154: DR/DM/MC | I154: 奥地利 | J154: Barcelona | K154: 180
A155: 2000256231 | B155: Lamine Yamal | D155: 18 | E155: 165 | F155: 165 | G155: 175 | H155: AM/RL | I155: 西班牙 | J155: Barcelona
A156: 78074598 | B156: Leonardo Fernández | D156: 26 | E156: 129 | F156: 129 | G156: 142 | H156: AM/RC | I156: 乌拉圭 | J156: Barcelona
A157: 2000295603 | B157: Marc Bernal | D157: 18 | E157: 125 | F157: 125 | G157: 151 | H157: DM/MC | I157: 西班牙 | J157: Barcelona
A158: 2000058198 | B158: Marc Casadó | D158: 21 | E158: 148 | F158: 148 | G158: 160 | H158: DM/MC | I158: 西班牙 | J158: Barcelona
A159: 2000069643 | B159: Mohamed Amoura | D159: 25 | E159: 148 | F159: 148 | G159: 153 | H159: ST | I159: 阿尔及利亚 | J159: Barcelona
A160: 13224511 | B160: Olakunle Olusegun | D160: 23 | E160: 122 | F160: 122 | G160: 132 | H160: AM/RL | I160: 尼日利亚 | J160: Barcelona
A161: 2000296497 | B161: Pau Cubarsí | D161: 18 | E161: 154 | F161: 154 | G161: 174 | H161: D/C | I161: 西班牙 | J161: Barcelona
A162: 2000088490 | B162: Roony Bardghji | D162: 18 | E162: 121 | F162: 121 | G162: 145 | H162: AM/R | I162: 瑞典 | J162: Barcelona | K162: 173
A163: 14236223 | B163: Santiago Castro | D163: 20 | E163: 142 | F163: 142 | G163: 163 | H163: AMRL/ST | I163: 阿根廷 | J163: Barcelona
A164: 28112993 | B164: Tariq Lamptey | D164: 24 | E164: 136 | F164: 136 | G164: 153 | H164: D/WB/R | I164: 加纳 | J164: Barcelona
A165: 19058734 | B165: Alisson | D165: 32 | E165: 180 | F165: 180 | G165: 182 | H165: GK | I165: 巴西 | J165: Bayer 04
A166: 48042658 | B166: Bryan Mbeumo | D166: 25 | E166: 155 | F166: 155 | G166: 160 | H166: M/AMRL/ST | I166: 喀麦隆 | J166: Bayer 04
A167: 2000385886 | B167: Diego León | D167: 18 | E167: 101 | F167: 101 | G167: 160 | H167: D/WB/L | I167: 巴拉圭 | J167: Bayer 04
A168: 83105845 | B168: Diogo Dalot | D168: 26 | E168: 146 | F168: 146 | G168: 155 | H168: D/WB/RL | I168: 葡萄牙 | J168: Bayer 04
A169: 29123128 | B169: Dominic Calvert-Lewin | D169: 28 | E169: 137 | F169: 137 | G169: 163 | H169: ST | I169: 英格兰 | J169: Bayer 04
A170: 37060922 | B170: Joshua Zirkzee | D170: 24 | E170: 143 | F170: 143 | G170: 160 | H170: ST | I170: 荷兰 | J170: Bayer 04
A171: 28116558 | B171: Largie Ramazani | D171: 24 | E171: 134 | F171: 134 | G171: 155 | H171: AMRL/ST | I171: 比利时 | J171: Bayer 04
A172: 14167329 | B172: Lisandro Martínez | D172: 27 | E172: 152 | F172: 152 | G172: 160 | H172: D/LC | I172: 阿根廷 | J172: Bayer 04
A173: 2000153212 | B173: Liu-Shao Ziyang | D173: 19 | E173: 90 | F173: 90 | G173: 120 | H173: GK | I173: 中国 | J173: Bayer 04
A174: 29076105 | B174: Luke Shaw | D174: 30 | E174: 152 | F174: 152 | G174: 162 | H174: D/WB/LC | I174: 英格兰 | J174: Bayer 04
... A182: 91137493 | B182: Waldemar Anton | D182: 28 | E182: 146 | F182: 146 | G182: 150 | H182: D/C | I182: 德国 | J182: Bayer 04
A183: 83282675 | B183: Alexsandro Ribeiro | D183: 25 | E183: 144 | F183: 144 | G183: 154 | H183: D/C | J183: Benfica
A184: 14110846 | B184: Exequiel Palacios | D184: 26 | E184: 156 | F184: 156 | G184: 160 | H184: DM/MC | I184: 阿根廷 | J184: Benfica
A185: 83137935 | B185: Francisco Trincão | D185: 25 | E185: 154 | F185: 154 | G185: 165 | H185: AM/RLC | I185: 葡萄牙 | J185: Benfica
A186: 39060464 | B186: Hákon Arnar Haraldsson | D186: 22 | E186: 139 | F186: 139 | G186: 157 | H186: M/AMLC | I186: 冰岛 | J186: Benfica
A187: 2000054508 | B187: Jaden Slory | D187: 20 | E187: 125 | F187: 125 | G187: 160 | H187: AM/R | J187: Benfica
A188: 2000056845 | B188: James Beadle | D188: 21 | E188: 120 | F188: 120 | G188: 160 | H188: GK | J188: Benfica
A189: 2000229718 | B189: Jon Martín | D189: 19 | E189: 127 | F189: 127 | G189: 166 | H189: D/C | I189: 西班牙 | J189: Benfica
A190: 2000019418 | B190: Jorge Pascual | D190: 20 | E190: 125 | F190: 125 | G190: 160 | H190: ST | I190: 荷兰 | J190: Benfica
A191: 92039023 | B191: Joshua Kimmich | D191: 30 | E191: 177 | F191: 177 | G191: 183 | H191: D/DM/M/RC | I191: 德国 | J191: Benfica
...

Sheet 球队名
I10: As Roma
I11: Aston Villa
I12: Barcelona
I13: Bayer 04
I14: Nottm Forest
I15: Borussia Dortmund
I16: Eintracht Frankfurt
I17: Inter
I18: Juventus
I19: Liverpool
I20: Man UFC
I21: Newcastle
... I65: Zhejiang
